Workbook

Sheet Dinâmica
A3: Rótulos de Linha | B3: Soma de Valor em Atraso (R$) | C3: %
A4: 1 a 30 dias | B4: 848207.35 | C4: =GETPIVOTDATA("Valor em Atraso (R$)",$A$3,"Aging Alexandria","1 a 30 dias")/GETPIVOTDATA("Valor em Atraso (R$)",$A$3) -> 0.49991494
A5: 31 a 60 dias | B5: 390367.3 | C5: =GETPIVOTDATA("Valor em Atraso (R$)",$A$3,"Aging Alexandria","31 a 60 dias")/GETPIVOTDATA("Valor em Atraso (R$)",$A$3) -> 0.23007399
A6: 61 a 90 dias | B6: 182066.03 | C6: =GETPIVOTDATA("Valor em Atraso (R$)",$A$3,"Aging Alexandria","61 a 90 dias")/GETPIVOTDATA("Valor em Atraso (R$)",$A$3) -> 0.10730575
A7: Maior que 90 | B7: 276062.65 | C7: =GETPIVOTDATA("Valor em Atraso (R$)",$A$3,"Aging Alexandria","Maior que 90")/GETPIVOTDATA("Valor em Atraso (R$)",$A$3) -> 0.16270532
A8: (vazio)
A9: Total Geral | B9: 1696703.3

Sheet Base EDP
A1: ID Cobranca | B1: Status Fat | C1: Núm Inst | D1: CNPJ / CPF | E1: Razão Social / Nome | F1: Endereço | G1: ID do Contrato | H1: referência | I1: Mês de Referência | J1: Valor da Cobrança (R$) | K1: Vlr Adicional - Total | L1: Valor em Atraso (R$) | M1: Valor Pago (R$) | N1: Invoice Num | O1: Data Emissão | P1: Data Vencimento | Q1: Data Pagamento | R1: Dias Atraso | S1: Tp Inscr | T1: STATUS EDP | U1: STATUS ALEXANDRIA | V1: cod venda | W1: status | X1: usina_pg | Y1: Status FAT - LF | Z1: FINAL | AA1: Nome | AB1: Representante | AC1: Tipo Medição | AD1: Fat.Agrup. | AE1: Aging edp | AF1: UUID | AG1: Vencimento Lex | AH1: Aging Alexandria | AI1: AVISO_VENCIMENTO_2DIAS | AJ1: AVISO_VENCIMENTO_5DIAS | AK1: FATURA_ENVIO | AL1: FATURA_INADIMPLENCIA | AM1: FATURA_VENCE_HOJE | AN1: FATURA_VENCIDA_10_DIAS | AO1: FATURA_VENCIDA_14_DIAS | AP1: FATURA_VENCIDA_17_DIAS | AQ1: FATURA_VENCIDA_21_DIAS | AR1: FATURA_VENCIDA_25_DIAS | AS1: FATURA_VENCIDA_30_DIAS | AT1: FATURA_VENCIDA_3_DIAS | AU1: FATURA_VENCIDA_5_DIAS | AV1: FATURA_VENCIDA_7_DIAS
A2: COB-243058 | B2: Faturado | C2: 5315550 | D2: 40261800000180 | E2: VENTURA SERVICOS MEDICOS LTDA | F2: Rua Doutor José Peroba 325 SL-1406 Stiep Salvador BA 41770-235 | G2: ADE-17650-X3P0X6 | H2: 46082 | I2: 202603 | J2: 248.50894 | L2: 248.51 | N2: 90520454 | O2: 46101 | P2: 46111 | R2: 15 | S2: 1 - CNPJ | T2: Em aberto - Vencido | U2: Em aberto - Vencido | V2: U41JLVB | W2: 6 | X2: false | Y2: 6 | Z2: Em aberto - Vencido | AA2: ASSOCIAÇÃO BA ? L1 | AB2: 35.686.965/0001-64 - ALEXANDRIA TECH | AC2: Estimado | AE2: 1 a 30 dias | AF2: 8522cc6f-66f1-4a8e-99bf-7b04f8b2a8aa | AG2: 46111 | AH2: 1 a 30 dias | AI2: =_xlfn.XLOOKUP(Tabela5[[#This Row],[UUID]],Planilha2!$A:$A,Planilha2!B:B,"") -> 1 | AJ2: =_xlfn.XLOOKUP(Tabela5[[#This Row],[UUID]],Planilha2!$A:$A,Planilha2!C:C,"") -> 1 | AK2: =_xlfn.XLOOKUP(Tabela5[[#This Row],[UUID]],Planilha2!$A:$A,Planilha2!D:D,"") -> 8 | AL2: =_xlfn.XLOOKUP(Tabela5[[#This Row],[UUID]],Planilha2!$A:$A,Planilha2!E:E,"") -> 0 | AM2: =_xlfn.XLOOKUP(Tabela5[[#This Row],[UUID]],Planilha2!$A:$A,Planilha2!F:F,"") -> 1 | AN2: =_xlfn.XLOOKUP(Tabela5[[#This Row],[UUID]],Planilha2!$A:$A,Planilha2!G:G,"") -> 1 | AO2: =_xlfn.XLOOKUP(Tabela5[[#This Row],[UUID]],Planilha2!$A:$A,Planilha2!H:H,"") -> 1 | AP2: =_xlfn.XLOOKUP(Tabela5[[#This Row],[UUID]],Planilha2!$A:$A,Planilha2!I:I,"") -> 0 | AQ2: =_xlfn.XLOOKUP(Tabela5[[#This Row],[UUID]],Planilha2!$A:$A,Planilha2!J:J,"") -> 0 | AR2: =_xlfn.XLOOKUP(Tabela5[[#This Row],[UUID]],Planilha2!$A:$A,Planilha2!K:K,"") -> 0 | AS2: =_xlfn.XLOOKUP(Tabela5[[#This Row],[UUID]],Planilha2!$A:$A,Planilha2!L:L,"") -> 0 | AT2: =_xlfn.XLOOKUP(Tabela5[[#This Row],[UUID]],Planilha2!$A:$A,Planilha2!M:M,"") -> 1 | AU2: =_xlfn.XLOOKUP(Tabela5[[#This Row],[UUID]],Planilha2!$A:$A,Planilha2!N:N,"") -> 1 | AV2: =_xlfn.XLOOKUP(Tabela5[[#This Row],[UUID]],Planilha2!$A:$A,Planilha2!O:O,"") -> 1
A3: COB-243042 | B3: Faturado | C3: 648143 | D3: 976482568 | E3: GERALDO CARDOSO DOS SANTOS | F3: RUA MONTE DAS OLIVEIRAS 34 Alto do Cristo Caetité BA 46400000 | G3: ADE-17365-S4H7T6 | H3: 46082 | I3: 202603 | J3: 123.18638 | L3: 123.19 | N3: 90520370 | O3: 46101 | P3: 46111 | R3: 15 | S3: 2 - CPF | T3: Em aberto - Vencido | U3: Em aberto - Vencido | V3: 77JE70K | W3: 6 | X3: false | Y3: 6 | Z3: Em aberto - Vencido | AA3: ASSOCIAÇÃO BA ? L1 | AB3: 35.686.965/0001-64 - ALEXANDRIA TECH | AC3: Estimado | AE3: 1 a 30 dias | AF3: 60e65356-e6f9-483a-ac37-ce26512ba3ff | AG3: 46111 | AH3: 1 a 30 dias | AI3: =_xlfn.XLOOKUP(Tabela5[[#This Row],[UUID]],Planilha2!$A:$A,Planilha2!B:B,"") -> 1 | AJ3: =_xlfn.XLOOKUP(Tabela5[[#This Row],[UUID]],Planilha2!$A:$A,Planilha2!C:C,"") -> 1 | AK3: =_xlfn.XLOOKUP(Tabela5[[#This Row],[UUID]],Planilha2!$A:$A,Planilha2!D:D,"") -> 1 | AL3: =_xlfn.XLOOKUP(Tabela5[[#This Row],[UUID]],Planilha2!$A:$A,Planilha2!E:E,"") -> 0 | AM3: =_xlfn.XLOOKUP(Tabela5[[#This Row],[UUID]],Planilha2!$A:$A,Planilha2!F:F,"") -> 1 | AN3: =_xlfn.XLOOKUP(Tabela5[[#This Row],[UUID]],Planilha2!$A:$A,Planilha2!G:G,"") -> 1 | AO3: =_xlfn.XLOOKUP(Tabela5[[#This Row],[UUID]],Planilha2!$A:$A,Planilha2!H:H,"") -> 1 | AP3: =_xlfn.XLOOKUP(Tabela5[[#This Row],[UUID]],Planilha2!$A:$A,Planilha2!I:I,"") -> 0 | AQ3: =_xlfn.XLOOKUP(Tabela5[[#This Row],[UUID]],Planilha2!$A:$A,Planilha2!J:J,"") -> 0 | AR3: =_xlfn.XLOOKUP(Tabela5[[#This Row],[UUID]],Planilha2!$A:$A,Planilha2!K:K,"") -> 0 | AS3: =_xlfn.XLOOKUP(Tabela5[[#This Row],[UUID]],Planilha2!$A:$A,Planilha2!L:L,"") -> 0 | AT3: =_xlfn.XLOOKUP(Tabela5[[#This Row],[UUID]],Planilha2!$A:$A,Planilha2!M:M,"") -> 1 | AU3: =_xlfn.XLOOKUP(Tabela5[[#This Row],[UUID]],Planilha2!$A:$A,Planilha2!N:N,"") -> 1 | AV3: =_xlfn.XLOOKUP(Tabela5[[#This Row],[UUID]],Planilha2!$A:$A,Planilha2!O:O,"") -> 1
A4: COB-243024 | B4: Faturado | C4: 560430 | D4: 85891658500 | E4: FLAVIANE ARAUJO MOREIRA | F4: RUA E 20 SANTA TEREZA Brumado BA 46100-000 | G4: ADE-17197-V7Q1L0 | H4: 46082 | I4: 202603 | J4: 133.15522 | L4: 133.16 | N4: 90520498 | O4: 46101 | P4: 46111 | R4: 15 | S4: 2 - CPF | T4: Em aberto - Vencido | U4: Em aberto - Vencido | V4: X1AQCA7 | W4: 6 | X4: false | Y4: 6 | Z4: Em aberto - Vencido | AA4: ASSOCIAÇÃO BA ? L1 | AB4: 35.686.965/0001-64 - ALEXANDRIA TECH | AC4: Estimado | AE4: 1 a 30 dias | AF4: 1b1353ff-2679-4e66-a4e1-8e6cb9807f4d | AG4: 46111 | AH4: 1 a 30 dias | AI4: =_xlfn.XLOOKUP(Tabela5[[#This Row],[UUID]],Planilha2!$A:$A,Planilha2!B:B,"") -> 1 | AJ4: =_xlfn.XLOOKUP(Tabela5[[#This Row],[UUID]],Planilha2!$A:$A,Planilha2!C:C,"") -> 1 | AK4: =_xlfn.XLOOKUP(Tabela5[[#This Row],[UUID]],Planilha2!$A:$A,Planilha2!D:D,"") -> 1 | AL4: =_xlfn.XLOOKUP(Tabela5[[#This Row],[UUID]],Planilha2!$A:$A,Planilha2!E:E,"") -> 0 | AM4: =_xlfn.XLOOKUP(Tabela5[[#This Row],[UUID]],Planilha2!$A:$A,Planilha2!F:F,"") -> 1 | AN4: =_xlfn.XLOOKUP(Tabela5[[#This Row],[UUID]],Planilha2!$A:$A,Planilha2!G:G,"") -> 1 | AO4: =_xlfn.XLOOKUP(Tabela5[[#This Row],[UUID]],Planilha2!$A:$A,Planilha2!H:H,"") -> 1 | AP4: =_xlfn.XLOOKUP(Tabela5[[#This Row],[UUID]],Planilha2!$A:$A,Planilha2!I:I,"") -> 0 | AQ4: =_xlfn.XLOOKUP(Tabela5[[#This Row],[UUID]],Planilha2!$A:$A,Planilha2!J:J,"") -> 0 | AR4: =_xlfn.XLOOKUP(Tabela5[[#This Row],[UUID]],Planilha2!$A:$A,Planilha2!K:K,"") -> 0 | AS4: =_xlfn.XLOOKUP(Tabela5[[#This Row],[UUID]],Planilha2!$A:$A,Planilha2!L:L,"") -> 0 | AT4: =_xlfn.XLOOKUP(Tabela5[[#This Row],[UUID]],Planilha2!$A:$A,Planilha2!M:M,"") -> 1 | AU4: =_xlfn.XLOOKUP(Tabela5[[#This Row],[UUID]],Planilha2!$A:$A,Planilha2!N:N,"") -> 1 | AV4: =_xlfn.XLOOKUP(Tabela5[[#This Row],[UUID]],Planilha2!$A:$A,Planilha2!O:O,"") -> 1
A5: COB-120638 | B5: Faturado | C5: 2680126150 | D5: 6377392133 | E5: FELLIPE BITENCOURT DE OLIVEIRA | F5: RUA PAQUETA, Q. 38, L. 10-12, S/N PARQUE ARAGUARI CEP: 72880000 CIDADE OCIDENTAL GO BRASIL | G5: ADE-11135-V3G8V8 | H5: 45778 | I5: 202505 | J5: 64.47272 | L5: 64.47 | N5: 90305430 | O5: 45831 | P5: 45841 | R5: 285 | S5: 2 - CPF | T5: Em aberto - Vencido | U5: Em aberto - Vencido | V5: 632TDKU | W5: 6 | X5: false | Y5: 6 | Z5: Em aberto - Vencido | AA5: ASSOCIAÇÃO GO-L1 | AB5: 35.686.965/0001-64 - ALEXANDRIA TECH | AE5: 171 a 450 dias | AF5: ac63bd63-376f-4148-b396-b2f86a95d9a3 | AG5: 46020 | AH5: Maior que 90 | AI5: =_xlfn.XLOOKUP(Tabela5[[#This Row],[UUID]],Planilha2!$A:$A,Planilha2!B:B,"") -> 0 | AJ5: =_xlfn.XLOOKUP(Tabela5[[#This Row],[UUID]],Planilha2!$A:$A,Planilha2!C:C,"") -> 0 | AK5: =_xlfn.XLOOKUP(Tabela5[[#This Row],[UUID]],Planilha2!$A:$A,Planilha2!D:D,"") -> 1 | AL5: =_xlfn.XLOOKUP(Tabela5[[#This Row],[UUID]],Planilha2!$A:$A,Planilha2!E:E,"") -> 2 | AM5: =_xlfn.XLOOKUP(Tabela5[[#This Row],[UUID]],Planilha2!$A:$A,Planilha2!F:F,"") -> 0 | AN5: =_xlfn.XLOOKUP(Tabela5[[#This Row],[UUID]],Planilha2!$A:$A,Planilha2!G:G,"") -> 0 | AO5: =_xlfn.XLOOKUP(Tabela5[[#This Row],[UUID]],Planilha2!$A:$A,Planilha2!H:H,"") -> 0 | AP5: =_xlfn.XLOOKUP(Tabela5[[#This Row],[UUID]],Planilha2!$A:$A,Planilha2!I:I,"") -> 1 | AQ5: =_xlfn.XLOOKUP(Tabela5[[#This Row],[UUID]],Planilha2!$A:$A,Planilha2!J:J,"") -> 1 | AR5: =_xlfn.XLOOKUP(Tabela5[[#This Row],[UUID]],Planilha2!$A:$A,Planilha2!K:K,"") -> 1 | AS5: =_xlfn.XLOOKUP(Tabela5[[#This Row],[UUID]],Planilha2!$A:$A,Planilha2!L:L,"") -> 1 | AT5: =_xlfn.XLOOKUP(Tabela5[[#This Row],[UUID]],Planilha2!$A:$A,Planilha2!M:M,"") -> 0 | AU5: =_xlfn.XLOOKUP(Tabela5[[#This Row],[UUID]],Planilha2!$A:$A,Planilha2!N:N,"") -> 0 | AV5: =_xlfn.XLOOKUP(Tabela5[[#This Row],[UUID]],Planilha2!$A:$A,Planilha2!O:O,"") -> 0
A6: COB-242944 | B6: Faturado | C6: 1411413 | D6: 2086578512 | E6: MIRELIA NUNES PEREIRA | F6: RUA DA PAROQUIA 170 CENTRO Érico Cardoso BA 46180-000 | G6: ADE-16846-B0T3S5 | H6: 46082 | I6: 202603 | J6: 148.82054 | L6: 148.82 | N6: 90520399 | O6: 46101 | P6: 46111 | R6: 15 | S6: 2 - CPF | T6: Em aberto - Vencido | U6: Em aberto - Vencido | V6: O3M6EB9 | W6: 6 | X6: false | Y6: 6 | Z6: Em aberto - Vencido | AA6: ASSOCIAÇÃO BA ? L1 | AB6: 35.686.965/0001-64 - ALEXANDRIA TECH | AC6: Estimado | AE6: 1 a 30 dias | AF6: c874ae86-bfe5-48a1-84c3-350d7091e666 | AG6: 46111 | AH6: 1 a 30 dias | AI6: =_xlfn.XLOOKUP(Tabela5[[#This Row],[UUID]],Planilha2!$A:$A,Planilha2!B:B,"") -> 1 | AJ6: =_xlfn.XLOOKUP(Tabela5[[#This Row],[UUID]],Planilha2!$A:$A,Planilha2!C:C,"") -> 1 | AK6: =_xlfn.XLOOKUP(Tabela5[[#This Row],[UUID]],Planilha2!$A:$A,Planilha2!D:D,"") -> 1 | AL6: =_xlfn.XLOOKUP(Tabela5[[#This Row],[UUID]],Planilha2!$A:$A,Planilha2!E:E,"") -> 0 | AM6: =_xlfn.XLOOKUP(Tabela5[[#This Row],[UUID]],Planilha2!$A:$A,Planilha2!F:F,"") -> 1 | AN6: =_xlfn.XLOOKUP(Tabela5[[#This Row],[UUID]],Planilha2!$A:$A,Planilha2!G:G,"") -> 1 | AO6: =_xlfn.XLOOKUP(Tabela5[[#This Row],[UUID]],Planilha2!$A:$A,Planilha2!H:H,"") -> 1 | AP6: =_xlfn.XLOOKUP(Tabela5[[#This Row],[UUID]],Planilha2!$A:$A,Planilha2!I:I,"") -> 0 | AQ6: =_xlfn.XLOOKUP(Tabela5[[#This Row],[UUID]],Planilha2!$A:$A,Planilha2!J:J,"") -> 0 | AR6: =_xlfn.XLOOKUP(Tabela5[[#This Row],[UUID]],Planilha2!$A:$A,Planilha2!K:K,"") -> 0 | AS6: =_xlfn.XLOOKUP(Tabela5[[#This Row],[UUID]],Planilha2!$A:$A,Planilha2!L:L,"") -> 0 | AT6: =_xlfn.XLOOKUP(Tabela5[[#This Row],[UUID]],Planilha2!$A:$A,Planilha2!M:M,"") -> 1 | AU6: =_xlfn.XLOOKUP(Tabela5[[#This Row],[UUID]],Planilha2!$A:$A,Planilha2!N:N,"") -> 1 | AV6: =_xlfn.XLOOKUP(Tabela5[[#This Row],[UUID]],Planilha2!$A:$A,Planilha2!O:O,"") -> 1
A7: COB-242941 | B7: Faturado | C7: 40257119 | D7: 1870686586 | E7: JUSCELIA DOS SANTOS DIAS ALMEIDA | F7: RUA PRINCESA LEOPOLDINA 197 FT DR JURACY PIRES GOMES Brumado BA 46100-000 | G7: ADE-16812-B1F5D3 | H7: 46082 | I7: 202603 | J7: 145.9723 | L7: 145.97 | N7: 90520521 | O7: 46101 | P7: 46111 | R7: 15 | S7: 2 - CPF | T7: Em aberto - Vencido | U7: Em aberto - Vencido | V7: PCWO0XR | W7: 6 | X7: false | Y7: 6 | Z7: Em aberto - Vencido | AA7: ASSOCIAÇÃO BA ? L1 | AB7: 35.686.965/0001-64 - ALEXANDRIA TECH | AC7: Estimado | AE7: 1 a 30 dias | AF7: 4fd06ac5-aa94-4d20-9802-e4b62c886713 | AG7: 46115 | AH7: 1 a 30 dias | AI7: =_xlfn.XLOOKUP(Tabela5[[#This Row],[UUID]],Planilha2!$A:$A,Planilha2!B:B,"") -> 1 | AJ7: =_xlfn.XLOOKUP(Tabela5[[#This Row],[UUID]],Planilha2!$A:$A,Planilha2!C:C,"") -> 1 | AK7: =_xlfn.XLOOKUP(Tabela5[[#This Row],[UUID]],Planilha2!$A:$A,Planilha2!D:D,"") -> 7 | AL7: =_xlfn.XLOOKUP(Tabela5[[#This Row],[UUID]],Planilha2!$A:$A,Planilha2!E:E,"") -> 0 | AM7: =_xlfn.XLOOKUP(Tabela5[[#This Row],[UUID]],Planilha2!$A:$A,Planilha2!F:F,"") -> 1 | AN7: =_xlfn.XLOOKUP(Tabela5[[#This Row],[UUID]],Planilha2!$A:$A,Planilha2!G:G,"") -> 1 | AO7: =_xlfn.XLOOKUP(Tabela5[[#This Row],[UUID]],Planilha2!$A:$A,Planilha2!H:H,"") -> 0 | AP7: =_xlfn.XLOOKUP(Tabela5[[#This Row],[UUID]],Planilha2!$A:$A,Planilha2!I:I,"") -> 0 | AQ7: =_xlfn.XLOOKUP(Tabela5[[#This Row],[UUID]],Planilha2!$A:$A,Planilha2!J:J,"") -> 0 | AR7: =_xlfn.XLOOKUP(Tabela5[[#This Row],[UUID]],Planilha2!$A:$A,Planilha2!K:K,"") -> 0 | AS7: =_xlfn.XLOOKUP(Tabela5[[#This Row],[UUID]],Planilha2!$A:$A,Planilha2!L:L,"") -> 0 | AT7: =_xlfn.XLOOKUP(Tabela5[[#This Row],[UUID]],Planilha2!$A:$A,Planilha2!M:M,"") -> 0 | AU7: =_xlfn.XLOOKUP(Tabela5[[#This Row],[UUID]],Planilha2!$A:$A,Planilha2!N:N,"") -> 1 | AV7: =_xlfn.XLOOKUP(Tabela5[[#This Row],[UUID]],Planilha2!$A:$A,Planilha2!O:O,"") -> 1
A8: COB-242936 | B8: Faturado | C8: 11212444 | D8: 8161375526 | E8: KAYC VITOR ASSIS OLIVEIRA | F8: FZ ILICURITIBA 9999 CENTRO Conceição do Jacuípe BA 44245-000 | G8: ADE-16795-N2Y0W7 | H8: 46082 | I8: 202603 | J8: 169.47028 | L8: 169.47 | N8: 90520426 | O8: 46101 | P8: 46111 | R8: 15 | S8: 2 - CPF | T8: Em aberto - Vencido | U8: Em aberto - Vencido | V8: E7XRQO7 | W8: 6 | X8: false | Y8: 6 | Z8: Em aberto - Vencido | AA8: ASSOCIAÇÃO BA ? L1 | AB8: 35.686.965/0001-64 - ALEXANDRIA TECH | AC8: Estimado | AE8: 1 a 30 dias | AF8: 85c2c47d-d065-4e4d-928b-e750b48be0b5 | AG8: 46115 | AH8: 1 a 30 dias | AI8: =_xlfn.XLOOKUP(Tabela5[[#This Row],[UUID]],Planilha2!$A:$A,Planilha2!B:B,"") -> 1 | AJ8: =_xlfn.XLOOKUP(Tabela5[[#This Row],[UUID]],Planilha2!$A:$A,Planilha2!C:C,"") -> 1 | AK8: =_xlfn.XLOOKUP(Tabela5[[#This Row],[UUID]],Planilha2!$A:$A,Planilha2!D:D,"") -> 1 | AL8: =_xlfn.XLOOKUP(Tabela5[[#This Row],[UUID]],Planilha2!$A:$A,Planilha2!E:E,"") -> 0 | AM8: =_xlfn.XLOOKUP(Tabela5[[#This Row],[UUID]],Planilha2!$A:$A,Planilha2!F:F,"") -> 1 | AN8: =_xlfn.XLOOKUP(Tabela5[[#This Row],[UUID]],Planilha2!$A:$A,Planilha2!G:G,"") -> 1 | AO8: =_xlfn.XLOOKUP(Tabela5[[#This Row],[UUID]],Planilha2!$A:$A,Planilha2!H:H,"") -> 0 | AP8: =_xlfn.XLOOKUP(Tabela5[[#This Row],[UUID]],Planilha2!$A:$A,Planilha2!I:I,"") -> 0 | AQ8: =_xlfn.XLOOKUP(Tabela5[[#This Row],[UUID]],Planilha2!$A:$A,Planilha2!J:J,"") -> 0 | AR8: =_xlfn.XLOOKUP(Tabela5[[#This Row],[UUID]],Planilha2!$A:$A,Planilha2!K:K,"") -> 0 | AS8: =_xlfn.XLOOKUP(Tabela5[[#This Row],[UUID]],Planilha2!$A:$A,Planilha2!L:L,"") -> 0 | AT8: =_xlfn.XLOOKUP(Tabela5[[#This Row],[UUID]],Planilha2!$A:$A,Planilha2!M:M,"") -> 0 | AU8: =_xlfn.XLOOKUP(Tabela5[[#This Row],[UUID]],Planilha2!$A:$A,Planilha2!N:N,"") -> 1 | AV8: =_xlfn.XLOOKUP(Tabela5[[#This Row],[UUID]],Planilha2!$A:$A,Planilha2!O:O,"") -> 1
A9: COB-242926 | B9: Faturado | C9: 30243027 | D9: 95303383504 | E9: EVANILDA DE SOUZA SILVA SANTOS | F9: RUA AUTA LEITE OLIVEIRA 774 DO TANQUE Brumado BA 46100-000 | G9: ADE-16762-W4C4Y0 | H9: 46082 | I9: 202603 | J9: 187.27178 | L9: 187.27 | N9: 90520228 | O9: 46101 | P9: 46111 | R9: 15 | S9: 2 - CPF | T9: Em aberto - Vencido | U9: Em aberto - Vencido | V9: 05J946B | Y9: 6 | Z9: NA | AA9: ASSOCIAÇÃO BA ? L1 | AB9: 35.686.965/0001-64 - ALEXANDRIA TECH | AC9: Estimado | AE9: 1 a 30 dias | AF9: 7102abfa-f467-4498-9224-b177677008f0 | AG9: 46111 | AH9: 1 a 30 dias | AI9: =_xlfn.XLOOKUP(Tabela5[[#This Row],[UUID]],Planilha2!$A:$A,Planilha2!B:B,"") -> 1 | AJ9: =_xlfn.XLOOKUP(Tabela5[[#This Row],[UUID]],Planilha2!$A:$A,Planilha2!C:C,"") -> 1 | AK9: =_xlfn.XLOOKUP(Tabela5[[#This Row],[UUID]],Planilha2!$A:$A,Planilha2!D:D,"") -> 6 | AL9: =_xlfn.XLOOKUP(Tabela5[[#This Row],[UUID]],Planilha2!$A:$A,Planilha2!E:E,"") -> 0 | AM9: =_xlfn.XLOOKUP(Tabela5[[#This Row],[UUID]],Planilha2!$A:$A,Planilha2!F:F,"") -> 1 | AN9: =_xlfn.XLOOKUP(Tabela5[[#This Row],[UUID]],Planilha2!$A:$A,Planilha2!G:G,"") -> 1 | AO9: =_xlfn.XLOOKUP(Tabela5[[#This Row],[UUID]],Planilha2!$A:$A,Planilha2!H:H,"") -> 1 | AP9: =_xlfn.XLOOKUP(Tabela5[[#This Row],[UUID]],Planilha2!$A:$A,Planilha2!I:I,"") -> 0 | AQ9: =_xlfn.XLOOKUP(Tabela5[[#This Row],[UUID]],Planilha2!$A:$A,Planilha2!J:J,"") -> 0 | AR9: =_xlfn.XLOOKUP(Tabela5[[#This Row],[UUID]],Planilha2!$A:$A,Planilha2!K:K,"") -> 0 | AS9: =_xlfn.XLOOKUP(Tabela5[[#This Row],[UUID]],Planilha2!$A:$A,Planilha2!L:L,"") -> 0 | AT9: =_xlfn.XLOOKUP(Tabela5[[#This Row],[UUID]],Planilha2!$A:$A,Planilha2!M:M,"") -> 1 | AU9: =_xlfn.XLOOKUP(Tabela5[[#This Row],[UUID]],Planilha2!$A:$A,Planilha2!N:N,"") -> 1 | AV9: =_xlfn.XLOOKUP(Tabela5[[#This Row],[UUID]],Planilha2!$A:$A,Planilha2!O:O,"") -> 1
A10: COB-242920 | B10: Faturado | C10: 6538183 | D10: 40407594 | E10: MARIA JOSE FERREIRA DE OLIVEIRA | F10: RUA PADRE MANOEL NOBREGA 32 CRUZEIRO Vitória da Conquista BA 45000-000 | G10: ADE-16632-P5Q3G8 | H10: 46082 | I10: 202603 | J10: 143.59402 | L10: 143.59 | N10: 90520276 | O10: 46101 | P10: 46111 | R10: 15 | S10: 2 - CPF | T10: Em aberto - Vencido | U10: Em aberto - Vencido | V10: D9506SY | W10: 6 | X10: false | Y10: 6 | Z10: Em aberto - Vencido | AA10: ASSOCIAÇÃO BA ? L1 | AB10: 35.686.965/0001-64 - ALEXANDRIA TECH | AC10: Estimado | AE10: 1 a 30 dias | AF10: 47b1bf63-a080-4de2-ae40-d66a39bb05f1 | AG10: 46115 | AH10: 1 a 30 dias | AI10: =_xlfn.XLOOKUP(Tabela5[[#This Row],[UUID]],Planilha2!$A:$A,Planilha2!B:B,"") -> 1 | AJ10: =_xlfn.XLOOKUP(Tabela5[[#This Row],[UUID]],Planilha2!$A:$A,Planilha2!C:C,"") -> 1 | AK10: =_xlfn.XLOOKUP(Tabela5[[#This Row],[UUID]],Planilha2!$A:$A,Planilha2!D:D,"") -> 1 | AL10: =_xlfn.XLOOKUP(Tabela5[[#This Row],[UUID]],Planilha2!$A:$A,Planilha2!E:E,"") -> 0 | AM10: =_xlfn.XLOOKUP(Tabela5[[#This Row],[UUID]],Planilha2!$A:$A,Planilha2!F:F,"") -> 1 | AN10: =_xlfn.XLOOKUP(Tabela5[[#This Row],[UUID]],Planilha2!$A:$A,Planilha2!G:G,"") -> 1 | AO10: =_xlfn.XLOOKUP(Tabela5[[#This Row],[UUID]],Planilha2!$A:$A,Planilha2!H:H,"") -> 0 | AP10: =_xlfn.XLOOKUP(Tabela5[[#This Row],[UUID]],Planilha2!$A:$A,Planilha2!I:I,"") -> 0 | AQ10: =_xlfn.XLOOKUP(Tabela5[[#This Row],[UUID]],Planilha2!$A:$A,Planilha2!J:J,"") -> 0 | AR10: =_xlfn.XLOOKUP(Tabela5[[#This Row],[UUID]],Planilha2!$A:$A,Planilha2!K:K,"") -> 0 | AS10: =_xlfn.XLOOKUP(Tabela5[[#This Row],[UUID]],Planilha2!$A:$A,Planilha2!L:L,"") -> 0 | AT10: =_xlfn.XLOOKUP(Tabela5[[#This Row],[UUID]],Planilha2!$A:$A,Planilha2!M:M,"") -> 0 | AU10: =_xlfn.XLOOKUP(Tabela5[[#This Row],[UUID]],Planilha2!$A:$A,Planilha2!N:N,"") -> 1 | AV10: =_xlfn.XLOOKUP(Tabela5[[#This Row],[UUID]],Planilha2!$A:$A,Planilha2!O:O,"") -> 1
A11: COB-242908 | B11: Faturado | C11: 10922377 | D11: 326740589 | E11: CLAUDIVANE MIRANDA DA SILVA | F11: RUA DIRETA DA MANGABEIRA 69 C Cajazeiras VIII Salvador BA 41338-710 | G11: ADE-16529-W6Y2L0 | H11: 46082 | I11: 202603 | J11: 311.17022 | L11: 311.17 | N11: 90520366 | O11: 46101 | P11: 46111 | R11: 15 | S11: 2 - CPF | T11: Em aberto - Vencido | U11: Em aberto - Vencido | V11: PRADFKG | W11: 6 | X11: false | Y11: 6 | Z11: Em aberto - Vencido | AA11: ASSOCIAÇÃO BA ? L1 | AB11: 35.686.965/0001-64 - ALEXANDRIA TECH | AC11: Estimado | AE11: 1 a 30 dias | AF11: e0013a76-c338-4256-bfb2-f914966e5c27 | AG11: 46115 | AH11: 1 a 30 dias | AI11: =_xlfn.XLOOKUP(Tabela5[[#This Row],[UUID]],Planilha2!$A:$A,Planilha2!B:B,"") -> 1 | AJ11: =_xlfn.XLOOKUP(Tabela5[[#This Row],[UUID]],Planilha2!$A:$A,Planilha2!C:C,"") -> 1 | AK11: =_xlfn.XLOOKUP(Tabela5[[#This Row],[UUID]],Planilha2!$A:$A,Planilha2!D:D,"") -> 12 | AL11: =_xlfn.XLOOKUP(Tabela5[[#This Row],[UUID]],Planilha2!$A:$A,Planilha2!E:E,"") -> 0 | AM11: =_xlfn.XLOOKUP(Tabela5[[#This Row],[UUID]],Planilha2!$A:$A,Planilha2!F:F,"") -> 1 | AN11: =_xlfn.XLOOKUP(Tabela5[[#This Row],[UUID]],Planilha2!$A:$A,Planilha2!G:G,"") -> 1 | AO11: =_xlfn.XLOOKUP(Tabela5[[#This Row],[UUID]],Planilha2!$A:$A,Planilha2!H:H,"") -> 0 | AP11: =_xlfn.XLOOKUP(Tabela5[[#This Row],[UUID]],Planilha2!$A:$A,Planilha2!I:I,"") -> 0 | AQ11: =_xlfn.XLOOKUP(Tabela5[[#This Row],[UUID]],Planilha2!$A:$A,Planilha2!J:J,"") -> 0 | AR11: =_xlfn.XLOOKUP(Tabela5[[#This Row],[UUID]],Planilha2!$A:$A,Planilha2!K:K,"") -> 0 | AS11: =_xlfn.XLOOKUP(Tabela5[[#This Row],[UUID]],Planilha2!$A:$A,Planilha2!L:L,"") -> 0 | AT11: =_xlfn.XLOOKUP(Tabela5[[#This Row],[UUID]],Planilha2!$A:$A,Planilha2!M:M,"") -> 0 | AU11: =_xlfn.XLOOKUP(Tabela5[[#This Row],[UUID]],Planilha2!$A:$A,Planilha2!N:N,"") -> 1 | AV11: =_xlfn.XLOOKUP(Tabela5[[#This Row],[UUID]],Planilha2!$A:$A,Planilha2!O:O,"") -> 1
A12: COB-125624 | B12: Faturado | C12: 74420895 | D12: 18308585809 | E12: VAGNER MAURO ALCARAZ | F12: RUA CARLOTA MARCIO 475 11677-000 MASSAGUACU / CARAGUATATUBA - SP | G12: ADE-12297-B5R6H6 | H12: 45839 | I12: 202507 | J12: 580.94785 | L12: 580.95 | N12: 90364329 | O12: 45916 | P12: 45926 | R12: 200 | S12: 2 - CPF | T12: Em aberto - Vencido | U12: Em aberto - Vencido | V12: 9QGZO0A | W12: 6 | X12: false | Y12: 6 | Z12: Em aberto - Vencido | AA12: ASSOCIAÇÃO SP-L3 | AB12: 35.686.965/0001-64 - ALEXANDRIA TECH | AE12: 171 a 450 dias | AF12: 159cfc1a-ef8c-4fcc-8ac4-999baf6c1e2a | AG12: 45965 | AH12: Maior que 90 | AI12: =_xlfn.XLOOKUP(Tabela5[[#This Row],[UUID]],Planilha2!$A:$A,Planilha2!B:B,"") -> 0 | AJ12: =_xlfn.XLOOKUP(Tabela5[[#This Row],[UUID]],Planilha2!$A:$A,Planilha2!C:C,"") -> 0 | AK12: =_xlfn.XLOOKUP(Tabela5[[#This Row],[UUID]],Planilha2!$A:$A,Planilha2!D:D,"") -> 0 | AL12: =_xlfn.XLOOKUP(Tabela5[[#This Row],[UUID]],Planilha2!$A:$A,Planilha2!E:E,"") -> 5 | AM12: =_xlfn.XLOOKUP(Tabela5[[#This Row],[UUID]],Planilha2!$A:$A,Planilha2!F:F,"") -> 0 | AN12: =_xlfn.XLOOKUP(Tabela5[[#This Row],[UUID]],Planilha2!$A:$A,Planilha2!G:G,"") -> 0 | AO12: =_xlfn.XLOOKUP(Tabela5[[#This Row],[UUID]],Planilha2!$A:$A,Planilha2!H:H,"") -> 0 | AP12: =_xlfn.XLOOKUP(Tabela5[[#This Row],[UUID]],Planilha2!$A:$A,Planilha2!I:I,"") -> 0 | AQ12: =_xlfn.XLOOKUP(Tabela5[[#This Row],[UUID]],Planilha2!$A:$A,Planilha2!J:J,"") -> 0 | AR12: =_xlfn.XLOOKUP(Tabela5[[#This Row],[UUID]],Planilha2!$A:$A,Planilha2!K:K,"") -> 0 | AS12: =_xlfn.XLOOKUP(Tabela5[[#This Row],[UUID]],Planilha2!$A:$A,Planilha2!L:L,"") -> 0 | AT12: =_xlfn.XLOOKUP(Tabela5[[#This Row],[UUID]],Planilha2!$A:$A,Planilha2!M:M,"") -> 0 | AU12: =_xlfn.XLOOKUP(Tabela5[[#This Row],[UUID]],Planilha2!$A:$A,Planilha2!N:N,"") -> 0 | AV12: =_xlfn.XLOOKUP(Tabela5[[#This Row],[UUID]],Planilha2!$A:$A,Planilha2!O:O,"") -> 0
A13: COB-242907 | B13: Faturado | C13: 4989707 | D13: 13347454553 | E13: JOSE SANTANA FRANCA | F13: Rua Opatciana da Silva Oliveira 132 AP: 102 CJ Rodrigo Salvador BROTAS Salvador BA 40276-070 | G13: ADE-16525-J2C8R6 | H13: 46082 | I13: 202603 | J13: 124.6105 | L13: 124.61 | N13: 90520316 | O13: 46101 | P13: 46111 | R13: 15 | S13: 2 - CPF | T13: Em aberto - Vencido | U13: Em aberto - Vencido | V13: BQSCN0K | W13: 6 | X13: false | Y13: 6 | Z13: Em aberto - Vencido | AA13: ASSOCIAÇÃO BA ? L1 | AB13: 35.686.965/0001-64 - ALEXANDRIA TECH | AC13: Estimado | AE13: 1 a 30 dias | AF13: 622cd132-8f40-44ea-93fd-965ed0144832 | AG13: 46115 | AH13: 1 a 30 dias | AI13: =_xlfn.XLOOKUP(Tabela5[[#This Row],[UUID]],Planilha2!$A:$A,Planilha2!B:B,"") -> 1 | AJ13: =_xlfn.XLOOKUP(Tabela5[[#This Row],[UUID]],Planilha2!$A:$A,Planilha2!C:C,"") -> 1 | AK13: =_xlfn.XLOOKUP(Tabela5[[#This Row],[UUID]],Planilha2!$A:$A,Planilha2!D:D,"") -> 1 | AL13: =_xlfn.XLOOKUP(Tabela5[[#This Row],[UUID]],Planilha2!$A:$A,Planilha2!E:E,"") -> 0 | AM13: =_xlfn.XLOOKUP(Tabela5[[#This Row],[UUID]],Planilha2!$A:$A,Planilha2!F:F,"") -> 1 | AN13: =_xlfn.XLOOKUP(Tabela5[[#This Row],[UUID]],Planilha2!$A:$A,Planilha2!G:G,"") -> 1 | AO13: =_xlfn.XLOOKUP(Tabela5[[#This Row],[UUID]],Planilha2!$A:$A,Planilha2!H:H,"") -> 0 | AP13: =_xlfn.XLOOKUP(Tabela5[[#This Row],[UUID]],Planilha2!$A:$A,Planilha2!I:I,"") -> 0 | AQ13: =_xlfn.XLOOKUP(Tabela5[[#This Row],[UUID]],Planilha2!$A:$A,Planilha2!J:J,"") -> 0 | AR13: =_xlfn.XLOOKUP(Tabela5[[#This Row],[UUID]],Planilha2!$A:$A,Planilha2!K:K,"") -> 0 | AS13: =_xlfn.XLOOKUP(Tabela5[[#This Row],[UUID]],Planilha2!$A:$A,Planilha2!L:L,"") -> 0 | AT13: =_xlfn.XLOOKUP(Tabela5[[#This Row],[UUID]],Planilha2!$A:$A,Planilha2!M:M,"") -> 0 | AU13: =_xlfn.XLOOKUP(Tabela5[[#This Row],[UUID]],Planilha2!$A:$A,Planilha2!N:N,"") -> 1 | AV13: =_xlfn.XLOOKUP(Tabela5[[#This Row],[UUID]],Planilha2!$A:$A,Planilha2!O:O,"") -> 1
A14: COB-242906 | B14: Faturado | C14: 1491079 | D14: 4746887551 | E14: ANA CORDEIRO VICENTE | F14: RUA ANTONIO OLIMP DA SILVA 136 JUCA ROSA Eunápolis BA 45833-999 | G14: ADE-16509-Z2N3T3 | H14: 46082 | I14: 202603 | J14: 168.04616 | L14: 168.05 | N14: 90520484 | O14: 46101 | P14: 46111 | R14: 15 | S14: 2 - CPF | T14: Em aberto - Vencido | U14: Em aberto - Vencido | V14: XQOC28O | W14: 6 | X14: false | Y14: 6 | Z14: Em aberto - Vencido | AA14: ASSOCIAÇÃO BA ? L1 | AB14: 35.686.965/0001-64 - ALEXANDRIA TECH | AC14: Estimado | AE14: 1 a 30 dias | AF14: 639dd04c-82dd-45f9-a862-8da0cb96b2c1 | AG14: 46115 | AH14: 1 a 30 dias | AI14: =_xlfn.XLOOKUP(Tabela5[[#This Row],[UUID]],Planilha2!$A:$A,Planilha2!B:B,"") -> 1 | AJ14: =_xlfn.XLOOKUP(Tabela5[[#This Row],[UUID]],Planilha2!$A:$A,Planilha2!C:C,"") -> 1 | AK14: =_xlfn.XLOOKUP(Tabela5[[#This Row],[UUID]],Planilha2!$A:$A,Planilha2!D:D,"") -> 1 | AL14: =_xlfn.XLOOKUP(Tabela5[[#This Row],[UUID]],Planilha2!$A:$A,Planilha2!E:E,"") -> 0 | AM14: =_xlfn.XLOOKUP(Tabela5[[#This Row],[UUID]],Planilha2!$A:$A,Planilha2!F:F,"") -> 1 | AN14: =_xlfn.XLOOKUP(Tabela5[[#This Row],[UUID]],Planilha2!$A:$A,Planilha2!G:G,"") -> 1 | AO14: =_xlfn.XLOOKUP(Tabela5[[#This Row],[UUID]],Planilha2!$A:$A,Planilha2!H:H,"") -> 0 | AP14: =_xlfn.XLOOKUP(Tabela5[[#This Row],[UUID]],Planilha2!$A:$A,Planilha2!I:I,"") -> 0 | AQ14: =_xlfn.XLOOKUP(Tabela5[[#This Row],[UUID]],Planilha2!$A:$A,Planilha2!J:J,"") -> 0 | AR14: =_xlfn.XLOOKUP(Tabela5[[#This Row],[UUID]],Planilha2!$A:$A,Planilha2!K:K,"") -> 0 | AS14: =_xlfn.XLOOKUP(Tabela5[[#This Row],[UUID]],Planilha2!$A:$A,Planilha2!L:L,"") -> 0 | AT14: =_xlfn.XLOOKUP(Tabela5[[#This Row],[UUID]],Planilha2!$A:$A,Planilha2!M:M,"") -> 0 | AU14: =_xlfn.XLOOKUP(Tabela5[[#This Row],[UUID]],Planilha2!$A:$A,Planilha2!N:N,"") -> 1 | AV14: =_xlfn.XLOOKUP(Tabela5[[#This Row],[UUID]],Planilha2!$A:$A,Planilha2!O:O,"") -> 1
A15: COB-242902 | B15: Faturado | C15: 759988 | D15: 18857167534 | E15: SEBASTIAO CASTRO DA SILVA | F15: CA 22 2 B GLEBA E/CAMACARI Camaçari BA 42849-999 | G15: ADE-16502-H5B5N2 | H15: 46082 | I15: 202603 | J15: 178.72706 | L15: 178.73 | N15: 90520303 | O15: 46101 | P15: 46111 | R15: 15 | S15: 2 - CPF | T15: Em aberto - Vencido | U15: Em aberto - Vencido | V15: TRZA0UH | W15: 6 | X15: false | Y15: 6 | Z15: Em aberto - Vencido | AA15: ASSOCIAÇÃO BA ? L1 | AB15: 35.686.965/0001-64 - ALEXANDRIA TECH | AC15: Estimado | AE15: 1 a 30 dias | AF15: 896e934c-975f-47a0-8f55-a7d2e63dd813 | AG15: 46115 | AH15: 1 a 30 dias | AI15: =_xlfn.XLOOKUP(Tabela5[[#This Row],[UUID]],Planilha2!$A:$A,Planilha2!B:B,"") -> 1 | AJ15: =_xlfn.XLOOKUP(Tabela5[[#This Row],[UUID]],Planilha2!$A:$A,Planilha2!C:C,"") -> 1 | AK15: =_xlfn.XLOOKUP(Tabela5[[#This Row],[UUID]],Planilha2!$A:$A,Planilha2!D:D,"") -> 11 | AL15: =_xlfn.XLOOKUP(Tabela5[[#This Row],[UUID]],Planilha2!$A:$A,Planilha2!E:E,"") -> 0 | AM15: =_xlfn.XLOOKUP(Tabela5[[#This Row],[UUID]],Planilha2!$A:$A,Planilha2!F:F,"") -> 1 | AN15: =_xlfn.XLOOKUP(Tabela5[[#This Row],[UUID]],Planilha2!$A:$A,Planilha2!G:G,"") -> 1 | AO15: =_xlfn.XLOOKUP(Tabela5[[#This Row],[UUID]],Planilha2!$A:$A,Planilha2!H:H,"") -> 0 | AP15: =_xlfn.XLOOKUP(Tabela5[[#This Row],[UUID]],Planilha2!$A:$A,Planilha2!I:I,"") -> 0 | AQ15: =_xlfn.XLOOKUP(Tabela5[[#This Row],[UUID]],Planilha2!$A:$A,Planilha2!J:J,"") -> 0 | AR15: =_xlfn.XLOOKUP(Tabela5[[#This Row],[UUID]],Planilha2!$A:$A,Planilha2!K:K,"") -> 0 | AS15: =_xlfn.XLOOKUP(Tabela5[[#This Row],[UUID]],Planilha2!$A:$A,Planilha2!L:L,"") -> 0 | AT15: =_xlfn.XLOOKUP(Tabela5[[#This Row],[UUID]],Planilha2!$A:$A,Planilha2!M:M,"") -> 0 | AU15: =_xlfn.XLOOKUP(Tabela5[[#This Row],[UUID]],Planilha2!$A:$A,Planilha2!N:N,"") -> 1 | AV15: =_xlfn.XLOOKUP(Tabela5[[#This Row],[UUID]],Planilha2!$A:$A,Planilha2!O:O,"") -> 1
A16: COB-242901 | B16: Faturado | C16: 4771655 | D16: 46859071591 | E16: SANDOVAL AMARAL DOS SANTOS | F16: VIA COLETADORA B 1300 CD Res Portal do Vale Bl 03 Ap 303 CAJAZEIRAS Salvador BA 41345-100 | G16: ADE-16500-Q3B1N7 | H16: 46082 | I16: 202603 | J16: 149.5326 | L16: 149.53 | N16: 90520463 | O16: 46101 | P16: 46111 | R16: 15 | S16: 2 - CPF | T16: Em aberto - Vencido | U16: Em aberto - Vencido | V16: 11FTOV0 | W16: 6 | X16: false | Y16: 6 | Z16: Em aberto - Vencido | AA16: ASSOCIAÇÃO BA ? L1 | AB16: 35.686.965/0001-64 - ALEXANDRIA TECH | AC16: Estimado | AE16: 1 a 30 dias | AF16: f5817f41-7a5d-452f-ba2b-648168cd5e6b | AG16: 46115 | AH16: 1 a 30 dias | AI16: =_xlfn.XLOOKUP(Tabela5[[#This Row],[UUID]],Planilha2!$A:$A,Planilha2!B:B,"") -> 1 | AJ16: =_xlfn.XLOOKUP(Tabela5[[#This Row],[UUID]],Planilha2!$A:$A,Planilha2!C:C,"") -> 1 | AK16: =_xlfn.XLOOKUP(Tabela5[[#This Row],[UUID]],Planilha2!$A:$A,Planilha2!D:D,"") -> 1 | AL16: =_xlfn.XLOOKUP(Tabela5[[#This Row],[UUID]],Planilha2!$A:$A,Planilha2!E:E,"") -> 0 | AM16: =_xlfn.XLOOKUP(Tabela5[[#This Row],[UUID]],Planilha2!$A:$A,Planilha2!F:F,"") -> 1 | AN16: =_xlfn.XLOOKUP(Tabela5[[#This Row],[UUID]],Planilha2!$A:$A,Planilha2!G:G,"") -> 1 | AO16: =_xlfn.XLOOKUP(Tabela5[[#This Row],[UUID]],Planilha2!$A:$A,Planilha2!H:H,"") -> 0 | AP16: =_xlfn.XLOOKUP(Tabela5[[#This Row],[UUID]],Planilha2!$A:$A,Planilha2!I:I,"") -> 0 | AQ16: =_xlfn.XLOOKUP(Tabela5[[#This Row],[UUID]],Planilha2!$A:$A,Planilha2!J:J,"") -> 0 | AR16: =_xlfn.XLOOKUP(Tabela5[[#This Row],[UUID]],Planilha2!$A:$A,Planilha2!K:K,"") -> 0 | AS16: =_xlfn.XLOOKUP(Tabela5[[#This Row],[UUID]],Planilha2!$A:$A,Planilha2!L:L,"") -> 0 | AT16: =_xlfn.XLOOKUP(Tabela5[[#This Row],[UUID]],Planilha2!$A:$A,Planilha2!M:M,"") -> 0 | AU16: =_xlfn.XLOOKUP(Tabela5[[#This Row],[UUID]],Planilha2!$A:$A,Planilha2!N:N,"") -> 1 | AV16: =_xlfn.XLOOKUP(Tabela5[[#This Row],[UUID]],Planilha2!$A:$A,Planilha2!O:O,"") -> 1
A17: COB-242897 | B17: Faturado | C17: 70250212 | D17: 86411440565 | E17: QUEVENI DEIRON DOS SANTOS | F17: RUA ACU DA TORRE 59 A Praia do Forte Mata de São João BA 48287-000 | G17: ADE-16492-V1J0S7 | H17: 46082 | I17: 202603 | J17: 3155.1379 | L17: 3155.14 | N17: 90520438 | O17: 46101 | P17: 46111 | R17: 15 | S17: 2 - CPF | T17: Em aberto - Vencido | U17: Em aberto - Vencido | V17: RFD99E0 | Y17: 6 | Z17: NA | AA17: ASSOCIAÇÃO BA ? L1 | AB17: 35.686.965/0001-64 - ALEXANDRIA TECH | AC17: Estimado | AE17: 1 a 30 dias | AF17: ca7705bf-29a8-46a6-b1f1-23e3ba1bef05 | AG17: 46115 | AH17: 1 a 30 dias | AI17: =_xlfn.XLOOKUP(Tabela5[[#This Row],[UUID]],Planilha2!$A:$A,Planilha2!B:B,"") -> 1 | AJ17: =_xlfn.XLOOKUP(Tabela5[[#This Row],[UUID]],Planilha2!$A:$A,Planilha2!C:C,"") -> 1 | AK17: =_xlfn.XLOOKUP(Tabela5[[#This Row],[UUID]],Planilha2!$A:$A,Planilha2!D:D,"") -> 10 | AL17: =_xlfn.XLOOKUP(Tabela5[[#This Row],[UUID]],Planilha2!$A:$A,Planilha2!E:E,"") -> 0 | AM17: =_xlfn.XLOOKUP(Tabela5[[#This Row],[UUID]],Planilha2!$A:$A,Planilha2!F:F,"") -> 1 | AN17: =_xlfn.XLOOKUP(Tabela5[[#This Row],[UUID]],Planilha2!$A:$A,Planilha2!G:G,"") -> 1 | AO17: =_xlfn.XLOOKUP(Tabela5[[#This Row],[UUID]],Planilha2!$A:$A,Planilha2!H:H,"") -> 0 | AP17: =_xlfn.XLOOKUP(Tabela5[[#This Row],[UUID]],Planilha2!$A:$A,Planilha2!I:I,"") -> 0 | AQ17: =_xlfn.XLOOKUP(Tabela5[[#This Row],[UUID]],Planilha2!$A:$A,Planilha2!J:J,"") -> 0 | AR17: =_xlfn.XLOOKUP(Tabela5[[#This Row],[UUID]],Planilha2!$A:$A,Planilha2!K:K,"") -> 0 | AS17: =_xlfn.XLOOKUP(Tabela5[[#This Row],[UUID]],Planilha2!$A:$A,Planilha2!L:L,"") -> 0 | AT17: =_xlfn.XLOOKUP(Tabela5[[#This Row],[UUID]],Planilha2!$A:$A,Planilha2!M:M,"") -> 0 | AU17: =_xlfn.XLOOKUP(Tabela5[[#This Row],[UUID]],Planilha2!$A:$A,Planilha2!N:N,"") -> 1 | AV17: =_xlfn.XLOOKUP(Tabela5[[#This Row],[UUID]],Planilha2!$A:$A,Planilha2!O:O,"") -> 1
A18: COB-242891 | B18: Faturado | C18: 1475211 | D18: 35140015889 | E18: UILES OLIVEIRA MEIRA | F18: RUA SAO JUDAS TADEU 19 Rosa Neto Eunápolis BA 45823-210 | G18: ADE-16435-R8F8P5 | H18: 46082 | I18: 202603 | J18: 219.31448 | L18: 219.31 | N18: 90520528 | O18: 46101 | P18: 46111 | R18: 15 | S18: 2 - CPF | T18: Em aberto - Vencido | U18: Em aberto - Vencido | V18: 3Z3BNU1 | W18: 6 | X18: false | Y18: 6 | Z18: Em aberto - Vencido | AA18: ASSOCIAÇÃO BA ? L1 | AB18: 35.686.965/0001-64 - ALEXANDRIA TECH | AC18: Estimado | AE18: 1 a 30 dias | AF18: 58f53212-2251-4d6a-ab70-f3b3b8bf414f | AG18: 46115 | AH18: 1 a 30 dias | AI18: =_xlfn.XLOOKUP(Tabela5[[#This Row],[UUID]],Planilha2!$A:$A,Planilha2!B:B,"") -> 1 | AJ18: =_xlfn.XLOOKUP(Tabela5[[#This Row],[UUID]],Planilha2!$A:$A,Planilha2!C:C,"") -> 1 | AK18: =_xlfn.XLOOKUP(Tabela5[[#This Row],[UUID]],Planilha2!$A:$A,Planilha2!D:D,"") -> 1 | AL18: =_xlfn.XLOOKUP(Tabela5[[#This Row],[UUID]],Planilha2!$A:$A,Planilha2!E:E,"") -> 0 | AM18: =_xlfn.XLOOKUP(Tabela5[[#This Row],[UUID]],Planilha2!$A:$A,Planilha2!F:F,"") -> 1 | AN18: =_xlfn.XLOOKUP(Tabela5[[#This Row],[UUID]],Planilha2!$A:$A,Planilha2!G:G,"") -> 1 | AO18: =_xlfn.XLOOKUP(Tabela5[[#This Row],[UUID]],Planilha2!$A:$A,Planilha2!H:H,"") -> 0 | AP18: =_xlfn.XLOOKUP(Tabela5[[#This Row],[UUID]],Planilha2!$A:$A,Planilha2!I:I,"") -> 0 | AQ18: =_xlfn.XLOOKUP(Tabela5[[#This Row],[UUID]],Planilha2!$A:$A,Planilha2!J:J,"") -> 0 | AR18: =_xlfn.XLOOKUP(Tabela5[[#This Row],[UUID]],Planilha2!$A:$A,Planilha2!K:K,"") -> 0 | AS18: =_xlfn.XLOOKUP(Tabela5[[#This Row],[UUID]],Planilha2!$A:$A,Planilha2!L:L,"") -> 0 | AT18: =_xlfn.XLOOKUP(Tabela5[[#This Row],[UUID]],Planilha2!$A:$A,Planilha2!M:M,"") -> 0 | AU18: =_xlfn.XLOOKUP(Tabela5[[#This Row],[UUID]],Planilha2!$A:$A,Planilha2!N:N,"") -> 1 | AV18: =_xlfn.XLOOKUP(Tabela5[[#This Row],[UUID]],Planilha2!$A:$A,Planilha2!O:O,"") -> 1
A19: COB-242892 | B19: Faturado | C19: 763229 | D19: 33490902572 | E19: ALCIR GOMES SANTOS | F19: CA D 08 19 NOVO HORIZONTE Camaçari BA 42849-999 | G19: ADE-16434-J1P7Q2 | H19: 46082 | I19: 202603 | J19: 128.1708 | L19: 128.17 | N19: 90520516 | O19: 46101 | P19: 46111 | R19: 15 | S19: 2 - CPF | T19: Em aberto - Vencido | U19: Em aberto - Vencido | V19: P3OEP8P | W19: 6 | X19: false | Y19: 6 | Z19: Em aberto - Vencido | AA19: ASSOCIAÇÃO BA ? L1 | AB19: 35.686.965/0001-64 - ALEXANDRIA TECH | AC19: Estimado | AE19: 1 a 30 dias | AF19: 1e6ffd93-9562-48f3-8e39-27de4349d95e | AG19: 46115 | AH19: 1 a 30 dias | AI19: =_xlfn.XLOOKUP(Tabela5[[#This Row],[UUID]],Planilha2!$A:$A,Planilha2!B:B,"") -> 1 | AJ19: =_xlfn.XLOOKUP(Tabela5[[#This Row],[UUID]],Planilha2!$A:$A,Planilha2!C:C,"") -> 1 | AK19: =_xlfn.XLOOKUP(Tabela5[[#This Row],[UUID]],Planilha2!$A:$A,Planilha2!D:D,"") -> 1 | AL19: =_xlfn.XLOOKUP(Tabela5[[#This Row],[UUID]],Planilha2!$A:$A,Planilha2!E:E,"") -> 0 | AM19: =_xlfn.XLOOKUP(Tabela5[[#This Row],[UUID]],Planilha2!$A:$A,Planilha2!F:F,"") -> 1 | AN19: =_xlfn.XLOOKUP(Tabela5[[#This Row],[UUID]],Planilha2!$A:$A,Planilha2!G:G,"") -> 1 | AO19: =_xlfn.XLOOKUP(Tabela5[[#This Row],[UUID]],Planilha2!$A:$A,Planilha2!H:H,"") -> 0 | AP19: =_xlfn.XLOOKUP(Tabela5[[#This Row],[UUID]],Planilha2!$A:$A,Planilha2!I:I,"") -> 0 | AQ19: =_xlfn.XLOOKUP(Tabela5[[#This Row],[UUID]],Planilha2!$A:$A,Planilha2!J:J,"") -> 0 | AR19: =_xlfn.XLOOKUP(Tabela5[[#This Row],[UUID]],Planilha2!$A:$A,Planilha2!K:K,"") -> 0 | AS19: =_xlfn.XLOOKUP(Tabela5[[#This Row],[UUID]],Planilha2!$A:$A,Planilha2!L:L,"") -> 0 | AT19: =_xlfn.XLOOKUP(Tabela5[[#This Row],[UUID]],Planilha2!$A:$A,Planilha2!M:M,"") -> 0 | AU19: =_xlfn.XLOOKUP(Tabela5[[#This Row],[UUID]],Planilha2!$A:$A,Planilha2!N:N,"") -> 1 | AV19: =_xlfn.XLOOKUP(Tabela5[[#This Row],[UUID]],Planilha2!$A:$A,Planilha2!O:O,"") -> 1
A20: COB-242888 | B20: Faturado | C20: 4262924 | D20: 7015471540 | E20: TAMISSON SILVA MELO | F20: RUA DO BALNEARIO 110 ED AMARALINA PREDIO DA LOTERICA ESPORTIV AMARALINA Salvador BA 41900-050 | G20: ADE-16431-Q3T8C6 | H20: 46082 | I20: 202603 | J20: 205.78534 | L20: 205.79 | N20: 90520389 | O20: 46101 | P20: 46111 | R20: 15 | S20: 2 - CPF | T20: Em aberto - Vencido | U20: Em aberto - Vencido | V20: 6KDR19A | W20: 6 | X20: false | Y20: 6 | Z20: Em aberto - Vencido | AA20: ASSOCIAÇÃO BA ? L1 | AB20: 35.686.965/0001-64 - ALEXANDRIA TECH | AC20: Estimado | AE20: 1 a 30 dias | AF20: 6d962e72-a894-45b6-83e0-43f20aecc3a2 | AG20: 46115 | AH20: 1 a 30 dias | AI20: =_xlfn.XLOOKUP(Tabela5[[#This Row],[UUID]],Planilha2!$A:$A,Planilha2!B:B,"") -> 1 | AJ20: =_xlfn.XLOOKUP(Tabela5[[#This Row],[UUID]],Planilha2!$A:$A,Planilha2!C:C,"") -> 1 | AK20: =_xlfn.XLOOKUP(Tabela5[[#This Row],[UUID]],Planilha2!$A:$A,Planilha2!D:D,"") -> 10 | AL20: =_xlfn.XLOOKUP(Tabela5[[#This Row],[UUID]],Planilha2!$A:$A,Planilha2!E:E,"") -> 0 | AM20: =_xlfn.XLOOKUP(Tabela5[[#This Row],[UUID]],Planilha2!$A:$A,Planilha2!F:F,"") -> 1 | AN20: =_xlfn.XLOOKUP(Tabela5[[#This Row],[UUID]],Planilha2!$A:$A,Planilha2!G:G,"") -> 1 | AO20: =_xlfn.XLOOKUP(Tabela5[[#This Row],[UUID]],Planilha2!$A:$A,Planilha2!H:H,"") -> 0 | AP20: =_xlfn.XLOOKUP(Tabela5[[#This Row],[UUID]],Planilha2!$A:$A,Planilha2!I:I,"") -> 0 | AQ20: =_xlfn.XLOOKUP(Tabela5[[#This Row],[UUID]],Planilha2!$A:$A,Planilha2!J:J,"") -> 0 | AR20: =_xlfn.XLOOKUP(Tabela5[[#This Row],[UUID]],Planilha2!$A:$A,Planilha2!K:K,"") -> 0 | AS20: =_xlfn.XLOOKUP(Tabela5[[#This Row],[UUID]],Planilha2!$A:$A,Planilha2!L:L,"") -> 0 | AT20: =_xlfn.XLOOKUP(Tabela5[[#This Row],[UUID]],Planilha2!$A:$A,Planilha2!M:M,"") -> 0 | AU20: =_xlfn.XLOOKUP(Tabela5[[#This Row],[UUID]],Planilha2!$A:$A,Planilha2!N:N,"") -> 1 | AV20: =_xlfn.XLOOKUP(Tabela5[[#This Row],[UUID]],Planilha2!$A:$A,Planilha2!O:O,"") -> 1
A21: COB-242548 | B21: Faturado | C21: 5293706 | D21: 2436169535 | E21: REGINA BARBARA SANTOS SILVA | F21: RUA BELA VISTA DO CABRAL 94 SALVADOR 94 Nazaré Salvador BA 40055-000 | G21: ADE-14206-P2S4H8 | H21: 46082 | I21: 202603 | J21: 508.41084 | L21: 508.41 | N21: 90520353 | O21: 46101 | P21: 46111 | R21: 15 | S21: 2 - CPF | T21: Em aberto - Vencido | U21: Em aberto - Vencido | V21: 4NHRTWD | W21: 6 | X21: false | Y21: 6 | Z21: Em aberto - Vencido | AA21: ASSOCIAÇÃO BA ? L1 | AB21: 35.686.965/0001-64 - ALEXANDRIA TECH | AC21: Estimado | AE21: 1 a 30 dias | AF21: 5123a75a-49f9-4223-b470-821f9e7bd3a7 | AG21: 46115 | AH21: 1 a 30 dias | AI21: =_xlfn.XLOOKUP(Tabela5[[#This Row],[UUID]],Planilha2!$A:$A,Planilha2!B:B,"") -> 1 | AJ21: =_xlfn.XLOOKUP(Tabela5[[#This Row],[UUID]],Planilha2!$A:$A,Planilha2!C:C,"") -> 1 | AK21: =_xlfn.XLOOKUP(Tabela5[[#This Row],[UUID]],Planilha2!$A:$A,Planilha2!D:D,"") -> 12 | AL21: =_xlfn.XLOOKUP(Tabela5[[#This Row],[UUID]],Planilha2!$A:$A,Planilha2!E:E,"") -> 0 | AM21: =_xlfn.XLOOKUP(Tabela5[[#This Row],[UUID]],Planilha2!$A:$A,Planilha2!F:F,"") -> 1 | AN21: =_xlfn.XLOOKUP(Tabela5[[#This Row],[UUID]],Planilha2!$A:$A,Planilha2!G:G,"") -> 1 | AO21: =_xlfn.XLOOKUP(Tabela5[[#This Row],[UUID]],Planilha2!$A:$A,Planilha2!H:H,"") -> 0 | AP21: =_xlfn.XLOOKUP(Tabela5[[#This Row],[UUID]],Planilha2!$A:$A,Planilha2!I:I,"") -> 0 | AQ21: =_xlfn.XLOOKUP(Tabela5[[#This Row],[UUID]],Planilha2!$A:$A,Planilha2!J:J,"") -> 0 | AR21: =_xlfn.XLOOKUP(Tabela5[[#This Row],[UUID]],Planilha2!$A:$A,Planilha2!K:K,"") -> 0 | AS21: =_xlfn.XLOOKUP(Tabela5[[#This Row],[UUID]],Planilha2!$A:$A,Planilha2!L:L,"") -> 0 | AT21: =_xlfn.XLOOKUP(Tabela5[[#This Row],[UUID]],Planilha2!$A:$A,Planilha2!M:M,"") -> 0 | AU21: =_xlfn.XLOOKUP(Tabela5[[#This Row],[UUID]],Planilha2!$A:$A,Planilha2!N:N,"") -> 1 | AV21: =_xlfn.XLOOKUP(Tabela5[[#This Row],[UUID]],Planilha2!$A:$A,Planilha2!O:O,"") -> 1
A22: COB-242471 | B22: Faturado | C22: 4320722 | D22: 13609424591 | E22: JOAQUIM SIQUEIRA DA SILVA | F22: RUA DA SERRINHA 5 ITACARANHASALVADOR Salvador BA 40713-354 | G22: ADE-13770-Y7W6V9 | H22: 46082 | I22: 202603 | J22: 369.50652 | L22: 369.51 | N22: 90520359 | O22: 46101 | P22: 46111 | R22: 15 | S22: 2 - CPF | T22: Em aberto - Vencido | U22: Em aberto - Vencido | V22: E5OOKMY | W22: 6 | X22: false | Y22: 6 | Z22: Em aberto - Vencido | AA22: ASSOCIAÇÃO BA ? L1 | AB22: 35.686.965/0001-64 - ALEXANDRIA TECH | AC22: Estimado | AE22: 1 a 30 dias | AF22: 21d4813a-c6fc-4a13-b8dd-bd9ec6e50911 | AG22: 46115 | AH22: 1 a 30 dias | AI22: =_xlfn.XLOOKUP(Tabela5[[#This Row],[UUID]],Planilha2!$A:$A,Planilha2!B:B,"") -> 1 | AJ22: =_xlfn.XLOOKUP(Tabela5[[#This Row],[UUID]],Planilha2!$A:$A,Planilha2!C:C,"") -> 1 | AK22: =_xlfn.XLOOKUP(Tabela5[[#This Row],[UUID]],Planilha2!$A:$A,Planilha2!D:D,"") -> 10 | AL22: =_xlfn.XLOOKUP(Tabela5[[#This Row],[UUID]],Planilha2!$A:$A,Planilha2!E:E,"") -> 0 | AM22: =_xlfn.XLOOKUP(Tabela5[[#This Row],[UUID]],Planilha2!$A:$A,Planilha2!F:F,"") -> 1 | AN22: =_xlfn.XLOOKUP(Tabela5[[#This Row],[UUID]],Planilha2!$A:$A,Planilha2!G:G,"") -> 1 | AO22: =_xlfn.XLOOKUP(Tabela5[[#This Row],[UUID]],Planilha2!$A:$A,Planilha2!H:H,"") -> 0 | AP22: =_xlfn.XLOOKUP(Tabela5[[#This Row],[UUID]],Planilha2!$A:$A,Planilha2!I:I,"") -> 0 | AQ22: =_xlfn.XLOOKUP(Tabela5[[#This Row],[UUID]],Planilha2!$A:$A,Planilha2!J:J,"") -> 0 | AR22: =_xlfn.XLOOKUP(Tabela5[[#This Row],[UUID]],Planilha2!$A:$A,Planilha2!K:K,"") -> 0 | AS22: =_xlfn.XLOOKUP(Tabela5[[#This Row],[UUID]],Planilha2!$A:$A,Planilha2!L:L,"") -> 0 | AT22: =_xlfn.XLOOKUP(Tabela5[[#This Row],[UUID]],Planilha2!$A:$A,Planilha2!M:M,"") -> 0 | AU22: =_xlfn.XLOOKUP(Tabela5[[#This Row],[UUID]],Planilha2!$A:$A,Planilha2!N:N,"") -> 1 | AV22: =_xlfn.XLOOKUP(Tabela5[[#This Row],[UUID]],Planilha2!$A:$A,Planilha2!O:O,"") -> 1
A23: COB-125895 | B23: Faturado | C23: 150948667 | D23: 2068774712 | E23: MEYLERLOURDES FERREIRA MIRANDA LEITE | F23: RUA KARINA TATIANE SAMPAIO 60 PROV. OBRA 12000-000 RES ESTORIL / TAUBATE - SP | G23: ADE-12436-P7V0B7 | H23: 45839 | I23: 202507 | J23: 140.76911 | L23: 140.77 | N23: 90364317 | O23: 45916 | P23: 45926 | R23: 200 | S23: 2 - CPF | T23: Em aberto - Vencido | U23: Em aberto - Vencido | V23: 7QJ7R1K | W23: 6 | X23: false | Y23: 6 | Z23: Em aberto - Vencido | AA23: ASSOCIAÇÃO SP-L3 | AB23: 35.686.965/0001-64 - ALEXANDRIA TECH | AE23: 171 a 450 dias | AF23: ffcbc6dd-50fe-4475-a0c9-f22d2c728140 | AG23: 45965 | AH23: Maior que 90 | AI23: =_xlfn.XLOOKUP(Tabela5[[#This Row],[UUID]],Planilha2!$A:$A,Planilha2!B:B,"") -> 0 | AJ23: =_xlfn.XLOOKUP(Tabela5[[#This Row],[UUID]],Planilha2!$A:$A,Planilha2!C:C,"") -> 0 | AK23: =_xlfn.XLOOKUP(Tabela5[[#This Row],[UUID]],Planilha2!$A:$A,Planilha2!D:D,"") -> 0 | AL23: =_xlfn.XLOOKUP(Tabela5[[#This Row],[UUID]],Planilha2!$A:$A,Planilha2!E:E,"") -> 5 | AM23: =_xlfn.XLOOKUP(Tabela5[[#This Row],[UUID]],Planilha2!$A:$A,Planilha2!F:F,"") -> 0 | AN23: =_xlfn.XLOOKUP(Tabela5[[#This Row],[UUID]],Planilha2!$A:$A,Planilha2!G:G,"") -> 0 | AO23: =_xlfn.XLOOKUP(Tabela5[[#This Row],[UUID]],Planilha2!$A:$A,Planilha2!H:H,"") -> 0 | AP23: =_xlfn.XLOOKUP(Tabela5[[#This Row],[UUID]],Planilha2!$A:$A,Planilha2!I:I,"") -> 0 | AQ23: =_xlfn.XLOOKUP(Tabela5[[#This Row],[UUID]],Planilha2!$A:$A,Planilha2!J:J,"") -> 0 | AR23: =_xlfn.XLOOKUP(Tabela5[[#This Row],[UUID]],Planilha2!$A:$A,Planilha2!K:K,"") -> 0 | AS23: =_xlfn.XLOOKUP(Tabela5[[#This Row],[UUID]],Planilha2!$A:$A,Planilha2!L:L,"") -> 0 | AT23: =_xlfn.XLOOKUP(Tabela5[[#This Row],[UUID]],Planilha2!$A:$A,Planilha2!M:M,"") -> 0 | AU23: =_xlfn.XLOOKUP(Tabela5[[#This Row],[UUID]],Planilha2!$A:$A,Planilha2!N:N,"") -> 0 | AV23: =_xlfn.XLOOKUP(Tabela5[[#This Row],[UUID]],Planilha2!$A:$A,Planilha2!O:O,"") -> 0
A24: COB-242467 | B24: Faturado | C24: 30203351 | D24: 82265135534 | E24: ALTAIR EDUARDO SANTANA GOMES | F24: RUA PAU MIUDO 34 Pau Miúdo Euclides da Cunha BA 48500-000 | G24: ADE-13750-N0J4N2 | H24: 46082 | I24: 202603 | J24: 221.19146 | L24: 221.19 | N24: 90520356 | O24: 46101 | P24: 46111 | R24: 15 | S24: 2 - CPF | T24: Em aberto - Vencido | U24: Em aberto - Vencido | V24: LIMD0A9 | W24: 6 | X24: false | Y24: 6 | Z24: Em aberto - Vencido | AA24: ASSOCIAÇÃO BA ? L1 | AB24: 35.686.965/0001-64 - ALEXANDRIA TECH | AC24: Estimado | AE24: 1 a 30 dias | AF24: 701f3a48-9f07-44a6-9386-8487d816d1e7 | AG24: 46115 | AH24: 1 a 30 dias | AI24: =_xlfn.XLOOKUP(Tabela5[[#This Row],[UUID]],Planilha2!$A:$A,Planilha2!B:B,"") -> 1 | AJ24: =_xlfn.XLOOKUP(Tabela5[[#This Row],[UUID]],Planilha2!$A:$A,Planilha2!C:C,"") -> 1 | AK24: =_xlfn.XLOOKUP(Tabela5[[#This Row],[UUID]],Planilha2!$A:$A,Planilha2!D:D,"") -> 12 | AL24: =_xlfn.XLOOKUP(Tabela5[[#This Row],[UUID]],Planilha2!$A:$A,Planilha2!E:E,"") -> 0 | AM24: =_xlfn.XLOOKUP(Tabela5[[#This Row],[UUID]],Planilha2!$A:$A,Planilha2!F:F,"") -> 1 | AN24: =_xlfn.XLOOKUP(Tabela5[[#This Row],[UUID]],Planilha2!$A:$A,Planilha2!G:G,"") -> 1 | AO24: =_xlfn.XLOOKUP(Tabela5[[#This Row],[UUID]],Planilha2!$A:$A,Planilha2!H:H,"") -> 0 | AP24: =_xlfn.XLOOKUP(Tabela5[[#This Row],[UUID]],Planilha2!$A:$A,Planilha2!I:I,"") -> 0 | AQ24: =_xlfn.XLOOKUP(Tabela5[[#This Row],[UUID]],Planilha2!$A:$A,Planilha2!J:J,"") -> 0 | AR24: =_xlfn.XLOOKUP(Tabela5[[#This Row],[UUID]],Planilha2!$A:$A,Planilha2!K:K,"") -> 0 | AS24: =_xlfn.XLOOKUP(Tabela5[[#This Row],[UUID]],Planilha2!$A:$A,Planilha2!L:L,"") -> 0 | AT24: =_xlfn.XLOOKUP(Tabela5[[#This Row],[UUID]],Planilha2!$A:$A,Planilha2!M:M,"") -> 0 | AU24: =_xlfn.XLOOKUP(Tabela5[[#This Row],[UUID]],Planilha2!$A:$A,Planilha2!N:N,"") -> 1 | AV24: =_xlfn.XLOOKUP(Tabela5[[#This Row],[UUID]],Planilha2!$A:$A,Planilha2!O:O,"") -> 1
A25: COB-145312 | B25: Faturado | C25: 37630636 | D25: 376041986 | E25: ALEX SANDRO MIRANDA DE JESUS | F25: R MANOEL RIBAS, 85 NOSSO TETO 16370-000 PROMISSAO - SP | G25: ADE-11673-K1L8Y8 | H25: 45839 | I25: 202507 | J25: 24.08116 | L25: 24.08 | N25: 90364814 | O25: 45918 | P25: 45929 | R25: 197 | S25: 2 - CPF | T25: Em aberto - Vencido | U25: Em aberto - Vencido | V25: A4ASJ7B | W25: 6 | X25: false | Y25: 6 | Z25: Em aberto - Vencido | AA25: ASSOCIACAO SP-L2 | AB25: 35.686.965/0001-64 - ALEXANDRIA TECH | AE25: 171 a 450 dias | AF25: fba0a144-c4d4-4a18-8d90-ba314fbdfadc | AG25: 45929 | AH25: Maior que 90 | AI25: =_xlfn.XLOOKUP(Tabela5[[#This Row],[UUID]],Planilha2!$A:$A,Planilha2!B:B,"") -> 0 | AJ25: =_xlfn.XLOOKUP(Tabela5[[#This Row],[UUID]],Planilha2!$A:$A,Planilha2!C:C,"") -> 0 | AK25: =_xlfn.XLOOKUP(Tabela5[[#This Row],[UUID]],Planilha2!$A:$A,Planilha2!D:D,"") -> 0 | AL25: =_xlfn.XLOOKUP(Tabela5[[#This Row],[UUID]],Planilha2!$A:$A,Planilha2!E:E,"") -> 5 | AM25: =_xlfn.XLOOKUP(Tabela5[[#This Row],[UUID]],Planilha2!$A:$A,Planilha2!F:F,"") -> 0 | AN25: =_xlfn.XLOOKUP(Tabela5[[#This Row],[UUID]],Planilha2!$A:$A,Planilha2!G:G,"") -> 0 | AO25: =_xlfn.XLOOKUP(Tabela5[[#This Row],[UUID]],Planilha2!$A:$A,Planilha2!H:H,"") -> 0 | AP25: =_xlfn.XLOOKUP(Tabela5[[#This Row],[UUID]],Planilha2!$A:$A,Planilha2!I:I,"") -> 0 | AQ25: =_xlfn.XLOOKUP(Tabela5[[#This Row],[UUID]],Planilha2!$A:$A,Planilha2!J:J,"") -> 0 | AR25: =_xlfn.XLOOKUP(Tabela5[[#This Row],[UUID]],Planilha2!$A:$A,Planilha2!K:K,"") -> 0 | AS25: =_xlfn.XLOOKUP(Tabela5[[#This Row],[UUID]],Planilha2!$A:$A,Planilha2!L:L,"") -> 0 | AT25: =_xlfn.XLOOKUP(Tabela5[[#This Row],[UUID]],Planilha2!$A:$A,Planilha2!M:M,"") -> 0 | AU25: =_xlfn.XLOOKUP(Tabela5[[#This Row],[UUID]],Planilha2!$A:$A,Planilha2!N:N,"") -> 0 | AV25: =_xlfn.XLOOKUP(Tabela5[[#This Row],[UUID]],Planilha2!$A:$A,Planilha2!O:O,"") -> 0
A26: COB-242377 | B26: Faturado | C26: 3261505 | D26: 25503693515 | E26: NELTON JOSE LOPES FREIRE | F26: RUA A 2 CENTRO-MATA DE SAO JOAO/MATA DE SAO JOAO Mata de São João BA 48280-000 | G26: ADE-13130-V4K3X8 | H26: 46082 | I26: 202603 | J26: 186.15803 | L26: 186.16 | N26: 90520495 | O26: 46101 | P26: 46111 | R26: 15 | S26: 2 - CPF | T26: Em aberto - Vencido | U26: Em aberto - Vencido | V26: SSGJT1R | W26: 6 | X26: false | Y26: 6 | Z26: Em aberto - Vencido | AA26: ASSOCIAÇÃO BA ? L1 | AB26: 35.686.965/0001-64 - ALEXANDRIA TECH | AC26: Estimado | AE26: 1 a 30 dias | AF26: 4e0cdf25-bc3d-4e05-b42c-82b541814bf6 | AG26: 46115 | AH26: 1 a 30 dias | AI26: =_xlfn.XLOOKUP(Tabela5[[#This Row],[UUID]],Planilha2!$A:$A,Planilha2!B:B,"") -> 1 | AJ26: =_xlfn.XLOOKUP(Tabela5[[#This Row],[UUID]],Planilha2!$A:$A,Planilha2!C:C,"") -> 1 | AK26: =_xlfn.XLOOKUP(Tabela5[[#This Row],[UUID]],Planilha2!$A:$A,Planilha2!D:D,"") -> 1 | AL26: =_xlfn.XLOOKUP(Tabela5[[#This Row],[UUID]],Planilha2!$A:$A,Planilha2!E:E,"") -> 0 | AM26: =_xlfn.XLOOKUP(Tabela5[[#This Row],[UUID]],Planilha2!$A:$A,Planilha2!F:F,"") -> 1 | AN26: =_xlfn.XLOOKUP(Tabela5[[#This Row],[UUID]],Planilha2!$A:$A,Planilha2!G:G,"") -> 1 | AO26: =_xlfn.XLOOKUP(Tabela5[[#This Row],[UUID]],Planilha2!$A:$A,Planilha2!H:H,"") -> 0 | AP26: =_xlfn.XLOOKUP(Tabela5[[#This Row],[UUID]],Planilha2!$A:$A,Planilha2!I:I,"") -> 0 | AQ26: =_xlfn.XLOOKUP(Tabela5[[#This Row],[UUID]],Planilha2!$A:$A,Planilha2!J:J,"") -> 0 | AR26: =_xlfn.XLOOKUP(Tabela5[[#This Row],[UUID]],Planilha2!$A:$A,Planilha2!K:K,"") -> 0 | AS26: =_xlfn.XLOOKUP(Tabela5[[#This Row],[UUID]],Planilha2!$A:$A,Planilha2!L:L,"") -> 0 | AT26: =_xlfn.XLOOKUP(Tabela5[[#This Row],[UUID]],Planilha2!$A:$A,Planilha2!M:M,"") -> 0 | AU26: =_xlfn.XLOOKUP(Tabela5[[#This Row],[UUID]],Planilha2!$A:$A,Planilha2!N:N,"") -> 1 | AV26: =_xlfn.XLOOKUP(Tabela5[[#This Row],[UUID]],Planilha2!$A:$A,Planilha2!O:O,"") -> 1
A27: COB-242353 | B27: Faturado | C27: 4210058 | D27: 78547105549 | E27: ALEX CARLOS TRINDADE BRITO | F27: RUA CRISTOVAO FERREIRA 66 ZZ Ap 1 Boca do Rio Salvador BA 41710-030 | G27: ADE-13030-G5R4W4 | H27: 46082 | I27: 202603 | J27: 199.89663 | L27: 199.9 | N27: 90520465 | O27: 46101 | P27: 46111 | R27: 15 | S27: 2 - CPF | T27: Em aberto - Vencido | U27: Em aberto - Vencido | V27: 8Y36H6M | Y27: 6 | Z27: NA | AA27: ASSOCIAÇÃO BA ? L1 | AB27: 35.686.965/0001-64 - ALEXANDRIA TECH | AC27: Estimado | AE27: 1 a 30 dias | AF27: 5a6df157-18b3-4643-a1c4-2d9d96469901 | AG27: 46115 | AH27: 1 a 30 dias | AI27: =_xlfn.XLOOKUP(Tabela5[[#This Row],[UUID]],Planilha2!$A:$A,Planilha2!B:B,"") -> 1 | AJ27: =_xlfn.XLOOKUP(Tabela5[[#This Row],[UUID]],Planilha2!$A:$A,Planilha2!C:C,"") -> 1 | AK27: =_xlfn.XLOOKUP(Tabela5[[#This Row],[UUID]],Planilha2!$A:$A,Planilha2!D:D,"") -> 1 | AL27: =_xlfn.XLOOKUP(Tabela5[[#This Row],[UUID]],Planilha2!$A:$A,Planilha2!E:E,"") -> 0 | AM27: =_xlfn.XLOOKUP(Tabela5[[#This Row],[UUID]],Planilha2!$A:$A,Planilha2!F:F,"") -> 1 | AN27: =_xlfn.XLOOKUP(Tabela5[[#This Row],[UUID]],Planilha2!$A:$A,Planilha2!G:G,"") -> 1 | AO27: =_xlfn.XLOOKUP(Tabela5[[#This Row],[UUID]],Planilha2!$A:$A,Planilha2!H:H,"") -> 0 | AP27: =_xlfn.XLOOKUP(Tabela5[[#This Row],[UUID]],Planilha2!$A:$A,Planilha2!I:I,"") -> 0 | AQ27: =_xlfn.XLOOKUP(Tabela5[[#This Row],[UUID]],Planilha2!$A:$A,Planilha2!J:J,"") -> 0 | AR27: =_xlfn.XLOOKUP(Tabela5[[#This Row],[UUID]],Planilha2!$A:$A,Planilha2!K:K,"") -> 0 | AS27: =_xlfn.XLOOKUP(Tabela5[[#This Row],[UUID]],Planilha2!$A:$A,Planilha2!L:L,"") -> 0 | AT27: =_xlfn.XLOOKUP(Tabela5[[#This Row],[UUID]],Planilha2!$A:$A,Planilha2!M:M,"") -> 0 | AU27: =_xlfn.XLOOKUP(Tabela5[[#This Row],[UUID]],Planilha2!$A:$A,Planilha2!N:N,"") -> 1 | AV27: =_xlfn.XLOOKUP(Tabela5[[#This Row],[UUID]],Planilha2!$A:$A,Planilha2!O:O,"") -> 1
A28: COB-242347 | B28: Faturado | C28: 3280767 | D28: 15833232520 | E28: CARLOS ANTUNES SILVA PEREIRA | F28: Rua Esbela Costa 0 Medeiros Neto Medeiros Neto BA 45960-000 | G28: ADE-13016-P4B5T7 | H28: 46082 | I28: 202603 | J28: 265.84191 | L28: 265.84 | N28: 90520306 | O28: 46101 | P28: 46111 | R28: 15 | S28: 2 - CPF | T28: Em aberto - Vencido | U28: Em aberto - Vencido | V28: 67W9BRH | W28: 6 | X28: false | Y28: 6 | Z28: Em aberto - Vencido | AA28: ASSOCIAÇÃO BA ? L1 | AB28: 35.686.965/0001-64 - ALEXANDRIA TECH | AC28: Estimado | AE28: 1 a 30 dias | AF28: 8b73fa3c-1273-4a87-8e7f-1331613320a1 | AG28: 46115 | AH28: 1 a 30 dias | AI28: =_xlfn.XLOOKUP(Tabela5[[#This Row],[UUID]],Planilha2!$A:$A,Planilha2!B:B,"") -> 1 | AJ28: =_xlfn.XLOOKUP(Tabela5[[#This Row],[UUID]],Planilha2!$A:$A,Planilha2!C:C,"") -> 1 | AK28: =_xlfn.XLOOKUP(Tabela5[[#This Row],[UUID]],Planilha2!$A:$A,Planilha2!D:D,"") -> 10 | AL28: =_xlfn.XLOOKUP(Tabela5[[#This Row],[UUID]],Planilha2!$A:$A,Planilha2!E:E,"") -> 0 | AM28: =_xlfn.XLOOKUP(Tabela5[[#This Row],[UUID]],Planilha2!$A:$A,Planilha2!F:F,"") -> 1 | AN28: =_xlfn.XLOOKUP(Tabela5[[#This Row],[UUID]],Planilha2!$A:$A,Planilha2!G:G,"") -> 1 | AO28: =_xlfn.XLOOKUP(Tabela5[[#This Row],[UUID]],Planilha2!$A:$A,Planilha2!H:H,"") -> 0 | AP28: =_xlfn.XLOOKUP(Tabela5[[#This Row],[UUID]],Planilha2!$A:$A,Planilha2!I:I,"") -> 0 | AQ28: =_xlfn.XLOOKUP(Tabela5[[#This Row],[UUID]],Planilha2!$A:$A,Planilha2!J:J,"") -> 0 | AR28: =_xlfn.XLOOKUP(Tabela5[[#This Row],[UUID]],Planilha2!$A:$A,Planilha2!K:K,"") -> 0 | AS28: =_xlfn.XLOOKUP(Tabela5[[#This Row],[UUID]],Planilha2!$A:$A,Planilha2!L:L,"") -> 0 | AT28: =_xlfn.XLOOKUP(Tabela5[[#This Row],[UUID]],Planilha2!$A:$A,Planilha2!M:M,"") -> 0 | AU28: =_xlfn.XLOOKUP(Tabela5[[#This Row],[UUID]],Planilha2!$A:$A,Planilha2!N:N,"") -> 1 | AV28: =_xlfn.XLOOKUP(Tabela5[[#This Row],[UUID]],Planilha2!$A:$A,Planilha2!O:O,"") -> 1
A29: COB-242338 | B29: Faturado | C29: 9809902 | D29: 2759407560 | E29: RILDO MARQUES DE ARAUJO FILHO | F29: RUA COLONIA BOA UNIAO 99 Reserva Parque Camaçari BA 42821-900 | G29: ADE-12992-R9Y8N0 | H29: 46082 | I29: 202603 | J29: 315.9878 | L29: 315.99 | N29: 90520494 | O29: 46101 | P29: 46111 | R29: 15 | S29: 2 - CPF | T29: Em aberto - Vencido | U29: Em aberto - Vencido | V29: 6KH4DY5 | W29: 6 | X29: false | Y29: 6 | Z29: Em aberto - Vencido | AA29: ASSOCIAÇÃO BA ? L1 | AB29: 35.686.965/0001-64 - ALEXANDRIA TECH | AC29: Estimado | AE29: 1 a 30 dias | AF29: 5de7aebf-cef5-49dd-b92a-5439104b3a49 | AG29: 46117 | AH29: 1 a 30 dias | AI29: =_xlfn.XLOOKUP(Tabela5[[#This Row],[UUID]],Planilha2!$A:$A,Planilha2!B:B,"") -> 1 | AJ29: =_xlfn.XLOOKUP(Tabela5[[#This Row],[UUID]],Planilha2!$A:$A,Planilha2!C:C,"") -> 1 | AK29: =_xlfn.XLOOKUP(Tabela5[[#This Row],[UUID]],Planilha2!$A:$A,Planilha2!D:D,"") -> 1 | AL29: =_xlfn.XLOOKUP(Tabela5[[#This Row],[UUID]],Planilha2!$A:$A,Planilha2!E:E,"") -> 0 | AM29: =_xlfn.XLOOKUP(Tabela5[[#This Row],[UUID]],Planilha2!$A:$A,Planilha2!F:F,"") -> 1 | AN29: =_xlfn.XLOOKUP(Tabela5[[#This Row],[UUID]],Planilha2!$A:$A,Planilha2!G:G,"") -> 0 | AO29: =_xlfn.XLOOKUP(Tabela5[[#This Row],[UUID]],Planilha2!$A:$A,Planilha2!H:H,"") -> 0 | AP29: =_xlfn.XLOOKUP(Tabela5[[#This Row],[UUID]],Planilha2!$A:$A,Planilha2!I:I,"") -> 0 | AQ29: =_xlfn.XLOOKUP(Tabela5[[#This Row],[UUID]],Planilha2!$A:$A,Planilha2!J:J,"") -> 0 | AR29: =_xlfn.XLOOKUP(Tabela5[[#This Row],[UUID]],Planilha2!$A:$A,Planilha2!K:K,"") -> 0 | AS29: =_xlfn.XLOOKUP(Tabela5[[#This Row],[UUID]],Planilha2!$A:$A,Planilha2!L:L,"") -> 0 | AT29: =_xlfn.XLOOKUP(Tabela5[[#This Row],[UUID]],Planilha2!$A:$A,Planilha2!M:M,"") -> 1 | AU29: =_xlfn.XLOOKUP(Tabela5[[#This Row],[UUID]],Planilha2!$A:$A,Planilha2!N:N,"") -> 1 | AV29: =_xlfn.XLOOKUP(Tabela5[[#This Row],[UUID]],Planilha2!$A:$A,Planilha2!O:O,"") -> 1
A30: COB-242332 | B30: Faturado | C30: 2639964 | D30: 91328110559 | E30: CICERO CONCEICAO DA HORA | F30: RUA MELLO LEITE 30 CENTRO Ituberá BA 45435-000 | G30: ADE-12940-K4M4L2 | H30: 46082 | I30: 202603 | J30: 279.58051 | L30: 279.58 | N30: 90520464 | O30: 46101 | P30: 46111 | R30: 15 | S30: 2 - CPF | T30: Em aberto - Vencido | U30: Em aberto - Vencido | V30: UK8F9T0 | W30: 6 | X30: false | Y30: 6 | Z30: Em aberto - Vencido | AA30: ASSOCIAÇÃO BA ? L1 | AB30: 35.686.965/0001-64 - ALEXANDRIA TECH | AC30: Estimado | AE30: 1 a 30 dias | AF30: 3633625c-63e3-4b5e-8083-e5fe427051b3 | AG30: 46120 | AH30: 1 a 30 dias | AI30: =_xlfn.XLOOKUP(Tabela5[[#This Row],[UUID]],Planilha2!$A:$A,Planilha2!B:B,"") -> 1 | AJ30: =_xlfn.XLOOKUP(Tabela5[[#This Row],[UUID]],Planilha2!$A:$A,Planilha2!C:C,"") -> 1 | AK30: =_xlfn.XLOOKUP(Tabela5[[#This Row],[UUID]],Planilha2!$A:$A,Planilha2!D:D,"") -> 1 | AL30: =_xlfn.XLOOKUP(Tabela5[[#This Row],[UUID]],Planilha2!$A:$A,Planilha2!E:E,"") -> 0 | AM30: =_xlfn.XLOOKUP(Tabela5[[#This Row],[UUID]],Planilha2!$A:$A,Planilha2!F:F,"") -> 1 | AN30: =_xlfn.XLOOKUP(Tabela5[[#This Row],[UUID]],Planilha2!$A:$A,Planilha2!G:G,"") -> 0 | AO30: =_xlfn.XLOOKUP(Tabela5[[#This Row],[UUID]],Planilha2!$A:$A,Planilha2!H:H,"") -> 0 | AP30: =_xlfn.XLOOKUP(Tabela5[[#This Row],[UUID]],Planilha2!$A:$A,Planilha2!I:I,"") -> 0 | AQ30: =_xlfn.XLOOKUP(Tabela5[[#This Row],[UUID]],Planilha2!$A:$A,Planilha2!J:J,"") -> 0 | AR30: =_xlfn.XLOOKUP(Tabela5[[#This Row],[UUID]],Planilha2!$A:$A,Planilha2!K:K,"") -> 0 | AS30: =_xlfn.XLOOKUP(Tabela5[[#This Row],[UUID]],Planilha2!$A:$A,Planilha2!L:L,"") -> 0 | AT30: =_xlfn.XLOOKUP(Tabela5[[#This Row],[UUID]],Planilha2!$A:$A,Planilha2!M:M,"") -> 0 | AU30: =_xlfn.XLOOKUP(Tabela5[[#This Row],[UUID]],Planilha2!$A:$A,Planilha2!N:N,"") -> 1 | AV30: =_xlfn.XLOOKUP(Tabela5[[#This Row],[UUID]],Planilha2!$A:$A,Planilha2!O:O,"") -> 1
A31: COB-242326 | B31: Faturado | C31: 10322348 | D31: 94738220578 | E31: JAILSON GUIMARAES PINHEIRO | F31: Rua Melvin Jones 147 AP- 1104 ED ACQUA MARINE RESIDENCIAL Jardim Armação Salvador BA 41750-010 | G31: ADE-12898-Z7W9R9 | H31: 46082 | I31: 202603 | J31: 514.51057 | L31: 514.51 | N31: 90520233 | O31: 46101 | P31: 46111 | R31: 15 | S31: 2 - CPF | T31: Em aberto - Vencido | U31: Em aberto - Vencido | V31: S8J68XB | W31: 6 | X31: false | Y31: 6 | Z31: Em aberto - Vencido | AA31: ASSOCIAÇÃO BA ? L1 | AB31: 35.686.965/0001-64 - ALEXANDRIA TECH | AC31: Estimado | AE31: 1 a 30 dias | AF31: 57da7b8d-f0e3-480d-9c91-b54adbb3b304 | AG31: 46115 | AH31: 1 a 30 dias | AI31: =_xlfn.XLOOKUP(Tabela5[[#This Row],[UUID]],Planilha2!$A:$A,Planilha2!B:B,"") -> 1 | AJ31: =_xlfn.XLOOKUP(Tabela5[[#This Row],[UUID]],Planilha2!$A:$A,Planilha2!C:C,"") -> 1 | AK31: =_xlfn.XLOOKUP(Tabela5[[#This Row],[UUID]],Planilha2!$A:$A,Planilha2!D:D,"") -> 10 | AL31: =_xlfn.XLOOKUP(Tabela5[[#This Row],[UUID]],Planilha2!$A:$A,Planilha2!E:E,"") -> 0 | AM31: =_xlfn.XLOOKUP(Tabela5[[#This Row],[UUID]],Planilha2!$A:$A,Planilha2!F:F,"") -> 1 | AN31: =_xlfn.XLOOKUP(Tabela5[[#This Row],[UUID]],Planilha2!$A:$A,Planilha2!G:G,"") -> 1 | AO31: =_xlfn.XLOOKUP(Tabela5[[#This Row],[UUID]],Planilha2!$A:$A,Planilha2!H:H,"") -> 0 | AP31: =_xlfn.XLOOKUP(Tabela5[[#This Row],[UUID]],Planilha2!$A:$A,Planilha2!I:I,"") -> 0 | AQ31: =_xlfn.XLOOKUP(Tabela5[[#This Row],[UUID]],Planilha2!$A:$A,Planilha2!J:J,"") -> 0 | AR31: =_xlfn.XLOOKUP(Tabela5[[#This Row],[UUID]],Planilha2!$A:$A,Planilha2!K:K,"") -> 0 | AS31: =_xlfn.XLOOKUP(Tabela5[[#This Row],[UUID]],Planilha2!$A:$A,Planilha2!L:L,"") -> 0 | AT31: =_xlfn.XLOOKUP(Tabela5[[#This Row],[UUID]],Planilha2!$A:$A,Planilha2!M:M,"") -> 0 | AU31: =_xlfn.XLOOKUP(Tabela5[[#This Row],[UUID]],Planilha2!$A:$A,Planilha2!N:N,"") -> 1 | AV31: =_xlfn.XLOOKUP(Tabela5[[#This Row],[UUID]],Planilha2!$A:$A,Planilha2!O:O,"") -> 1
A32: COB-242325 | B32: Faturado | C32: 30143921 | D32: 52905624868 | E32: JOSE SOARES DA SILVA | F32: Rua 11 11 a Lot Vila Elisa Vitória da Conquista BA 45038-130 | G32: ADE-12894-B0R6Z1 | H32: 46082 | I32: 202603 | J32: 201.95742 | L32: 201.96 | N32: 90520285 | O32: 46101 | P32: 46111 | R32: 15 | S32: 2 - CPF | T32: Em aberto - Vencido | U32: Em aberto - Vencido | V32: YXDZ0ZE | W32: 6 | X32: false | Y32: 6 | Z32: Em aberto - Vencido | AA32: ASSOCIAÇÃO BA ? L1 | AB32: 35.686.965/0001-64 - ALEXANDRIA TECH | AC32: Estimado | AE32: 1 a 30 dias | AF32: cd74d20b-b1ea-42fb-9ee6-2065d9ae8cab | AG32: 46119 | AH32: 1 a 30 dias | AI32: =_xlfn.XLOOKUP(Tabela5[[#This Row],[UUID]],Planilha2!$A:$A,Planilha2!B:B,"") -> 1 | AJ32: =_xlfn.XLOOKUP(Tabela5[[#This Row],[UUID]],Planilha2!$A:$A,Planilha2!C:C,"") -> 1 | AK32: =_xlfn.XLOOKUP(Tabela5[[#This Row],[UUID]],Planilha2!$A:$A,Planilha2!D:D,"") -> 1 | AL32: =_xlfn.XLOOKUP(Tabela5[[#This Row],[UUID]],Planilha2!$A:$A,Planilha2!E:E,"") -> 0 | AM32: =_xlfn.XLOOKUP(Tabela5[[#This Row],[UUID]],Planilha2!$A:$A,Planilha2!F:F,"") -> 1 | AN32: =_xlfn.XLOOKUP(Tabela5[[#This Row],[UUID]],Planilha2!$A:$A,Planilha2!G:G,"") -> 0 | AO32: =_xlfn.XLOOKUP(Tabela5[[#This Row],[UUID]],Planilha2!$A:$A,Planilha2!H:H,"") -> 0 | AP32: =_xlfn.XLOOKUP(Tabela5[[#This Row],[UUID]],Planilha2!$A:$A,Planilha2!I:I,"") -> 0 | AQ32: =_xlfn.XLOOKUP(Tabela5[[#This Row],[UUID]],Planilha2!$A:$A,Planilha2!J:J,"") -> 0 | AR32: =_xlfn.XLOOKUP(Tabela5[[#This Row],[UUID]],Planilha2!$A:$A,Planilha2!K:K,"") -> 0 | AS32: =_xlfn.XLOOKUP(Tabela5[[#This Row],[UUID]],Planilha2!$A:$A,Planilha2!L:L,"") -> 0 | AT32: =_xlfn.XLOOKUP(Tabela5[[#This Row],[UUID]],Planilha2!$A:$A,Planilha2!M:M,"") -> 1 | AU32: =_xlfn.XLOOKUP(Tabela5[[#This Row],[UUID]],Planilha2!$A:$A,Planilha2!N:N,"") -> 1 | AV32: =_xlfn.XLOOKUP(Tabela5[[#This Row],[UUID]],Planilha2!$A:$A,Planilha2!O:O,"") -> 1
A33: COB-242323 | B33: Faturado | C33: 90034872 | D33: 3921564581 | E33: WECKSLLEY SANTOS E SANTOS | F33: RUA JUVENCIO PERI LIMA 29 A Centro Coaraci BA 45638-000 | G33: ADE-12890-Z0D2G2 | H33: 46082 | I33: 202603 | J33: 482.91179 | L33: 482.91 | N33: 90520492 | O33: 46101 | P33: 46111 | R33: 15 | S33: 2 - CPF | T33: Em aberto - Vencido | U33: Em aberto - Vencido | V33: XB9O08D | W33: 6 | X33: false | Y33: 6 | Z33: Em aberto - Vencido | AA33: ASSOCIAÇÃO BA ? L1 | AB33: 35.686.965/0001-64 - ALEXANDRIA TECH | AC33: Estimado | AE33: 1 a 30 dias | AF33: 4256b8f1-d225-440e-ad53-9d52a5a5b6ca | AG33: 46115 | AH33: 1 a 30 dias | AI33: =_xlfn.XLOOKUP(Tabela5[[#This Row],[UUID]],Planilha2!$A:$A,Planilha2!B:B,"") -> 1 | AJ33: =_xlfn.XLOOKUP(Tabela5[[#This Row],[UUID]],Planilha2!$A:$A,Planilha2!C:C,"") -> 1 | AK33: =_xlfn.XLOOKUP(Tabela5[[#This Row],[UUID]],Planilha2!$A:$A,Planilha2!D:D,"") -> 1 | AL33: =_xlfn.XLOOKUP(Tabela5[[#This Row],[UUID]],Planilha2!$A:$A,Planilha2!E:E,"") -> 0 | AM33: =_xlfn.XLOOKUP(Tabela5[[#This Row],[UUID]],Planilha2!$A:$A,Planilha2!F:F,"") -> 1 | AN33: =_xlfn.XLOOKUP(Tabela5[[#This Row],[UUID]],Planilha2!$A:$A,Planilha2!G:G,"") -> 1 | AO33: =_xlfn.XLOOKUP(Tabela5[[#This Row],[UUID]],Planilha2!$A:$A,Planilha2!H:H,"") -> 0 | AP33: =_xlfn.XLOOKUP(Tabela5[[#This Row],[UUID]],Planilha2!$A:$A,Planilha2!I:I,"") -> 0 | AQ33: =_xlfn.XLOOKUP(Tabela5[[#This Row],[UUID]],Planilha2!$A:$A,Planilha2!J:J,"") -> 0 | AR33: =_xlfn.XLOOKUP(Tabela5[[#This Row],[UUID]],Planilha2!$A:$A,Planilha2!K:K,"") -> 0 | AS33: =_xlfn.XLOOKUP(Tabela5[[#This Row],[UUID]],Planilha2!$A:$A,Planilha2!L:L,"") -> 0 | AT33: =_xlfn.XLOOKUP(Tabela5[[#This Row],[UUID]],Planilha2!$A:$A,Planilha2!M:M,"") -> 0 | AU33: =_xlfn.XLOOKUP(Tabela5[[#This Row],[UUID]],Planilha2!$A:$A,Planilha2!N:N,"") -> 1 | AV33: =_xlfn.XLOOKUP(Tabela5[[#This Row],[UUID]],Planilha2!$A:$A,Planilha2!O:O,"") -> 1
A34: COB-242320 | B34: Faturado | C34: 40252602 | D34: 27868063807 | E34: KARINA MAGALHAES WOLFF | F34: AT DA BOA VISTA 20 LADO SUL E LADO LESTE ALTO DA BOA VISTA Itacaré BA 45530-000 | G34: ADE-12879-B4D1H1 | H34: 46082 | I34: 202603 | J34: 401.16712 | L34: 401.17 | N34: 90520323 | O34: 46101 | P34: 46111 | R34: 15 | S34: 2 - CPF | T34: Em aberto - Vencido | U34: Em aberto - Vencido | V34: VK6JFIM | W34: 6 | X34: false | Y34: 6 | Z34: Em aberto - Vencido | AA34: ASSOCIAÇÃO BA ? L1 | AB34: 35.686.965/0001-64 - ALEXANDRIA TECH | AC34: Estimado | AE34: 1 a 30 dias | AF34: 4484875e-c79a-4da7-a12e-919abafba708 | AG34: 46115 | AH34: 1 a 30 dias | AI34: =_xlfn.XLOOKUP(Tabela5[[#This Row],[UUID]],Planilha2!$A:$A,Planilha2!B:B,"") -> 1 | AJ34: =_xlfn.XLOOKUP(Tabela5[[#This Row],[UUID]],Planilha2!$A:$A,Planilha2!C:C,"") -> 1 | AK34: =_xlfn.XLOOKUP(Tabela5[[#This Row],[UUID]],Planilha2!$A:$A,Planilha2!D:D,"") -> 1 | AL34: =_xlfn.XLOOKUP(Tabela5[[#This Row],[UUID]],Planilha2!$A:$A,Planilha2!E:E,"") -> 0 | AM34: =_xlfn.XLOOKUP(Tabela5[[#This Row],[UUID]],Planilha2!$A:$A,Planilha2!F:F,"") -> 1 | AN34: =_xlfn.XLOOKUP(Tabela5[[#This Row],[UUID]],Planilha2!$A:$A,Planilha2!G:G,"") -> 1 | AO34: =_xlfn.XLOOKUP(Tabela5[[#This Row],[UUID]],Planilha2!$A:$A,Planilha2!H:H,"") -> 0 | AP34: =_xlfn.XLOOKUP(Tabela5[[#This Row],[UUID]],Planilha2!$A:$A,Planilha2!I:I,"") -> 0 | AQ34: =_xlfn.XLOOKUP(Tabela5[[#This Row],[UUID]],Planilha2!$A:$A,Planilha2!J:J,"") -> 0 | AR34: =_xlfn.XLOOKUP(Tabela5[[#This Row],[UUID]],Planilha2!$A:$A,Planilha2!K:K,"") -> 0 | AS34: =_xlfn.XLOOKUP(Tabela5[[#This Row],[UUID]],Planilha2!$A:$A,Planilha2!L:L,"") -> 0 | AT34: =_xlfn.XLOOKUP(Tabela5[[#This Row],[UUID]],Planilha2!$A:$A,Planilha2!M:M,"") -> 0 | AU34: =_xlfn.XLOOKUP(Tabela5[[#This Row],[UUID]],Planilha2!$A:$A,Planilha2!N:N,"") -> 1 | AV34: =_xlfn.XLOOKUP(Tabela5[[#This Row],[UUID]],Planilha2!$A:$A,Planilha2!O:O,"") -> 1
A35: COB-242319 | B35: Faturado | C35: 9951748 | D35: 85424900534 | E35: RAFAEL BORGES DOS SANTOS | F35: AL Salvador 1057 Caminho das Árvores Salvador BA 41820-790 | G35: ADE-12872-V4P5Z8 | H35: 46082 | I35: 202603 | J35: 370.25527 | L35: 370.26 | N35: 90520246 | O35: 46101 | P35: 46111 | R35: 15 | S35: 2 - CPF | T35: Em aberto - Vencido | U35: Em aberto - Vencido | V35: M653KNL | W35: 4 | X35: false | Y35: 6 | Z35: Em aberto | AA35: ASSOCIAÇÃO BA ? L1 | AB35: 35.686.965/0001-64 - ALEXANDRIA TECH | AC35: Estimado | AE35: 1 a 30 dias | AF35: dac20b7f-63df-43db-8980-f789f0e0d287 | AG35: 46115 | AH35: 1 a 30 dias | AI35: =_xlfn.XLOOKUP(Tabela5[[#This Row],[UUID]],Planilha2!$A:$A,Planilha2!B:B,"") -> 1 | AJ35: =_xlfn.XLOOKUP(Tabela5[[#This Row],[UUID]],Planilha2!$A:$A,Planilha2!C:C,"") -> 1 | AK35: =_xlfn.XLOOKUP(Tabela5[[#This Row],[UUID]],Planilha2!$A:$A,Planilha2!D:D,"") -> 12 | AL35: =_xlfn.XLOOKUP(Tabela5[[#This Row],[UUID]],Planilha2!$A:$A,Planilha2!E:E,"") -> 0 | AM35: =_xlfn.XLOOKUP(Tabela5[[#This Row],[UUID]],Planilha2!$A:$A,Planilha2!F:F,"") -> 1 | AN35: =_xlfn.XLOOKUP(Tabela5[[#This Row],[UUID]],Planilha2!$A:$A,Planilha2!G:G,"") -> 1 | AO35: =_xlfn.XLOOKUP(Tabela5[[#This Row],[UUID]],Planilha2!$A:$A,Planilha2!H:H,"") -> 0 | AP35: =_xlfn.XLOOKUP(Tabela5[[#This Row],[UUID]],Planilha2!$A:$A,Planilha2!I:I,"") -> 0 | AQ35: =_xlfn.XLOOKUP(Tabela5[[#This Row],[UUID]],Planilha2!$A:$A,Planilha2!J:J,"") -> 0 | AR35: =_xlfn.XLOOKUP(Tabela5[[#This Row],[UUID]],Planilha2!$A:$A,Planilha2!K:K,"") -> 0 | AS35: =_xlfn.XLOOKUP(Tabela5[[#This Row],[UUID]],Planilha2!$A:$A,Planilha2!L:L,"") -> 0 | AT35: =_xlfn.XLOOKUP(Tabela5[[#This Row],[UUID]],Planilha2!$A:$A,Planilha2!M:M,"") -> 0 | AU35: =_xlfn.XLOOKUP(Tabela5[[#This Row],[UUID]],Planilha2!$A:$A,Planilha2!N:N,"") -> 1 | AV35: =_xlfn.XLOOKUP(Tabela5[[#This Row],[UUID]],Planilha2!$A:$A,Planilha2!O:O,"") -> 1
A36: COB-242313 | B36: Faturado | C36: 3258885 | D36: 98482530500 | E36: VALDEMIRO DA LUZ | F36: Rua Sao Pedro 5 BONFIM DA MATA Mata de São João BA 48280-000 | G36: ADE-12856-B0K7G3 | H36: 46082 | I36: 202603 | J36: 414.90572 | L36: 414.91 | N36: 90520295 | O36: 46101 | P36: 46111 | R36: 15 | S36: 2 - CPF | T36: Em aberto - Vencido | U36: Em aberto - Vencido | V36: K4GQIWO | W36: 6 | X36: false | Y36: 6 | Z36: Em aberto - Vencido | AA36: ASSOCIAÇÃO BA ? L1 | AB36: 35.686.965/0001-64 - ALEXANDRIA TECH | AC36: Estimado | AE36: 1 a 30 dias | AF36: 45836e09-a069-4752-8d89-7f2bce3fc472 | AG36: 46115 | AH36: 1 a 30 dias | AI36: =_xlfn.XLOOKUP(Tabela5[[#This Row],[UUID]],Planilha2!$A:$A,Planilha2!B:B,"") -> 1 | AJ36: =_xlfn.XLOOKUP(Tabela5[[#This Row],[UUID]],Planilha2!$A:$A,Planilha2!C:C,"") -> 1 | AK36: =_xlfn.XLOOKUP(Tabela5[[#This Row],[UUID]],Planilha2!$A:$A,Planilha2!D:D,"") -> 10 | AL36: =_xlfn.XLOOKUP(Tabela5[[#This Row],[UUID]],Planilha2!$A:$A,Planilha2!E:E,"") -> 0 | AM36: =_xlfn.XLOOKUP(Tabela5[[#This Row],[UUID]],Planilha2!$A:$A,Planilha2!F:F,"") -> 1 | AN36: =_xlfn.XLOOKUP(Tabela5[[#This Row],[UUID]],Planilha2!$A:$A,Planilha2!G:G,"") -> 1 | AO36: =_xlfn.XLOOKUP(Tabela5[[#This Row],[UUID]],Planilha2!$A:$A,Planilha2!H:H,"") -> 0 | AP36: =_xlfn.XLOOKUP(Tabela5[[#This Row],[UUID]],Planilha2!$A:$A,Planilha2!I:I,"") -> 0 | AQ36: =_xlfn.XLOOKUP(Tabela5[[#This Row],[UUID]],Planilha2!$A:$A,Planilha2!J:J,"") -> 0 | AR36: =_xlfn.XLOOKUP(Tabela5[[#This Row],[UUID]],Planilha2!$A:$A,Planilha2!K:K,"") -> 0 | AS36: =_xlfn.XLOOKUP(Tabela5[[#This Row],[UUID]],Planilha2!$A:$A,Planilha2!L:L,"") -> 0 | AT36: =_xlfn.XLOOKUP(Tabela5[[#This Row],[UUID]],Planilha2!$A:$A,Planilha2!M:M,"") -> 0 | AU36: =_xlfn.XLOOKUP(Tabela5[[#This Row],[UUID]],Planilha2!$A:$A,Planilha2!N:N,"") -> 1 | AV36: =_xlfn.XLOOKUP(Tabela5[[#This Row],[UUID]],Planilha2!$A:$A,Planilha2!O:O,"") -> 1
A37: COB-242311 | B37: Faturado | C37: 2156422 | D37: 41828488534 | E37: JAELTON FONSECA DE SOUZA | F37: PC Virgilio Damasio 206 Centro Ipiaú BA 45570-000 | G37: ADE-12849-B4S7S5 | H37: 46082 | I37: 202603 | J37: 588.01208 | L37: 588.01 | N37: 90520324 | O37: 46101 | P37: 46111 | R37: 15 | S37: 2 - CPF | T37: Em aberto - Vencido | U37: Em aberto - Vencido | V37: BZ33VYD | W37: 6 | X37: false | Y37: 6 | Z37: Em aberto - Vencido | AA37: ASSOCIAÇÃO BA ? L1 | AB37: 35.686.965/0001-64 - ALEXANDRIA TECH | AC37: Estimado | AE37: 1 a 30 dias | AF37: b86380e8-f9a9-43ec-9837-6567773a34c3 | AG37: 46115 | AH37: 1 a 30 dias | AI37: =_xlfn.XLOOKUP(Tabela5[[#This Row],[UUID]],Planilha2!$A:$A,Planilha2!B:B,"") -> 1 | AJ37: =_xlfn.XLOOKUP(Tabela5[[#This Row],[UUID]],Planilha2!$A:$A,Planilha2!C:C,"") -> 1 | AK37: =_xlfn.XLOOKUP(Tabela5[[#This Row],[UUID]],Planilha2!$A:$A,Planilha2!D:D,"") -> 1 | AL37: =_xlfn.XLOOKUP(Tabela5[[#This Row],[UUID]],Planilha2!$A:$A,Planilha2!E:E,"") -> 0 | AM37: =_xlfn.XLOOKUP(Tabela5[[#This Row],[UUID]],Planilha2!$A:$A,Planilha2!F:F,"") -> 1 | AN37: =_xlfn.XLOOKUP(Tabela5[[#This Row],[UUID]],Planilha2!$A:$A,Planilha2!G:G,"") -> 1 | AO37: =_xlfn.XLOOKUP(Tabela5[[#This Row],[UUID]],Planilha2!$A:$A,Planilha2!H:H,"") -> 0 | AP37: =_xlfn.XLOOKUP(Tabela5[[#This Row],[UUID]],Planilha2!$A:$A,Planilha2!I:I,"") -> 0 | AQ37: =_xlfn.XLOOKUP(Tabela5[[#This Row],[UUID]],Planilha2!$A:$A,Planilha2!J:J,"") -> 0 | AR37: =_xlfn.XLOOKUP(Tabela5[[#This Row],[UUID]],Planilha2!$A:$A,Planilha2!K:K,"") -> 0 | AS37: =_xlfn.XLOOKUP(Tabela5[[#This Row],[UUID]],Planilha2!$A:$A,Planilha2!L:L,"") -> 0 | AT37: =_xlfn.XLOOKUP(Tabela5[[#This Row],[UUID]],Planilha2!$A:$A,Planilha2!M:M,"") -> 0 | AU37: =_xlfn.XLOOKUP(Tabela5[[#This Row],[UUID]],Planilha2!$A:$A,Planilha2!N:N,"") -> 1 | AV37: =_xlfn.XLOOKUP(Tabela5[[#This Row],[UUID]],Planilha2!$A:$A,Planilha2!O:O,"") -> 1
A38: COB-242283 | B38: Faturado | C38: 6522860 | D38: 22711081877 | E38: SCHIRLEI APARECIDA OLIVEIRA DE SOUZA | F38: Avenida Otávio Santos 570 CENTRO Vitória da Conquista BA 45020-750 | G38: ADE-12502-H3H9S8 | H38: 46082 | I38: 202603 | J38: 202.64435 | L38: 202.64 | N38: 90520257 | O38: 46101 | P38: 46111 | R38: 15 | S38: 2 - CPF | T38: Em aberto - Vencido | U38: Em aberto - Vencido | V38: JOEM5Z9 | W38: 6 | X38: false | Y38: 6 | Z38: Em aberto - Vencido | AA38: ASSOCIAÇÃO BA ? L1 | AB38: 35.686.965/0001-64 - ALEXANDRIA TECH | AC38: Estimado | AE38: 1 a 30 dias | AF38: 2442c987-dbfa-4d30-88a9-be089ce2802f | AG38: 46115 | AH38: 1 a 30 dias | AI38: =_xlfn.XLOOKUP(Tabela5[[#This Row],[UUID]],Planilha2!$A:$A,Planilha2!B:B,"") -> 1 | AJ38: =_xlfn.XLOOKUP(Tabela5[[#This Row],[UUID]],Planilha2!$A:$A,Planilha2!C:C,"") -> 1 | AK38: =_xlfn.XLOOKUP(Tabela5[[#This Row],[UUID]],Planilha2!$A:$A,Planilha2!D:D,"") -> 10 | AL38: =_xlfn.XLOOKUP(Tabela5[[#This Row],[UUID]],Planilha2!$A:$A,Planilha2!E:E,"") -> 0 | AM38: =_xlfn.XLOOKUP(Tabela5[[#This Row],[UUID]],Planilha2!$A:$A,Planilha2!F:F,"") -> 1 | AN38: =_xlfn.XLOOKUP(Tabela5[[#This Row],[UUID]],Planilha2!$A:$A,Planilha2!G:G,"") -> 1 | AO38: =_xlfn.XLOOKUP(Tabela5[[#This Row],[UUID]],Planilha2!$A:$A,Planilha2!H:H,"") -> 0 | AP38: =_xlfn.XLOOKUP(Tabela5[[#This Row],[UUID]],Planilha2!$A:$A,Planilha2!I:I,"") -> 0 | AQ38: =_xlfn.XLOOKUP(Tabela5[[#This Row],[UUID]],Planilha2!$A:$A,Planilha2!J:J,"") -> 0 | AR38: =_xlfn.XLOOKUP(Tabela5[[#This Row],[UUID]],Planilha2!$A:$A,Planilha2!K:K,"") -> 0 | AS38: =_xlfn.XLOOKUP(Tabela5[[#This Row],[UUID]],Planilha2!$A:$A,Planilha2!L:L,"") -> 0 | AT38: =_xlfn.XLOOKUP(Tabela5[[#This Row],[UUID]],Planilha2!$A:$A,Planilha2!M:M,"") -> 0 | AU38: =_xlfn.XLOOKUP(Tabela5[[#This Row],[UUID]],Planilha2!$A:$A,Planilha2!N:N,"") -> 1 | AV38: =_xlfn.XLOOKUP(Tabela5[[#This Row],[UUID]],Planilha2!$A:$A,Planilha2!O:O,"") -> 1
A39: COB-242282 | B39: Faturado | C39: 60151790 | D39: 1318137578 | E39: ANCELMO PARENTE DO NASCIMENTO | F39: RUA JURACY MAGALHAES 16 B CS- 16 Ibiaçu Maraú BA 45523-000 | G39: ADE-12501-N2Y4K5 | H39: 46082 | I39: 202603 | J39: 290.57139 | L39: 290.57 | N39: 90520427 | O39: 46101 | P39: 46111 | R39: 15 | S39: 2 - CPF | T39: Em aberto - Vencido | U39: Em aberto - Vencido | V39: RYJ9MA7 | W39: 6 | X39: false | Y39: 6 | Z39: Em aberto - Vencido | AA39: ASSOCIAÇÃO BA ? L1 | AB39: 35.686.965/0001-64 - ALEXANDRIA TECH | AC39: Estimado | AE39: 1 a 30 dias | AF39: d0dc3c56-e364-4c9a-b761-671962e1693c | AG39: 46115 | AH39: 1 a 30 dias | AI39: =_xlfn.XLOOKUP(Tabela5[[#This Row],[UUID]],Planilha2!$A:$A,Planilha2!B:B,"") -> 1 | AJ39: =_xlfn.XLOOKUP(Tabela5[[#This Row],[UUID]],Planilha2!$A:$A,Planilha2!C:C,"") -> 1 | AK39: =_xlfn.XLOOKUP(Tabela5[[#This Row],[UUID]],Planilha2!$A:$A,Planilha2!D:D,"") -> 7 | AL39: =_xlfn.XLOOKUP(Tabela5[[#This Row],[UUID]],Planilha2!$A:$A,Planilha2!E:E,"") -> 0 | AM39: =_xlfn.XLOOKUP(Tabela5[[#This Row],[UUID]],Planilha2!$A:$A,Planilha2!F:F,"") -> 1 | AN39: =_xlfn.XLOOKUP(Tabela5[[#This Row],[UUID]],Planilha2!$A:$A,Planilha2!G:G,"") -> 1 | AO39: =_xlfn.XLOOKUP(Tabela5[[#This Row],[UUID]],Planilha2!$A:$A,Planilha2!H:H,"") -> 0 | AP39: =_xlfn.XLOOKUP(Tabela5[[#This Row],[UUID]],Planilha2!$A:$A,Planilha2!I:I,"") -> 0 | AQ39: =_xlfn.XLOOKUP(Tabela5[[#This Row],[UUID]],Planilha2!$A:$A,Planilha2!J:J,"") -> 0 | AR39: =_xlfn.XLOOKUP(Tabela5[[#This Row],[UUID]],Planilha2!$A:$A,Planilha2!K:K,"") -> 0 | AS39: =_xlfn.XLOOKUP(Tabela5[[#This Row],[UUID]],Planilha2!$A:$A,Planilha2!L:L,"") -> 0 | AT39: =_xlfn.XLOOKUP(Tabela5[[#This Row],[UUID]],Planilha2!$A:$A,Planilha2!M:M,"") -> 0 | AU39: =_xlfn.XLOOKUP(Tabela5[[#This Row],[UUID]],Planilha2!$A:$A,Planilha2!N:N,"") -> 1 | AV39: =_xlfn.XLOOKUP(Tabela5[[#This Row],[UUID]],Planilha2!$A:$A,Planilha2!O:O,"") -> 1
... A41: COB-243054 | B41: Faturado | C41: 10041520848 | D41: 4243541108 | E41: ERIC MILLER XAVIER DOS SANTOS | F41: RUA 2 S/N Q. 14, L. 15, Jardim Planalto Luziânia GO 75000-000 | G41: ADE-17595-G5J2Q4 | H41: 46082 | I41: 202603 | J41: 1145.716 | L41: 1145.72 | N41: 90520328 | O41: 46101 | P41: 46111 | R41: 15 | S41: 2 - CPF | T41: Em aberto - Vencido | U41: Em aberto - Vencido | V41: ZAFQGFY | W41: 6 | X41: false | Y41: 6 | Z41: Em aberto - Vencido | AA41: ASSOCIAÇÃO GO-L1 | AB41: 35.686.965/0001-64 - ALEXANDRIA TECH | AC41: Estimado | AE41: 1 a 30 dias | AF41: f38c46c3-0cb3-4666-b989-e8661e65ff4a | AG41: 46111 | AH41: 1 a 30 dias | AI41: =_xlfn.XLOOKUP(Tabela5[[#This Row],[UUID]],Planilha2!$A:$A,Planilha2!B:B,"") -> 1 | AJ41: =_xlfn.XLOOKUP(Tabela5[[#This Row],[UUID]],Planilha2!$A:$A,Planilha2!C:C,"") -> 1 | AK41: =_xlfn.XLOOKUP(Tabela5[[#This Row],[UUID]],Planilha2!$A:$A,Planilha2!D:D,"") -> 8 | AL41: =_xlfn.XLOOKUP(Tabela5[[#This Row],[UUID]],Planilha2!$A:$A,Planilha2!E:E,"") -> 0 | AM41: =_xlfn.XLOOKUP(Tabela5[[#This Row],[UUID]],Planilha2!$A:$A,Planilha2!F:F,"") -> 1 | AN41: =_xlfn.XLOOKUP(Tabela5[[#This Row],[UUID]],Planilha2!$A:$A,Planilha2!G:G,"") -> 1 | AO41: =_xlfn.XLOOKUP(Tabela5[[#This Row],[UUID]],Planilha2!$A:$A,Planilha2!H:H,"") -> 1 | AP41: =_xlfn.XLOOKUP(Tabela5[[#This Row],[UUID]],Planilha2!$A:$A,Planilha2!I:I,"") -> 0 | AQ41: =_xlfn.XLOOKUP(Tabela5[[#This Row],[UUID]],Planilha2!$A:$A,Planilha2!J:J,"") -> 0 | AR41: =_xlfn.XLOOKUP(Tabela5[[#This Row],[UUID]],Planilha2!$A:$A,Planilha2!K:K,"") -> 0 | AS41: =_xlfn.XLOOKUP(Tabela5[[#This Row],[UUID]],Planilha2!$A:$A,Planilha2!L:L,"") -> 0 | AT41: =_xlfn.XLOOKUP(Tabela5[[#This Row],[UUID]],Planilha2!$A:$A,Planilha2!M:M,"") -> 1 | AU41: =_xlfn.XLOOKUP(Tabela5[[#This Row],[UUID]],Planilha2!$A:$A,Planilha2!N:N,"") -> 1 | AV41: =_xlfn.XLOOKUP(Tabela5[[#This Row],[UUID]],Planilha2!$A:$A,Planilha2!O:O,"") -> 1
A42: COB-176568 | B42: Faturado | C42: 1402498 | D42: 13274033740 | E42: GEOVANE DA COSTA | F42: RUA ATENEU 10 CAIXA 1 RESIDENCIAL ITAPARICA / VILA VELHA - ES CEP: 29102-853 | G42: ADE-12048-Z5F0H9 | H42: 45839 | I42: 202507 | J42: 458.17229 | L42: 458.17 | N42: 90427138 | O42: 45995 | P42: 46006 | R42: 120 | S42: 2 - CPF | T42: Em aberto - Vencido | U42: Em aberto - Vencido | V42: XZV40FB | W42: 6 | X42: false | Y42: 6 | Z42: Em aberto - Vencido | AA42: ASSOCIAÇÃO ES-L1 | AB42: 35.686.965/0001-64 - ALEXANDRIA TECH | AE42: 61 a 120 dias | AF42: bfeca25e-6bcf-4d8b-809f-0fd96de8bacd | AG42: 45917 | AH42: Maior que 90 | AI42: =_xlfn.XLOOKUP(Tabela5[[#This Row],[UUID]],Planilha2!$A:$A,Planilha2!B:B,"") -> 0 | AJ42: =_xlfn.XLOOKUP(Tabela5[[#This Row],[UUID]],Planilha2!$A:$A,Planilha2!C:C,"") -> 0 | AK42: =_xlfn.XLOOKUP(Tabela5[[#This Row],[UUID]],Planilha2!$A:$A,Planilha2!D:D,"") -> 0 | AL42: =_xlfn.XLOOKUP(Tabela5[[#This Row],[UUID]],Planilha2!$A:$A,Planilha2!E:E,"") -> 6 | AM42: =_xlfn.XLOOKUP(Tabela5[[#This Row],[UUID]],Planilha2!$A:$A,Planilha2!F:F,"") -> 0 | AN42: =_xlfn.XLOOKUP(Tabela5[[#This Row],[UUID]],Planilha2!$A:$A,Planilha2!G:G,"") -> 0 | AO42: =_xlfn.XLOOKUP(Tabela5[[#This Row],[UUID]],Planilha2!$A:$A,Planilha2!H:H,"") -> 0 | AP42: =_xlfn.XLOOKUP(Tabela5[[#This Row],[UUID]],Planilha2!$A:$A,Planilha2!I:I,"") -> 0 | AQ42: =_xlfn.XLOOKUP(Tabela5[[#This Row],[UUID]],Planilha2!$A:$A,Planilha2!J:J,"") -> 0 | AR42: =_xlfn.XLOOKUP(Tabela5[[#This Row],[UUID]],Planilha2!$A:$A,Planilha2!K:K,"") -> 0 | AS42: =_xlfn.XLOOKUP(Tabela5[[#This Row],[UUID]],Planilha2!$A:$A,Planilha2!L:L,"") -> 0 | AT42: =_xlfn.XLOOKUP(Tabela5[[#This Row],[UUID]],Planilha2!$A:$A,Planilha2!M:M,"") -> 0 | AU42: =_xlfn.XLOOKUP(Tabela5[[#This Row],[UUID]],Planilha2!$A:$A,Planilha2!N:N,"") -> 0 | AV42: =_xlfn.XLOOKUP(Tabela5[[#This Row],[UUID]],Planilha2!$A:$A,Planilha2!O:O,"") -> 0
A43: COB-243049 | B43: Faturado | C43: 470008714 | D43: 24728616134 | E43: EVA MARIA DUTRA REZENDE | F43: RUA JOSE PEREIRA FAUSTINO 467 Q. 2 A, L. 0, Setor Central Cristianópolis GO 75230000 | G43: ADE-17506-Q2N6N8 | H43: 46082 | I43: 202603 | J43: 212.94285 | L43: 212.94 | N43: 90520333 | O43: 46101 | P43: 46111 | R43: 15 | S43: 2 - CPF | T43: Em aberto - Vencido | U43: Em aberto - Vencido | V43: 864T6A1 | W43: 6 | X43: false | Y43: 6 | Z43: Em aberto - Vencido | AA43: ASSOCIAÇÃO GO-L1 | AB43: 35.686.965/0001-64 - ALEXANDRIA TECH | AC43: Estimado | AE43: 1 a 30 dias | AF43: 2e1318ad-cc32-4734-bab9-f51dc39f5776 | AG43: 46115 | AH43: 1 a 30 dias | AI43: =_xlfn.XLOOKUP(Tabela5[[#This Row],[UUID]],Planilha2!$A:$A,Planilha2!B:B,"") -> 1 | AJ43: =_xlfn.XLOOKUP(Tabela5[[#This Row],[UUID]],Planilha2!$A:$A,Planilha2!C:C,"") -> 1 | AK43: =_xlfn.XLOOKUP(Tabela5[[#This Row],[UUID]],Planilha2!$A:$A,Planilha2!D:D,"") -> 1 | AL43: =_xlfn.XLOOKUP(Tabela5[[#This Row],[UUID]],Planilha2!$A:$A,Planilha2!E:E,"") -> 0 | AM43: =_xlfn.XLOOKUP(Tabela5[[#This Row],[UUID]],Planilha2!$A:$A,Planilha2!F:F,"") -> 1 | AN43: =_xlfn.XLOOKUP(Tabela5[[#This Row],[UUID]],Planilha2!$A:$A,Planilha2!G:G,"") -> 1 | AO43: =_xlfn.XLOOKUP(Tabela5[[#This Row],[UUID]],Planilha2!$A:$A,Planilha2!H:H,"") -> 0 | AP43: =_xlfn.XLOOKUP(Tabela5[[#This Row],[UUID]],Planilha2!$A:$A,Planilha2!I:I,"") -> 0 | AQ43: =_xlfn.XLOOKUP(Tabela5[[#This Row],[UUID]],Planilha2!$A:$A,Planilha2!J:J,"") -> 0 | AR43: =_xlfn.XLOOKUP(Tabela5[[#This Row],[UUID]],Planilha2!$A:$A,Planilha2!K:K,"") -> 0 | AS43: =_xlfn.XLOOKUP(Tabela5[[#This Row],[UUID]],Planilha2!$A:$A,Planilha2!L:L,"") -> 0 | AT43: =_xlfn.XLOOKUP(Tabela5[[#This Row],[UUID]],Planilha2!$A:$A,Planilha2!M:M,"") -> 0 | AU43: =_xlfn.XLOOKUP(Tabela5[[#This Row],[UUID]],Planilha2!$A:$A,Planilha2!N:N,"") -> 1 | AV43: =_xlfn.XLOOKUP(Tabela5[[#This Row],[UUID]],Planilha2!$A:$A,Planilha2!O:O,"") -> 1
A44: COB-176576 | B44: Faturado | C44: 843841 | D44: 15874764798 | E44: SARHA MONTEIRO ITALO UCHOA | F44: AV ESTD JOSE JULIO DE SOUZA 1742 AP 504 VINA DEL MAR PRAIA DE ITAPARICA / VILA VELHA - ES CEP: 29102-010 | G44: ADE-12055-R7B9T1 | H44: 45839 | I44: 202507 | J44: 233.83239 | L44: 233.83 | N44: 90427206 | O44: 45995 | P44: 46006 | R44: 120 | S44: 2 - CPF | T44: Em aberto - Vencido | U44: Em aberto - Vencido | V44: J1ZBFEJ | W44: 6 | X44: false | Y44: 6 | Z44: Em aberto - Vencido | AA44: ASSOCIAÇÃO ES-L1 | AB44: 35.686.965/0001-64 - ALEXANDRIA TECH | AE44: 61 a 120 dias | AF44: fb6c53fc-5e97-40b9-bb31-6f26d200f40a | AG44: 45917 | AH44: Maior que 90 | AI44: =_xlfn.XLOOKUP(Tabela5[[#This Row],[UUID]],Planilha2!$A:$A,Planilha2!B:B,"") -> 0 | AJ44: =_xlfn.XLOOKUP(Tabela5[[#This Row],[UUID]],Planilha2!$A:$A,Planilha2!C:C,"") -> 0 | AK44: =_xlfn.XLOOKUP(Tabela5[[#This Row],[UUID]],Planilha2!$A:$A,Planilha2!D:D,"") -> 0 | AL44: =_xlfn.XLOOKUP(Tabela5[[#This Row],[UUID]],Planilha2!$A:$A,Planilha2!E:E,"") -> 5 | AM44: =_xlfn.XLOOKUP(Tabela5[[#This Row],[UUID]],Planilha2!$A:$A,Planilha2!F:F,"") -> 0 | AN44: =_xlfn.XLOOKUP(Tabela5[[#This Row],[UUID]],Planilha2!$A:$A,Planilha2!G:G,"") -> 0 | AO44: =_xlfn.XLOOKUP(Tabela5[[#This Row],[UUID]],Planilha2!$A:$A,Planilha2!H:H,"") -> 0 | AP44: =_xlfn.XLOOKUP(Tabela5[[#This Row],[UUID]],Planilha2!$A:$A,Planilha2!I:I,"") -> 0 | AQ44: =_xlfn.XLOOKUP(Tabela5[[#This Row],[UUID]],Planilha2!$A:$A,Planilha2!J:J,"") -> 0 | AR44: =_xlfn.XLOOKUP(Tabela5[[#This Row],[UUID]],Planilha2!$A:$A,Planilha2!K:K,"") -> 0 | AS44: =_xlfn.XLOOKUP(Tabela5[[#This Row],[UUID]],Planilha2!$A:$A,Planilha2!L:L,"") -> 0 | AT44: =_xlfn.XLOOKUP(Tabela5[[#This Row],[UUID]],Planilha2!$A:$A,Planilha2!M:M,"") -> 0 | AU44: =_xlfn.XLOOKUP(Tabela5[[#This Row],[UUID]],Planilha2!$A:$A,Planilha2!N:N,"") -> 0 | AV44: =_xlfn.XLOOKUP(Tabela5[[#This Row],[UUID]],Planilha2!$A:$A,Planilha2!O:O,"") -> 0
A45: COB-243048 | B45: Faturado | C45: 8680001857 | D45: 15066517120 | E45: VALDOMIRO LOPES DA SILVA | F45: RUA DAS FLORES 163 Q. 1, LT. 23 SETOR NORTE São Domingos GO 73860-000 | G45: ADE-17502-T2C7B5 | H45: 46082 | I45: 202603 | J45: 247.18072 | L45: 247.18 | N45: 90520414 | O45: 46101 | P45: 46111 | R45: 15 | S45: 2 - CPF | T45: Em aberto - Vencido | U45: Em aberto - Vencido | V45: 3RSP0T5 | W45: 6 | X45: false | Y45: 6 | Z45: Em aberto - Vencido | AA45: ASSOCIAÇÃO GO-L1 | AB45: 35.686.965/0001-64 - ALEXANDRIA TECH | AC45: Estimado | AE45: 1 a 30 dias | AF45: 5d5770a9-da57-4a91-9308-b5468881a58d | AG45: 46111 | AH45: 1 a 30 dias | AI45: =_xlfn.XLOOKUP(Tabela5[[#This Row],[UUID]],Planilha2!$A:$A,Planilha2!B:B,"") -> 1 | AJ45: =_xlfn.XLOOKUP(Tabela5[[#This Row],[UUID]],Planilha2!$A:$A,Planilha2!C:C,"") -> 1 | AK45: =_xlfn.XLOOKUP(Tabela5[[#This Row],[UUID]],Planilha2!$A:$A,Planilha2!D:D,"") -> 2 | AL45: =_xlfn.XLOOKUP(Tabela5[[#This Row],[UUID]],Planilha2!$A:$A,Planilha2!E:E,"") -> 0 | AM45: =_xlfn.XLOOKUP(Tabela5[[#This Row],[UUID]],Planilha2!$A:$A,Planilha2!F:F,"") -> 1 | AN45: =_xlfn.XLOOKUP(Tabela5[[#This Row],[UUID]],Planilha2!$A:$A,Planilha2!G:G,"") -> 1 | AO45: =_xlfn.XLOOKUP(Tabela5[[#This Row],[UUID]],Planilha2!$A:$A,Planilha2!H:H,"") -> 1 | AP45: =_xlfn.XLOOKUP(Tabela5[[#This Row],[UUID]],Planilha2!$A:$A,Planilha2!I:I,"") -> 0 | AQ45: =_xlfn.XLOOKUP(Tabela5[[#This Row],[UUID]],Planilha2!$A:$A,Planilha2!J:J,"") -> 0 | AR45: =_xlfn.XLOOKUP(Tabela5[[#This Row],[UUID]],Planilha2!$A:$A,Planilha2!K:K,"") -> 0 | AS45: =_xlfn.XLOOKUP(Tabela5[[#This Row],[UUID]],Planilha2!$A:$A,Planilha2!L:L,"") -> 0 | AT45: =_xlfn.XLOOKUP(Tabela5[[#This Row],[UUID]],Planilha2!$A:$A,Planilha2!M:M,"") -> 1 | AU45: =_xlfn.XLOOKUP(Tabela5[[#This Row],[UUID]],Planilha2!$A:$A,Planilha2!N:N,"") -> 1 | AV45: =_xlfn.XLOOKUP(Tabela5[[#This Row],[UUID]],Planilha2!$A:$A,Planilha2!O:O,"") -> 1
A46: COB-243035 | B46: Faturado | C46: 10033059118 | D46: 5849514180 | E46: SILVIO VICTOR ALBINO | F46: RUA MARIA BERNADA DA SILVA 136 Q. 02, L. 01-A RESIDENCIAL AGUAS CLARAS Tatuí SP 18270-840 | G46: ADE-17342-F5H9B0 | H46: 46082 | I46: 202603 | J46: 212.10778 | K46: 5.8 | L46: 217.91 | N46: 90520321 | O46: 46101 | P46: 46111 | R46: 15 | S46: 2 - CPF | T46: Em aberto - Vencido | U46: Em aberto - Vencido | V46: X6VZ72B | W46: 6 | X46: false | Y46: 6 | Z46: Em aberto - Vencido | AA46: ASSOCIAÇÃO GO-L1 | AB46: 35.686.965/0001-64 - ALEXANDRIA TECH | AC46: Estimado | AE46: 1 a 30 dias | AF46: 3e133274-0da7-4f58-89bc-868f3bc7d437 | AG46: 46111 | AH46: 1 a 30 dias | AI46: =_xlfn.XLOOKUP(Tabela5[[#This Row],[UUID]],Planilha2!$A:$A,Planilha2!B:B,"") -> 1 | AJ46: =_xlfn.XLOOKUP(Tabela5[[#This Row],[UUID]],Planilha2!$A:$A,Planilha2!C:C,"") -> 1 | AK46: =_xlfn.XLOOKUP(Tabela5[[#This Row],[UUID]],Planilha2!$A:$A,Planilha2!D:D,"") -> 1 | AL46: =_xlfn.XLOOKUP(Tabela5[[#This Row],[UUID]],Planilha2!$A:$A,Planilha2!E:E,"") -> 0 | AM46: =_xlfn.XLOOKUP(Tabela5[[#This Row],[UUID]],Planilha2!$A:$A,Planilha2!F:F,"") -> 1 | AN46: =_xlfn.XLOOKUP(Tabela5[[#This Row],[UUID]],Planilha2!$A:$A,Planilha2!G:G,"") -> 1 | AO46: =_xlfn.XLOOKUP(Tabela5[[#This Row],[UUID]],Planilha2!$A:$A,Planilha2!H:H,"") -> 1 | AP46: =_xlfn.XLOOKUP(Tabela5[[#This Row],[UUID]],Planilha2!$A:$A,Planilha2!I:I,"") -> 0 | AQ46: =_xlfn.XLOOKUP(Tabela5[[#This Row],[UUID]],Planilha2!$A:$A,Planilha2!J:J,"") -> 0 | AR46: =_xlfn.XLOOKUP(Tabela5[[#This Row],[UUID]],Planilha2!$A:$A,Planilha2!K:K,"") -> 0 | AS46: =_xlfn.XLOOKUP(Tabela5[[#This Row],[UUID]],Planilha2!$A:$A,Planilha2!L:L,"") -> 0 | AT46: =_xlfn.XLOOKUP(Tabela5[[#This Row],[UUID]],Planilha2!$A:$A,Planilha2!M:M,"") -> 1 | AU46: =_xlfn.XLOOKUP(Tabela5[[#This Row],[UUID]],Planilha2!$A:$A,Planilha2!N:N,"") -> 1 | AV46: =_xlfn.XLOOKUP(Tabela5[[#This Row],[UUID]],Planilha2!$A:$A,Planilha2!O:O,"") -> 1
A47: COB-243031 | B47: Faturado | C47: 470015196 | D47: 86899368153 | E47: SANTIAGO CASTRO MACHADO | F47: Rua IPE S/N Q.1 L.20 Setor floresta Cristianópolis GO 75230-000 | G47: ADE-17253-N8Y6R1 | H47: 46082 | I47: 202603 | J47: 154.54356 | L47: 154.54 | N47: 90520251 | O47: 46101 | P47: 46111 | R47: 15 | S47: 2 - CPF | T47: Em aberto - Vencido | U47: Em aberto - Vencido | V47: USAZ3VO | W47: 6 | X47: false | Y47: 6 | Z47: Em aberto - Vencido | AA47: ASSOCIAÇÃO GO-L1 | AB47: 35.686.965/0001-64 - ALEXANDRIA TECH | AC47: Estimado | AE47: 1 a 30 dias | AF47: 1c566181-f099-4b29-8eab-12d627391283 | AG47: 46115 | AH47: 1 a 30 dias | AI47: =_xlfn.XLOOKUP(Tabela5[[#This Row],[UUID]],Planilha2!$A:$A,Planilha2!B:B,"") -> 1 | AJ47: =_xlfn.XLOOKUP(Tabela5[[#This Row],[UUID]],Planilha2!$A:$A,Planilha2!C:C,"") -> 1 | AK47: =_xlfn.XLOOKUP(Tabela5[[#This Row],[UUID]],Planilha2!$A:$A,Planilha2!D:D,"") -> 12 | AL47: =_xlfn.XLOOKUP(Tabela5[[#This Row],[UUID]],Planilha2!$A:$A,Planilha2!E:E,"") -> 0 | AM47: =_xlfn.XLOOKUP(Tabela5[[#This Row],[UUID]],Planilha2!$A:$A,Planilha2!F:F,"") -> 1 | AN47: =_xlfn.XLOOKUP(Tabela5[[#This Row],[UUID]],Planilha2!$A:$A,Planilha2!G:G,"") -> 1 | AO47: =_xlfn.XLOOKUP(Tabela5[[#This Row],[UUID]],Planilha2!$A:$A,Planilha2!H:H,"") -> 0 | AP47: =_xlfn.XLOOKUP(Tabela5[[#This Row],[UUID]],Planilha2!$A:$A,Planilha2!I:I,"") -> 0 | AQ47: =_xlfn.XLOOKUP(Tabela5[[#This Row],[UUID]],Planilha2!$A:$A,Planilha2!J:J,"") -> 0 | AR47: =_xlfn.XLOOKUP(Tabela5[[#This Row],[UUID]],Planilha2!$A:$A,Planilha2!K:K,"") -> 0 | AS47: =_xlfn.XLOOKUP(Tabela5[[#This Row],[UUID]],Planilha2!$A:$A,Planilha2!L:L,"") -> 0 | AT47: =_xlfn.XLOOKUP(Tabela5[[#This Row],[UUID]],Planilha2!$A:$A,Planilha2!M:M,"") -> 0 | AU47: =_xlfn.XLOOKUP(Tabela5[[#This Row],[UUID]],Planilha2!$A:$A,Planilha2!N:N,"") -> 1 | AV47: =_xlfn.XLOOKUP(Tabela5[[#This Row],[UUID]],Planilha2!$A:$A,Planilha2!O:O,"") -> 1
A48: COB-243030 | B48: Faturado | C48: 2210147627 | D48: 69265984104 | E48: ANDRE LUIZ AQUINO | F48: AVENIDA PERIMETRAL SN Q. 90, L. 16, CASA - 2 Setor Central Santo Antônio do Descoberto GO 72900970 | G48: ADE-17250-R2S3F2 | H48: 46082 | I48: 202603 | J48: 379.12178 | L48: 379.12 | N48: 90520510 | O48: 46101 | P48: 46111 | R48: 15 | S48: 2 - CPF | T48: Em aberto - Vencido | U48: Em aberto - Vencido | V48: A9JGFVT | W48: 6 | X48: false | Y48: 6 | Z48: Em aberto - Vencido | AA48: ASSOCIAÇÃO GO-L1 | AB48: 35.686.965/0001-64 - ALEXANDRIA TECH | AC48: Estimado | AE48: 1 a 30 dias | AF48: c2da4718-3099-48c7-8fb4-5c649d4e3326 | AG48: 46117 | AH48: 1 a 30 dias | AI48: =_xlfn.XLOOKUP(Tabela5[[#This Row],[UUID]],Planilha2!$A:$A,Planilha2!B:B,"") -> 1 | AJ48: =_xlfn.XLOOKUP(Tabela5[[#This Row],[UUID]],Planilha2!$A:$A,Planilha2!C:C,"") -> 1 | AK48: =_xlfn.XLOOKUP(Tabela5[[#This Row],[UUID]],Planilha2!$A:$A,Planilha2!D:D,"") -> 1 | AL48: =_xlfn.XLOOKUP(Tabela5[[#This Row],[UUID]],Planilha2!$A:$A,Planilha2!E:E,"") -> 0 | AM48: =_xlfn.XLOOKUP(Tabela5[[#This Row],[UUID]],Planilha2!$A:$A,Planilha2!F:F,"") -> 1 | AN48: =_xlfn.XLOOKUP(Tabela5[[#This Row],[UUID]],Planilha2!$A:$A,Planilha2!G:G,"") -> 0 | AO48: =_xlfn.XLOOKUP(Tabela5[[#This Row],[UUID]],Planilha2!$A:$A,Planilha2!H:H,"") -> 0 | AP48: =_xlfn.XLOOKUP(Tabela5[[#This Row],[UUID]],Planilha2!$A:$A,Planilha2!I:I,"") -> 0 | AQ48: =_xlfn.XLOOKUP(Tabela5[[#This Row],[UUID]],Planilha2!$A:$A,Planilha2!J:J,"") -> 0 | AR48: =_xlfn.XLOOKUP(Tabela5[[#This Row],[UUID]],Planilha2!$A:$A,Planilha2!K:K,"") -> 0 | AS48: =_xlfn.XLOOKUP(Tabela5[[#This Row],[UUID]],Planilha2!$A:$A,Planilha2!L:L,"") -> 0 | AT48: =_xlfn.XLOOKUP(Tabela5[[#This Row],[UUID]],Planilha2!$A:$A,Planilha2!M:M,"") -> 1 | AU48: =_xlfn.XLOOKUP(Tabela5[[#This Row],[UUID]],Planilha2!$A:$A,Planilha2!N:N,"") -> 1 | AV48: =_xlfn.XLOOKUP(Tabela5[[#This Row],[UUID]],Planilha2!$A:$A,Planilha2!O:O,"") -> 1
A49: COB-176533 | B49: Faturado | C49: 294315 | D49: 10006084761 | E49: LUCIA HELENA FERNANDES | F49: RUA ONOFRIO MACHADO DE SOUZA 1 NOSSA SENHORA DA CONCEICAO / GUARAPARI - ES CEP: 29213-070 | G49: ADE-12068-X5X3C3 | H49: 45839 | I49: 202507 | J49: 117.73948 | L49: 117.74 | N49: 90427175 | O49: 45995 | P49: 46006 | R49: 120 | S49: 2 - CPF | T49: Em aberto - Vencido | U49: Em aberto - Vencido | V49: JW4W8BT | W49: 6 | X49: false | Y49: 6 | Z49: Em aberto - Vencido | AA49: ASSOCIAÇÃO ES-L1 | AB49: 35.686.965/0001-64 - ALEXANDRIA TECH | AE49: 61 a 120 dias | AF49: 4cd960a2-4657-4d0f-985e-3aecd505f4ed | AG49: 45917 | AH49: Maior que 90 | AI49: =_xlfn.XLOOKUP(Tabela5[[#This Row],[UUID]],Planilha2!$A:$A,Planilha2!B:B,"") -> 0 | AJ49: =_xlfn.XLOOKUP(Tabela5[[#This Row],[UUID]],Planilha2!$A:$A,Planilha2!C:C,"") -> 0 | AK49: =_xlfn.XLOOKUP(Tabela5[[#This Row],[UUID]],Planilha2!$A:$A,Planilha2!D:D,"") -> 0 | AL49: =_xlfn.XLOOKUP(Tabela5[[#This Row],[UUID]],Planilha2!$A:$A,Planilha2!E:E,"") -> 14 | AM49: =_xlfn.XLOOKUP(Tabela5[[#This Row],[UUID]],Planilha2!$A:$A,Planilha2!F:F,"") -> 0 | AN49: =_xlfn.XLOOKUP(Tabela5[[#This Row],[UUID]],Planilha2!$A:$A,Planilha2!G:G,"") -> 0 | AO49: =_xlfn.XLOOKUP(Tabela5[[#This Row],[UUID]],Planilha2!$A:$A,Planilha2!H:H,"") -> 0 | AP49: =_xlfn.XLOOKUP(Tabela5[[#This Row],[UUID]],Planilha2!$A:$A,Planilha2!I:I,"") -> 0 | AQ49: =_xlfn.XLOOKUP(Tabela5[[#This Row],[UUID]],Planilha2!$A:$A,Planilha2!J:J,"") -> 0 | AR49: =_xlfn.XLOOKUP(Tabela5[[#This Row],[UUID]],Planilha2!$A:$A,Planilha2!K:K,"") -> 0 | AS49: =_xlfn.XLOOKUP(Tabela5[[#This Row],[UUID]],Planilha2!$A:$A,Planilha2!L:L,"") -> 0 | AT49: =_xlfn.XLOOKUP(Tabela5[[#This Row],[UUID]],Planilha2!$A:$A,Planilha2!M:M,"") -> 0 | AU49: =_xlfn.XLOOKUP(Tabela5[[#This Row],[UUID]],Planilha2!$A:$A,Planilha2!N:N,"") -> 0 | AV49: =_xlfn.XLOOKUP(Tabela5[[#This Row],[UUID]],Planilha2!$A:$A,Planilha2!O:O,"") -> 0
A50: COB-242924 | B50: Faturado | C50: 30121036 | D50: 1530586178 | E50: JONIEL SILVA PASSOS | F50: AVENIDA REGINA PACES S/N Q. 28, L. 11 PARQUE SANTA MARTA Inhumas GO 75405141 | G50: ADE-16643-C5V6S3 | H50: 46082 | I50: 202603 | J50: 288.09915 | L50: 288.1 | N50: 90520476 | O50: 46101 | P50: 46111 | R50: 15 | S50: 2 - CPF | T50: Em aberto - Vencido | U50: Em aberto - Vencido | V50: TTOLYCG | W50: 6 | X50: false | Y50: 6 | Z50: Em aberto - Vencido | AA50: ASSOCIAÇÃO GO-L1 | AB50: 35.686.965/0001-64 - ALEXANDRIA TECH | AC50: Estimado | AE50: 1 a 30 dias | AF50: d772f0a8-266c-46b9-b853-c7032d214f56 | AG50: 46111 | AH50: 1 a 30 dias | AI50: =_xlfn.XLOOKUP(Tabela5[[#This Row],[UUID]],Planilha2!$A:$A,Planilha2!B:B,"") -> 1 | AJ50: =_xlfn.XLOOKUP(Tabela5[[#This Row],[UUID]],Planilha2!$A:$A,Planilha2!C:C,"") -> 1 | AK50: =_xlfn.XLOOKUP(Tabela5[[#This Row],[UUID]],Planilha2!$A:$A,Planilha2!D:D,"") -> 1 | AL50: =_xlfn.XLOOKUP(Tabela5[[#This Row],[UUID]],Planilha2!$A:$A,Planilha2!E:E,"") -> 0 | AM50: =_xlfn.XLOOKUP(Tabela5[[#This Row],[UUID]],Planilha2!$A:$A,Planilha2!F:F,"") -> 1 | AN50: =_xlfn.XLOOKUP(Tabela5[[#This Row],[UUID]],Planilha2!$A:$A,Planilha2!G:G,"") -> 1 | AO50: =_xlfn.XLOOKUP(Tabela5[[#This Row],[UUID]],Planilha2!$A:$A,Planilha2!H:H,"") -> 1 | AP50: =_xlfn.XLOOKUP(Tabela5[[#This Row],[UUID]],Planilha2!$A:$A,Planilha2!I:I,"") -> 0 | AQ50: =_xlfn.XLOOKUP(Tabela5[[#This Row],[UUID]],Planilha2!$A:$A,Planilha2!J:J,"") -> 0 | AR50: =_xlfn.XLOOKUP(Tabela5[[#This Row],[UUID]],Planilha2!$A:$A,Planilha2!K:K,"") -> 0 | AS50: =_xlfn.XLOOKUP(Tabela5[[#This Row],[UUID]],Planilha2!$A:$A,Planilha2!L:L,"") -> 0 | AT50: =_xlfn.XLOOKUP(Tabela5[[#This Row],[UUID]],Planilha2!$A:$A,Planilha2!M:M,"") -> 1 | AU50: =_xlfn.XLOOKUP(Tabela5[[#This Row],[UUID]],Planilha2!$A:$A,Planilha2!N:N,"") -> 1 | AV50: =_xlfn.XLOOKUP(Tabela5[[#This Row],[UUID]],Planilha2!$A:$A,Planilha2!O:O,"") -> 1
A51: COB-242917 | B51: Faturado | C51: 10006533467 | D51: 68487860206 | E51: ARTAXERXES PENICHE DOS SANTOS | F51: AVENIDA MARILIA LOPES S/N Q. 14, L. 5, PARK ITAMARATY Aparecida de Goiânia GO 74990480 | G51: ADE-16615-Y2H7D3 | H51: 46082 | I51: 202603 | J51: 300.6252 | L51: 300.63 | N51: 90520466 | O51: 46101 | P51: 46111 | R51: 15 | S51: 2 - CPF | T51: Em aberto - Vencido | U51: Em aberto - Vencido | V51: L2NNE3E | W51: 6 | X51: false | Y51: 6 | Z51: Em aberto - Vencido | AA51: ASSOCIAÇÃO GO-L1 | AB51: 35.686.965/0001-64 - ALEXANDRIA TECH | AC51: Estimado | AE51: 1 a 30 dias | AF51: 54db5e57-6862-4b1f-af74-369836ed32ed | AG51: 46113 | AH51: 1 a 30 dias | AI51: =_xlfn.XLOOKUP(Tabela5[[#This Row],[UUID]],Planilha2!$A:$A,Planilha2!B:B,"") -> 1 | AJ51: =_xlfn.XLOOKUP(Tabela5[[#This Row],[UUID]],Planilha2!$A:$A,Planilha2!C:C,"") -> 1 | AK51: =_xlfn.XLOOKUP(Tabela5[[#This Row],[UUID]],Planilha2!$A:$A,Planilha2!D:D,"") -> 1 | AL51: =_xlfn.XLOOKUP(Tabela5[[#This Row],[UUID]],Planilha2!$A:$A,Planilha2!E:E,"") -> 0 | AM51: =_xlfn.XLOOKUP(Tabela5[[#This Row],[UUID]],Planilha2!$A:$A,Planilha2!F:F,"") -> 1 | AN51: =_xlfn.XLOOKUP(Tabela5[[#This Row],[UUID]],Planilha2!$A:$A,Planilha2!G:G,"") -> 1 | AO51: =_xlfn.XLOOKUP(Tabela5[[#This Row],[UUID]],Planilha2!$A:$A,Planilha2!H:H,"") -> 1 | AP51: =_xlfn.XLOOKUP(Tabela5[[#This Row],[UUID]],Planilha2!$A:$A,Planilha2!I:I,"") -> 0 | AQ51: =_xlfn.XLOOKUP(Tabela5[[#This Row],[UUID]],Planilha2!$A:$A,Planilha2!J:J,"") -> 0 | AR51: =_xlfn.XLOOKUP(Tabela5[[#This Row],[UUID]],Planilha2!$A:$A,Planilha2!K:K,"") -> 0 | AS51: =_xlfn.XLOOKUP(Tabela5[[#This Row],[UUID]],Planilha2!$A:$A,Planilha2!L:L,"") -> 0 | AT51: =_xlfn.XLOOKUP(Tabela5[[#This Row],[UUID]],Planilha2!$A:$A,Planilha2!M:M,"") -> 0 | AU51: =_xlfn.XLOOKUP(Tabela5[[#This Row],[UUID]],Planilha2!$A:$A,Planilha2!N:N,"") -> 1 | AV51: =_xlfn.XLOOKUP(Tabela5[[#This Row],[UUID]],Planilha2!$A:$A,Planilha2!O:O,"") -> 1
A52: COB-242915 | B52: Faturado | C52: 12451083 | D52: 72607831172 | E52: DINILSON BERBARDES SILVA JUNIOR | F52: AVENIDA FRANCISCO MAGALHAES S/N Q. 8, L. 8, SALA 1 SETOR URIAS MAGALHÃES Goiânia GO 74565480 | G52: ADE-16605-T1N8B1 | H52: 46082 | I52: 202603 | J52: 314.82139 | L52: 314.82 | N52: 90520280 | O52: 46101 | P52: 46111 | R52: 15 | S52: 2 - CPF | T52: Em aberto - Vencido | U52: Em aberto - Vencido | V52: 2U628M9 | W52: 6 | X52: false | Y52: 6 | Z52: Em aberto - Vencido | AA52: ASSOCIAÇÃO GO-L1 | AB52: 35.686.965/0001-64 - ALEXANDRIA TECH | AC52: Estimado | AE52: 1 a 30 dias | AF52: f25ea77f-195b-4789-b640-6a8f23ddbccb | AG52: 46117 | AH52: 1 a 30 dias | AI52: =_xlfn.XLOOKUP(Tabela5[[#This Row],[UUID]],Planilha2!$A:$A,Planilha2!B:B,"") -> 1 | AJ52: =_xlfn.XLOOKUP(Tabela5[[#This Row],[UUID]],Planilha2!$A:$A,Planilha2!C:C,"") -> 1 | AK52: =_xlfn.XLOOKUP(Tabela5[[#This Row],[UUID]],Planilha2!$A:$A,Planilha2!D:D,"") -> 14 | AL52: =_xlfn.XLOOKUP(Tabela5[[#This Row],[UUID]],Planilha2!$A:$A,Planilha2!E:E,"") -> 0 | AM52: =_xlfn.XLOOKUP(Tabela5[[#This Row],[UUID]],Planilha2!$A:$A,Planilha2!F:F,"") -> 1 | AN52: =_xlfn.XLOOKUP(Tabela5[[#This Row],[UUID]],Planilha2!$A:$A,Planilha2!G:G,"") -> 0 | AO52: =_xlfn.XLOOKUP(Tabela5[[#This Row],[UUID]],Planilha2!$A:$A,Planilha2!H:H,"") -> 0 | AP52: =_xlfn.XLOOKUP(Tabela5[[#This Row],[UUID]],Planilha2!$A:$A,Planilha2!I:I,"") -> 0 | AQ52: =_xlfn.XLOOKUP(Tabela5[[#This Row],[UUID]],Planilha2!$A:$A,Planilha2!J:J,"") -> 0 | AR52: =_xlfn.XLOOKUP(Tabela5[[#This Row],[UUID]],Planilha2!$A:$A,Planilha2!K:K,"") -> 0 | AS52: =_xlfn.XLOOKUP(Tabela5[[#This Row],[UUID]],Planilha2!$A:$A,Planilha2!L:L,"") -> 0 | AT52: =_xlfn.XLOOKUP(Tabela5[[#This Row],[UUID]],Planilha2!$A:$A,Planilha2!M:M,"") -> 1 | AU52: =_xlfn.XLOOKUP(Tabela5[[#This Row],[UUID]],Planilha2!$A:$A,Planilha2!N:N,"") -> 1 | AV52: =_xlfn.XLOOKUP(Tabela5[[#This Row],[UUID]],Planilha2!$A:$A,Planilha2!O:O,"") -> 1
A53: COB-242876 | B53: Faturado | C53: 10015117756 | D53: 91517192153 | E53: ANA PAULA PRIETO PERES | F53: RUA PE LUZO 26 Q. 12, L. 26 Jardim Dom Bosco Aparecida de Goiânia GO 74963550 | G53: ADE-16266-X5B8J0 | H53: 46082 | I53: 202603 | J53: 361.22991 | L53: 361.23 | N53: 90520381 | O53: 46101 | P53: 46111 | R53: 15 | S53: 2 - CPF | T53: Em aberto - Vencido | U53: Em aberto - Vencido | V53: 7WD3DXQ | W53: 6 | X53: false | Y53: 6 | Z53: Em aberto - Vencido | AA53: ASSOCIAÇÃO GO-L1 | AB53: 35.686.965/0001-64 - ALEXANDRIA TECH | AC53: Estimado | AE53: 1 a 30 dias | AF53: 419be122-5b90-48fc-8430-874a840fd82f | AG53: 46111 | AH53: 1 a 30 dias | AI53: =_xlfn.XLOOKUP(Tabela5[[#This Row],[UUID]],Planilha2!$A:$A,Planilha2!B:B,"") -> 1 | AJ53: =_xlfn.XLOOKUP(Tabela5[[#This Row],[UUID]],Planilha2!$A:$A,Planilha2!C:C,"") -> 1 | AK53: =_xlfn.XLOOKUP(Tabela5[[#This Row],[UUID]],Planilha2!$A:$A,Planilha2!D:D,"") -> 1 | AL53: =_xlfn.XLOOKUP(Tabela5[[#This Row],[UUID]],Planilha2!$A:$A,Planilha2!E:E,"") -> 0 | AM53: =_xlfn.XLOOKUP(Tabela5[[#This Row],[UUID]],Planilha2!$A:$A,Planilha2!F:F,"") -> 1 | AN53: =_xlfn.XLOOKUP(Tabela5[[#This Row],[UUID]],Planilha2!$A:$A,Planilha2!G:G,"") -> 1 | AO53: =_xlfn.XLOOKUP(Tabela5[[#This Row],[UUID]],Planilha2!$A:$A,Planilha2!H:H,"") -> 1 | AP53: =_xlfn.XLOOKUP(Tabela5[[#This Row],[UUID]],Planilha2!$A:$A,Planilha2!I:I,"") -> 0 | AQ53: =_xlfn.XLOOKUP(Tabela5[[#This Row],[UUID]],Planilha2!$A:$A,Planilha2!J:J,"") -> 0 | AR53: =_xlfn.XLOOKUP(Tabela5[[#This Row],[UUID]],Planilha2!$A:$A,Planilha2!K:K,"") -> 0 | AS53: =_xlfn.XLOOKUP(Tabela5[[#This Row],[UUID]],Planilha2!$A:$A,Planilha2!L:L,"") -> 0 | AT53: =_xlfn.XLOOKUP(Tabela5[[#This Row],[UUID]],Planilha2!$A:$A,Planilha2!M:M,"") -> 1 | AU53: =_xlfn.XLOOKUP(Tabela5[[#This Row],[UUID]],Planilha2!$A:$A,Planilha2!N:N,"") -> 1 | AV53: =_xlfn.XLOOKUP(Tabela5[[#This Row],[UUID]],Planilha2!$A:$A,Planilha2!O:O,"") -> 1
A54: COB-239246 | B54: Faturado | C54: 10040662746 | D54: 70186681151 | E54: GABRIELLE OHANA LINHARES DOS SANTOS | F54: RUA AUGUSTA, Q. 84, L. 1/12, S/N, APART - 101 A, BLOCO - A, OUTROS - COND RECIDENCIAL MARAVILLE PARQUE DAS NA PARQUE DAS NACOES CEP: 74957090 APARECIDA DE GOIANIA GO BRASIL | G54: ADE-16217-Z3T5G8 | H54: 46082 | I54: 202603 | J54: 170.75059 | L54: 170.75 | N54: 90520417 | O54: 46101 | P54: 46111 | R54: 15 | S54: 2 - CPF | T54: Em aberto - Vencido | U54: Em aberto - Vencido | V54: PKM5GSD | W54: 6 | X54: false | Y54: 6 | Z54: Em aberto - Vencido | AA54: ASSOCIAÇÃO GO-L1 | AB54: 35.686.965/0001-64 - ALEXANDRIA TECH | AE54: 1 a 30 dias | AF54: c30db5f6-12ac-4e0d-a396-f7f6f0784908 | AG54: 46111 | AH54: 1 a 30 dias | AI54: =_xlfn.XLOOKUP(Tabela5[[#This Row],[UUID]],Planilha2!$A:$A,Planilha2!B:B,"") -> 1 | AJ54: =_xlfn.XLOOKUP(Tabela5[[#This Row],[UUID]],Planilha2!$A:$A,Planilha2!C:C,"") -> 1 | AK54: =_xlfn.XLOOKUP(Tabela5[[#This Row],[UUID]],Planilha2!$A:$A,Planilha2!D:D,"") -> 8 | AL54: =_xlfn.XLOOKUP(Tabela5[[#This Row],[UUID]],Planilha2!$A:$A,Planilha2!E:E,"") -> 0 | AM54: =_xlfn.XLOOKUP(Tabela5[[#This Row],[UUID]],Planilha2!$A:$A,Planilha2!F:F,"") -> 1 | AN54: =_xlfn.XLOOKUP(Tabela5[[#This Row],[UUID]],Planilha2!$A:$A,Planilha2!G:G,"") -> 1 | AO54: =_xlfn.XLOOKUP(Tabela5[[#This Row],[UUID]],Planilha2!$A:$A,Planilha2!H:H,"") -> 1 | AP54: =_xlfn.XLOOKUP(Tabela5[[#This Row],[UUID]],Planilha2!$A:$A,Planilha2!I:I,"") -> 0 | AQ54: =_xlfn.XLOOKUP(Tabela5[[#This Row],[UUID]],Planilha2!$A:$A,Planilha2!J:J,"") -> 0 | AR54: =_xlfn.XLOOKUP(Tabela5[[#This Row],[UUID]],Planilha2!$A:$A,Planilha2!K:K,"") -> 0 | AS54: =_xlfn.XLOOKUP(Tabela5[[#This Row],[UUID]],Planilha2!$A:$A,Planilha2!L:L,"") -> 0 | AT54: =_xlfn.XLOOKUP(Tabela5[[#This Row],[UUID]],Planilha2!$A:$A,Planilha2!M:M,"") -> 1 | AU54: =_xlfn.XLOOKUP(Tabela5[[#This Row],[UUID]],Planilha2!$A:$A,Planilha2!N:N,"") -> 1 | AV54: =_xlfn.XLOOKUP(Tabela5[[#This Row],[UUID]],Planilha2!$A:$A,Planilha2!O:O,"") -> 1
A55: COB-242858 | B55: Faturado | C55: 16756137 | D55: 64839443149 | E55: MARCIO AUGUSTO DO NASCIMENTO | F55: RUA FRANCISCO F DOS SANTOS, Q. 17, L. 20/21, S/N, - CASA 3 S/N Q. 17, L. 20/21 - CASA 3 JARDIM BELA MORADA Aparecida de Goiânia GO 74920755 | G55: ADE-16166-N8L4N1 | H55: 46082 | I55: 202603 | J55: 299.79013 | L55: 299.79 | N55: 90520288 | O55: 46101 | P55: 46111 | R55: 15 | S55: 2 - CPF | T55: Em aberto - Vencido | U55: Em aberto - Vencido | V55: 0HCUR5H | W55: 6 | X55: false | Y55: 6 | Z55: Em aberto - Vencido | AA55: ASSOCIAÇÃO GO-L1 | AB55: 35.686.965/0001-64 - ALEXANDRIA TECH | AC55: Estimado | AE55: 1 a 30 dias | AF55: 2527fa4f-d8d6-4a12-bd32-a5b49e4236ea | AG55: 46117 | AH55: 1 a 30 dias | AI55: =_xlfn.XLOOKUP(Tabela5[[#This Row],[UUID]],Planilha2!$A:$A,Planilha2!B:B,"") -> 1 | AJ55: =_xlfn.XLOOKUP(Tabela5[[#This Row],[UUID]],Planilha2!$A:$A,Planilha2!C:C,"") -> 1 | AK55: =_xlfn.XLOOKUP(Tabela5[[#This Row],[UUID]],Planilha2!$A:$A,Planilha2!D:D,"") -> 1 | AL55: =_xlfn.XLOOKUP(Tabela5[[#This Row],[UUID]],Planilha2!$A:$A,Planilha2!E:E,"") -> 0 | AM55: =_xlfn.XLOOKUP(Tabela5[[#This Row],[UUID]],Planilha2!$A:$A,Planilha2!F:F,"") -> 1 | AN55: =_xlfn.XLOOKUP(Tabela5[[#This Row],[UUID]],Planilha2!$A:$A,Planilha2!G:G,"") -> 0 | AO55: =_xlfn.XLOOKUP(Tabela5[[#This Row],[UUID]],Planilha2!$A:$A,Planilha2!H:H,"") -> 0 | AP55: =_xlfn.XLOOKUP(Tabela5[[#This Row],[UUID]],Planilha2!$A:$A,Planilha2!I:I,"") -> 0 | AQ55: =_xlfn.XLOOKUP(Tabela5[[#This Row],[UUID]],Planilha2!$A:$A,Planilha2!J:J,"") -> 0 | AR55: =_xlfn.XLOOKUP(Tabela5[[#This Row],[UUID]],Planilha2!$A:$A,Planilha2!K:K,"") -> 0 | AS55: =_xlfn.XLOOKUP(Tabela5[[#This Row],[UUID]],Planilha2!$A:$A,Planilha2!L:L,"") -> 0 | AT55: =_xlfn.XLOOKUP(Tabela5[[#This Row],[UUID]],Planilha2!$A:$A,Planilha2!M:M,"") -> 1 | AU55: =_xlfn.XLOOKUP(Tabela5[[#This Row],[UUID]],Planilha2!$A:$A,Planilha2!N:N,"") -> 1 | AV55: =_xlfn.XLOOKUP(Tabela5[[#This Row],[UUID]],Planilha2!$A:$A,Planilha2!O:O,"") -> 1
A56: COB-242856 | B56: Faturado | C56: 10009855767 | D56: 64263495187 | E56: ADEILDO FREITAS DOS SANTOS | F56: RUA TAMBORIL S/N Q. 18, L. 9 Residencial Aldeia dos Sonhos Anápolis GO 75054763 | G56: ADE-16163-Z3J9Z5 | H56: 46082 | I56: 202603 | J56: 188.08168 | L56: 188.08 | N56: 90519541 | O56: 46101 | P56: 46111 | R56: 15 | S56: 2 - CPF | T56: Em aberto - Vencido | U56: Em aberto - Vencido | V56: BSDDXE8 | W56: 6 | X56: false | Y56: 6 | Z56: Em aberto - Vencido | AA56: ASSOCIAÇÃO GO-L1 | AB56: 35.686.965/0001-64 - ALEXANDRIA TECH | AC56: Estimado | AE56: 1 a 30 dias | AF56: 4ec7bd47-b1c2-455c-b845-dca37090d2a2 | AG56: 46111 | AH56: 1 a 30 dias | AI56: =_xlfn.XLOOKUP(Tabela5[[#This Row],[UUID]],Planilha2!$A:$A,Planilha2!B:B,"") -> 1 | AJ56: =_xlfn.XLOOKUP(Tabela5[[#This Row],[UUID]],Planilha2!$A:$A,Planilha2!C:C,"") -> 1 | AK56: =_xlfn.XLOOKUP(Tabela5[[#This Row],[UUID]],Planilha2!$A:$A,Planilha2!D:D,"") -> 1 | AL56: =_xlfn.XLOOKUP(Tabela5[[#This Row],[UUID]],Planilha2!$A:$A,Planilha2!E:E,"") -> 0 | AM56: =_xlfn.XLOOKUP(Tabela5[[#This Row],[UUID]],Planilha2!$A:$A,Planilha2!F:F,"") -> 1 | AN56: =_xlfn.XLOOKUP(Tabela5[[#This Row],[UUID]],Planilha2!$A:$A,Planilha2!G:G,"") -> 1 | AO56: =_xlfn.XLOOKUP(Tabela5[[#This Row],[UUID]],Planilha2!$A:$A,Planilha2!H:H,"") -> 1 | AP56: =_xlfn.XLOOKUP(Tabela5[[#This Row],[UUID]],Planilha2!$A:$A,Planilha2!I:I,"") -> 0 | AQ56: =_xlfn.XLOOKUP(Tabela5[[#This Row],[UUID]],Planilha2!$A:$A,Planilha2!J:J,"") -> 0 | AR56: =_xlfn.XLOOKUP(Tabela5[[#This Row],[UUID]],Planilha2!$A:$A,Planilha2!K:K,"") -> 0 | AS56: =_xlfn.XLOOKUP(Tabela5[[#This Row],[UUID]],Planilha2!$A:$A,Planilha2!L:L,"") -> 0 | AT56: =_xlfn.XLOOKUP(Tabela5[[#This Row],[UUID]],Planilha2!$A:$A,Planilha2!M:M,"") -> 1 | AU56: =_xlfn.XLOOKUP(Tabela5[[#This Row],[UUID]],Planilha2!$A:$A,Planilha2!N:N,"") -> 1 | AV56: =_xlfn.XLOOKUP(Tabela5[[#This Row],[UUID]],Planilha2!$A:$A,Planilha2!O:O,"") -> 1
A57: COB-242853 | B57: Faturado | C57: 21175342 | D57: 96259698100 | E57: MARCIA ALENCAR LEMOS | F57: RUA 03 S/N Q. 12, L. 9, - CASA 4 Jardim América Anápolis GO 75115680 | G57: ADE-16157-P4X8F5 | H57: 46082 | I57: 202603 | J57: 141.9619 | L57: 141.96 | N57: 90520513 | O57: 46101 | P57: 46111 | R57: 15 | S57: 2 - CPF | T57: Em aberto - Vencido | U57: Em aberto - Vencido | V57: 81MQAQ1 | W57: 6 | X57: false | Y57: 6 | Z57: Em aberto - Vencido | AA57: ASSOCIAÇÃO GO-L1 | AB57: 35.686.965/0001-64 - ALEXANDRIA TECH | AC57: Estimado | AE57: 1 a 30 dias | AF57: c5d3258c-00e2-4c18-986a-405acffe1630 | AG57: 46111 | AH57: 1 a 30 dias | AI57: =_xlfn.XLOOKUP(Tabela5[[#This Row],[UUID]],Planilha2!$A:$A,Planilha2!B:B,"") -> 1 | AJ57: =_xlfn.XLOOKUP(Tabela5[[#This Row],[UUID]],Planilha2!$A:$A,Planilha2!C:C,"") -> 1 | AK57: =_xlfn.XLOOKUP(Tabela5[[#This Row],[UUID]],Planilha2!$A:$A,Planilha2!D:D,"") -> 1 | AL57: =_xlfn.XLOOKUP(Tabela5[[#This Row],[UUID]],Planilha2!$A:$A,Planilha2!E:E,"") -> 0 | AM57: =_xlfn.XLOOKUP(Tabela5[[#This Row],[UUID]],Planilha2!$A:$A,Planilha2!F:F,"") -> 1 | AN57: =_xlfn.XLOOKUP(Tabela5[[#This Row],[UUID]],Planilha2!$A:$A,Planilha2!G:G,"") -> 1 | AO57: =_xlfn.XLOOKUP(Tabela5[[#This Row],[UUID]],Planilha2!$A:$A,Planilha2!H:H,"") -> 1 | AP57: =_xlfn.XLOOKUP(Tabela5[[#This Row],[UUID]],Planilha2!$A:$A,Planilha2!I:I,"") -> 0 | AQ57: =_xlfn.XLOOKUP(Tabela5[[#This Row],[UUID]],Planilha2!$A:$A,Planilha2!J:J,"") -> 0 | AR57: =_xlfn.XLOOKUP(Tabela5[[#This Row],[UUID]],Planilha2!$A:$A,Planilha2!K:K,"") -> 0 | AS57: =_xlfn.XLOOKUP(Tabela5[[#This Row],[UUID]],Planilha2!$A:$A,Planilha2!L:L,"") -> 0 | AT57: =_xlfn.XLOOKUP(Tabela5[[#This Row],[UUID]],Planilha2!$A:$A,Planilha2!M:M,"") -> 1 | AU57: =_xlfn.XLOOKUP(Tabela5[[#This Row],[UUID]],Planilha2!$A:$A,Planilha2!N:N,"") -> 1 | AV57: =_xlfn.XLOOKUP(Tabela5[[#This Row],[UUID]],Planilha2!$A:$A,Planilha2!O:O,"") -> 1
A58: COB-242843 | B58: Faturado | C58: 10033775700 | D58: 18792197 | E58: LIGIANE RIBEIRO MARANHÃO SILVA | F58: RUA PA-19 S/N Q. 16, L. 22, CASA 2 Parque Alvorada Senador Canedo GO 75255728 | G58: ADE-16029-X3J9V5 | H58: 46082 | I58: 202603 | J58: 393.46146 | K58: 10.89 | L58: 404.35 | N58: 90520081 | O58: 46101 | P58: 46111 | R58: 15 | S58: 2 - CPF | T58: Em aberto - Vencido | U58: Em aberto - Vencido | V58: WX7TZLU | W58: 6 | X58: false | Y58: 6 | Z58: Em aberto - Vencido | AA58: ASSOCIAÇÃO GO-L1 | AB58: 35.686.965/0001-64 - ALEXANDRIA TECH | AC58: Estimado | AE58: 1 a 30 dias | AF58: 59015a73-c946-4cf3-b22f-1e05daa5b73a | AG58: 46113 | AH58: 1 a 30 dias | AI58: =_xlfn.XLOOKUP(Tabela5[[#This Row],[UUID]],Planilha2!$A:$A,Planilha2!B:B,"") -> 1 | AJ58: =_xlfn.XLOOKUP(Tabela5[[#This Row],[UUID]],Planilha2!$A:$A,Planilha2!C:C,"") -> 1 | AK58: =_xlfn.XLOOKUP(Tabela5[[#This Row],[UUID]],Planilha2!$A:$A,Planilha2!D:D,"") -> 1 | AL58: =_xlfn.XLOOKUP(Tabela5[[#This Row],[UUID]],Planilha2!$A:$A,Planilha2!E:E,"") -> 0 | AM58: =_xlfn.XLOOKUP(Tabela5[[#This Row],[UUID]],Planilha2!$A:$A,Planilha2!F:F,"") -> 1 | AN58: =_xlfn.XLOOKUP(Tabela5[[#This Row],[UUID]],Planilha2!$A:$A,Planilha2!G:G,"") -> 1 | AO58: =_xlfn.XLOOKUP(Tabela5[[#This Row],[UUID]],Planilha2!$A:$A,Planilha2!H:H,"") -> 1 | AP58: =_xlfn.XLOOKUP(Tabela5[[#This Row],[UUID]],Planilha2!$A:$A,Planilha2!I:I,"") -> 0 | AQ58: =_xlfn.XLOOKUP(Tabela5[[#This Row],[UUID]],Planilha2!$A:$A,Planilha2!J:J,"") -> 0 | AR58: =_xlfn.XLOOKUP(Tabela5[[#This Row],[UUID]],Planilha2!$A:$A,Planilha2!K:K,"") -> 0 | AS58: =_xlfn.XLOOKUP(Tabela5[[#This Row],[UUID]],Planilha2!$A:$A,Planilha2!L:L,"") -> 0 | AT58: =_xlfn.XLOOKUP(Tabela5[[#This Row],[UUID]],Planilha2!$A:$A,Planilha2!M:M,"") -> 0 | AU58: =_xlfn.XLOOKUP(Tabela5[[#This Row],[UUID]],Planilha2!$A:$A,Planilha2!N:N,"") -> 1 | AV58: =_xlfn.XLOOKUP(Tabela5[[#This Row],[UUID]],Planilha2!$A:$A,Planilha2!O:O,"") -> 1
A59: COB-242842 | B59: Faturado | C59: 10041062092 | D59: 20498819000138 | E59: COMERCIAL DE ALIMENTOS PLANALTO LTDA | F59: RUA 02 S/N Q. 14, L. 12A JARDIM PLANALTO Luziânia GO 72850-000 | G59: ADE-16020-G7V6T7 | H59: 46082 | I59: 202603 | J59: 4565.3277 | L59: 4565.33 | N59: 90520294 | O59: 46101 | P59: 46111 | R59: 15 | S59: 1 - CNPJ | T59: Em aberto - Vencido | U59: Em aberto - Vencido | V59: FWT0VB0 | W59: 6 | X59: false | Y59: 6 | Z59: Em aberto - Vencido | AA59: ASSOCIAÇÃO GO-L1 | AB59: 35.686.965/0001-64 - ALEXANDRIA TECH | AC59: Estimado | AE59: 1 a 30 dias | AF59: ee305644-273c-4927-b5b1-6b464985316a | AG59: 46111 | AH59: 1 a 30 dias | AI59: =_xlfn.XLOOKUP(Tabela5[[#This Row],[UUID]],Planilha2!$A:$A,Planilha2!B:B,"") -> 1 | AJ59: =_xlfn.XLOOKUP(Tabela5[[#This Row],[UUID]],Planilha2!$A:$A,Planilha2!C:C,"") -> 1 | AK59: =_xlfn.XLOOKUP(Tabela5[[#This Row],[UUID]],Planilha2!$A:$A,Planilha2!D:D,"") -> 2 | AL59: =_xlfn.XLOOKUP(Tabela5[[#This Row],[UUID]],Planilha2!$A:$A,Planilha2!E:E,"") -> 0 | AM59: =_xlfn.XLOOKUP(Tabela5[[#This Row],[UUID]],Planilha2!$A:$A,Planilha2!F:F,"") -> 1 | AN59: =_xlfn.XLOOKUP(Tabela5[[#This Row],[UUID]],Planilha2!$A:$A,Planilha2!G:G,"") -> 1 | AO59: =_xlfn.XLOOKUP(Tabela5[[#This Row],[UUID]],Planilha2!$A:$A,Planilha2!H:H,"") -> 1 | AP59: =_xlfn.XLOOKUP(Tabela5[[#This Row],[UUID]],Planilha2!$A:$A,Planilha2!I:I,"") -> 0 | AQ59: =_xlfn.XLOOKUP(Tabela5[[#This Row],[UUID]],Planilha2!$A:$A,Planilha2!J:J,"") -> 0 | AR59: =_xlfn.XLOOKUP(Tabela5[[#This Row],[UUID]],Planilha2!$A:$A,Planilha2!K:K,"") -> 0 | AS59: =_xlfn.XLOOKUP(Tabela5[[#This Row],[UUID]],Planilha2!$A:$A,Planilha2!L:L,"") -> 0 | AT59: =_xlfn.XLOOKUP(Tabela5[[#This Row],[UUID]],Planilha2!$A:$A,Planilha2!M:M,"") -> 1 | AU59: =_xlfn.XLOOKUP(Tabela5[[#This Row],[UUID]],Planilha2!$A:$A,Planilha2!N:N,"") -> 1 | AV59: =_xlfn.XLOOKUP(Tabela5[[#This Row],[UUID]],Planilha2!$A:$A,Planilha2!O:O,"") -> 1
A60: COB-242841 | B60: Faturado | C60: 10014398310 | D60: 35350014803 | E60: WELINGTON DE JESUS CRUZ | F60: RUA 03 S/N Q. 1, L. 12, TONICO BENTO Quirinópolis GO 75860-000 | G60: ADE-16019-Q6X4Z6 | H60: 46082 | I60: 202603 | J60: 376.61657 | L60: 376.62 | N60: 90520504 | O60: 46101 | P60: 46111 | R60: 15 | S60: 2 - CPF | T60: Em aberto - Vencido | U60: Em aberto - Vencido | V60: J6CY555 | W60: 6 | X60: false | Y60: 6 | Z60: Em aberto - Vencido | AA60: ASSOCIAÇÃO GO-L1 | AB60: 35.686.965/0001-64 - ALEXANDRIA TECH | AC60: Estimado | AE60: 1 a 30 dias | AF60: c1f756c9-3fed-4eb4-851b-a3beb814f7e4 | AG60: 46111 | AH60: 1 a 30 dias | AI60: =_xlfn.XLOOKUP(Tabela5[[#This Row],[UUID]],Planilha2!$A:$A,Planilha2!B:B,"") -> 1 | AJ60: =_xlfn.XLOOKUP(Tabela5[[#This Row],[UUID]],Planilha2!$A:$A,Planilha2!C:C,"") -> 1 | AK60: =_xlfn.XLOOKUP(Tabela5[[#This Row],[UUID]],Planilha2!$A:$A,Planilha2!D:D,"") -> 1 | AL60: =_xlfn.XLOOKUP(Tabela5[[#This Row],[UUID]],Planilha2!$A:$A,Planilha2!E:E,"") -> 0 | AM60: =_xlfn.XLOOKUP(Tabela5[[#This Row],[UUID]],Planilha2!$A:$A,Planilha2!F:F,"") -> 1 | AN60: =_xlfn.XLOOKUP(Tabela5[[#This Row],[UUID]],Planilha2!$A:$A,Planilha2!G:G,"") -> 1 | AO60: =_xlfn.XLOOKUP(Tabela5[[#This Row],[UUID]],Planilha2!$A:$A,Planilha2!H:H,"") -> 1 | AP60: =_xlfn.XLOOKUP(Tabela5[[#This Row],[UUID]],Planilha2!$A:$A,Planilha2!I:I,"") -> 0 | AQ60: =_xlfn.XLOOKUP(Tabela5[[#This Row],[UUID]],Planilha2!$A:$A,Planilha2!J:J,"") -> 0 | AR60: =_xlfn.XLOOKUP(Tabela5[[#This Row],[UUID]],Planilha2!$A:$A,Planilha2!K:K,"") -> 0 | AS60: =_xlfn.XLOOKUP(Tabela5[[#This Row],[UUID]],Planilha2!$A:$A,Planilha2!L:L,"") -> 0 | AT60: =_xlfn.XLOOKUP(Tabela5[[#This Row],[UUID]],Planilha2!$A:$A,Planilha2!M:M,"") -> 1 | AU60: =_xlfn.XLOOKUP(Tabela5[[#This Row],[UUID]],Planilha2!$A:$A,Planilha2!N:N,"") -> 1 | AV60: =_xlfn.XLOOKUP(Tabela5[[#This Row],[UUID]],Planilha2!$A:$A,Planilha2!O:O,"") -> 1
A61: COB-126342 | B61: Faturado | C61: 730672 | D61: 31802416000157 | E61: CONDOMINIO DO ED VAN GOGH | F61: AV AFONSO PENA 404 CONDOMINIO , ED VAN GOGH PRAIA DA COSTA / VILA VELHA - ES CEP: 29101-442 | G61: ADE-12090-Q5C4B4 | H61: 45839 | I61: 202507 | J61: 1406.603 | L61: 1406.6 | N61: 90364325 | O61: 45916 | P61: 45926 | R61: 200 | S61: 1 - CNPJ | T61: Em aberto - Vencido | U61: Em aberto - Vencido | V61: PW3740Q | W61: 6 | X61: false | Y61: 6 | Z61: Em aberto - Vencido | AA61: ASSOCIAÇÃO ES-L1 | AB61: 35.686.965/0001-64 - ALEXANDRIA TECH | AE61: 171 a 450 dias | AF61: d600c44e-0068-4d48-bf0a-635d196f7ef6 | AG61: 45965 | AH61: Maior que 90 | AI61: =_xlfn.XLOOKUP(Tabela5[[#This Row],[UUID]],Planilha2!$A:$A,Planilha2!B:B,"") -> 0 | AJ61: =_xlfn.XLOOKUP(Tabela5[[#This Row],[UUID]],Planilha2!$A:$A,Planilha2!C:C,"") -> 0 | AK61: =_xlfn.XLOOKUP(Tabela5[[#This Row],[UUID]],Planilha2!$A:$A,Planilha2!D:D,"") -> 0 | AL61: =_xlfn.XLOOKUP(Tabela5[[#This Row],[UUID]],Planilha2!$A:$A,Planilha2!E:E,"") -> 14 | AM61: =_xlfn.XLOOKUP(Tabela5[[#This Row],[UUID]],Planilha2!$A:$A,Planilha2!F:F,"") -> 0 | AN61: =_xlfn.XLOOKUP(Tabela5[[#This Row],[UUID]],Planilha2!$A:$A,Planilha2!G:G,"") -> 0 | AO61: =_xlfn.XLOOKUP(Tabela5[[#This Row],[UUID]],Planilha2!$A:$A,Planilha2!H:H,"") -> 0 | AP61: =_xlfn.XLOOKUP(Tabela5[[#This Row],[UUID]],Planilha2!$A:$A,Planilha2!I:I,"") -> 0 | AQ61: =_xlfn.XLOOKUP(Tabela5[[#This Row],[UUID]],Planilha2!$A:$A,Planilha2!J:J,"") -> 0 | AR61: =_xlfn.XLOOKUP(Tabela5[[#This Row],[UUID]],Planilha2!$A:$A,Planilha2!K:K,"") -> 0 | AS61: =_xlfn.XLOOKUP(Tabela5[[#This Row],[UUID]],Planilha2!$A:$A,Planilha2!L:L,"") -> 0 | AT61: =_xlfn.XLOOKUP(Tabela5[[#This Row],[UUID]],Planilha2!$A:$A,Planilha2!M:M,"") -> 0 | AU61: =_xlfn.XLOOKUP(Tabela5[[#This Row],[UUID]],Planilha2!$A:$A,Planilha2!N:N,"") -> 0 | AV61: =_xlfn.XLOOKUP(Tabela5[[#This Row],[UUID]],Planilha2!$A:$A,Planilha2!O:O,"") -> 0
A62: COB-176565 | B62: Faturado | C62: 186898 | D62: 83854487720 | E62: MARCIO DE OLIVEIRA GOMES | F62: RUA S LUIZ 17 CAIXA 01 BOA SORTE / CARIACICA - ES CEP: 29141-210 | G62: ADE-12094-X2V2J5 | H62: 45839 | I62: 202507 | J62: 385.80053 | L62: 385.8 | N62: 90427196 | O62: 45995 | P62: 46006 | R62: 120 | S62: 2 - CPF | T62: Em aberto - Vencido | U62: Em aberto - Vencido | V62: N8Z1P41 | W62: 6 | X62: false | Y62: 6 | Z62: Em aberto - Vencido | AA62: ASSOCIAÇÃO ES-L1 | AB62: 35.686.965/0001-64 - ALEXANDRIA TECH | AE62: 61 a 120 dias | AF62: a25d56ec-8251-4ec9-9c91-5175052204f6 | AG62: 45917 | AH62: Maior que 90 | AI62: =_xlfn.XLOOKUP(Tabela5[[#This Row],[UUID]],Planilha2!$A:$A,Planilha2!B:B,"") -> 0 | AJ62: =_xlfn.XLOOKUP(Tabela5[[#This Row],[UUID]],Planilha2!$A:$A,Planilha2!C:C,"") -> 0 | AK62: =_xlfn.XLOOKUP(Tabela5[[#This Row],[UUID]],Planilha2!$A:$A,Planilha2!D:D,"") -> 0 | AL62: =_xlfn.XLOOKUP(Tabela5[[#This Row],[UUID]],Planilha2!$A:$A,Planilha2!E:E,"") -> 5 | AM62: =_xlfn.XLOOKUP(Tabela5[[#This Row],[UUID]],Planilha2!$A:$A,Planilha2!F:F,"") -> 0 | AN62: =_xlfn.XLOOKUP(Tabela5[[#This Row],[UUID]],Planilha2!$A:$A,Planilha2!G:G,"") -> 0 | AO62: =_xlfn.XLOOKUP(Tabela5[[#This Row],[UUID]],Planilha2!$A:$A,Planilha2!H:H,"") -> 0 | AP62: =_xlfn.XLOOKUP(Tabela5[[#This Row],[UUID]],Planilha2!$A:$A,Planilha2!I:I,"") -> 0 | AQ62: =_xlfn.XLOOKUP(Tabela5[[#This Row],[UUID]],Planilha2!$A:$A,Planilha2!J:J,"") -> 0 | AR62: =_xlfn.XLOOKUP(Tabela5[[#This Row],[UUID]],Planilha2!$A:$A,Planilha2!K:K,"") -> 0 | AS62: =_xlfn.XLOOKUP(Tabela5[[#This Row],[UUID]],Planilha2!$A:$A,Planilha2!L:L,"") -> 0 | AT62: =_xlfn.XLOOKUP(Tabela5[[#This Row],[UUID]],Planilha2!$A:$A,Planilha2!M:M,"") -> 0 | AU62: =_xlfn.XLOOKUP(Tabela5[[#This Row],[UUID]],Planilha2!$A:$A,Planilha2!N:N,"") -> 0 | AV62: =_xlfn.XLOOKUP(Tabela5[[#This Row],[UUID]],Planilha2!$A:$A,Planilha2!O:O,"") -> 0
A63: COB-176579 | B63: Faturado | C63: 160424272 | D63: 17642939752 | E63: IGOR ISAO RODRIGUES MATUFUZI | F63: RUA JOSE PENNA MEDINA 216 LJ 06 PRAIA DA COSTA / VILA VELHA - ES CEP: 29101-320 | G63: ADE-12095-X0T0V1 | H63: 45839 | I63: 202507 | J63: 514.63092 | L63: 514.63 | N63: 90427201 | O63: 45995 | P63: 46006 | R63: 120 | S63: 2 - CPF | T63: Em aberto - Vencido | U63: Em aberto - Vencido | V63: UL1DT12 | W63: 6 | X63: false | Y63: 6 | Z63: Em aberto - Vencido | AA63: ASSOCIAÇÃO ES-L1 | AB63: 35.686.965/0001-64 - ALEXANDRIA TECH | AE63: 61 a 120 dias | AF63: 0c2e3a17-c3de-4647-bfee-f7877de45cb2 | AG63: 46006 | AH63: Maior que 90 | AI63: =_xlfn.XLOOKUP(Tabela5[[#This Row],[UUID]],Planilha2!$A:$A,Planilha2!B:B,"") -> 0 | AJ63: =_xlfn.XLOOKUP(Tabela5[[#This Row],[UUID]],Planilha2!$A:$A,Planilha2!C:C,"") -> 0 | AK63: =_xlfn.XLOOKUP(Tabela5[[#This Row],[UUID]],Planilha2!$A:$A,Planilha2!D:D,"") -> 0 | AL63: =_xlfn.XLOOKUP(Tabela5[[#This Row],[UUID]],Planilha2!$A:$A,Planilha2!E:E,"") -> 4 | AM63: =_xlfn.XLOOKUP(Tabela5[[#This Row],[UUID]],Planilha2!$A:$A,Planilha2!F:F,"") -> 0 | AN63: =_xlfn.XLOOKUP(Tabela5[[#This Row],[UUID]],Planilha2!$A:$A,Planilha2!G:G,"") -> 0 | AO63: =_xlfn.XLOOKUP(Tabela5[[#This Row],[UUID]],Planilha2!$A:$A,Planilha2!H:H,"") -> 0 | AP63: =_xlfn.XLOOKUP(Tabela5[[#This Row],[UUID]],Planilha2!$A:$A,Planilha2!I:I,"") -> 0 | AQ63: =_xlfn.XLOOKUP(Tabela5[[#This Row],[UUID]],Planilha2!$A:$A,Planilha2!J:J,"") -> 0 | AR63: =_xlfn.XLOOKUP(Tabela5[[#This Row],[UUID]],Planilha2!$A:$A,Planilha2!K:K,"") -> 0 | AS63: =_xlfn.XLOOKUP(Tabela5[[#This Row],[UUID]],Planilha2!$A:$A,Planilha2!L:L,"") -> 1 | AT63: =_xlfn.XLOOKUP(Tabela5[[#This Row],[UUID]],Planilha2!$A:$A,Planilha2!M:M,"") -> 0 | AU63: =_xlfn.XLOOKUP(Tabela5[[#This Row],[UUID]],Planilha2!$A:$A,Planilha2!N:N,"") -> 0 | AV63: =_xlfn.XLOOKUP(Tabela5[[#This Row],[UUID]],Planilha2!$A:$A,Planilha2!O:O,"") -> 0
A64: COB-242830 | B64: Faturado | C64: 200144613 | D64: 59035811100 | E64: JORDANIA JOSE DE SOUZA SANTOS | F64: RUA 23 S/N Q. 43, L. 26, Jardim Tiradentes Aparecida de Goiânia GO 74961180 | G64: ADE-15946-T5L1S2 | H64: 46082 | I64: 202603 | J64: 164.95155 | L64: 164.95 | N64: 90520478 | O64: 46101 | P64: 46111 | R64: 15 | S64: 2 - CPF | T64: Em aberto - Vencido | U64: Em aberto - Vencido | V64: GRMHEJG | W64: 6 | X64: false | Y64: 6 | Z64: Em aberto - Vencido | AA64: ASSOCIAÇÃO GO-L1 | AB64: 35.686.965/0001-64 - ALEXANDRIA TECH | AC64: Estimado | AE64: 1 a 30 dias | AF64: 01a83a6c-2a26-45a0-a6ab-55d69fcfc7fb | AG64: 46115 | AH64: 1 a 30 dias | AI64: =_xlfn.XLOOKUP(Tabela5[[#This Row],[UUID]],Planilha2!$A:$A,Planilha2!B:B,"") -> 1 | AJ64: =_xlfn.XLOOKUP(Tabela5[[#This Row],[UUID]],Planilha2!$A:$A,Planilha2!C:C,"") -> 1 | AK64: =_xlfn.XLOOKUP(Tabela5[[#This Row],[UUID]],Planilha2!$A:$A,Planilha2!D:D,"") -> 1 | AL64: =_xlfn.XLOOKUP(Tabela5[[#This Row],[UUID]],Planilha2!$A:$A,Planilha2!E:E,"") -> 0 | AM64: =_xlfn.XLOOKUP(Tabela5[[#This Row],[UUID]],Planilha2!$A:$A,Planilha2!F:F,"") -> 1 | AN64: =_xlfn.XLOOKUP(Tabela5[[#This Row],[UUID]],Planilha2!$A:$A,Planilha2!G:G,"") -> 1 | AO64: =_xlfn.XLOOKUP(Tabela5[[#This Row],[UUID]],Planilha2!$A:$A,Planilha2!H:H,"") -> 0 | AP64: =_xlfn.XLOOKUP(Tabela5[[#This Row],[UUID]],Planilha2!$A:$A,Planilha2!I:I,"") -> 0 | AQ64: =_xlfn.XLOOKUP(Tabela5[[#This Row],[UUID]],Planilha2!$A:$A,Planilha2!J:J,"") -> 0 | AR64: =_xlfn.XLOOKUP(Tabela5[[#This Row],[UUID]],Planilha2!$A:$A,Planilha2!K:K,"") -> 0 | AS64: =_xlfn.XLOOKUP(Tabela5[[#This Row],[UUID]],Planilha2!$A:$A,Planilha2!L:L,"") -> 0 | AT64: =_xlfn.XLOOKUP(Tabela5[[#This Row],[UUID]],Planilha2!$A:$A,Planilha2!M:M,"") -> 0 | AU64: =_xlfn.XLOOKUP(Tabela5[[#This Row],[UUID]],Planilha2!$A:$A,Planilha2!N:N,"") -> 1 | AV64: =_xlfn.XLOOKUP(Tabela5[[#This Row],[UUID]],Planilha2!$A:$A,Planilha2!O:O,"") -> 1
A65: COB-242828 | B65: Faturado | C65: 15065339 | D65: 77621085134 | E65: RAMON RONES SANTOS DE OLIVEIRA | F65: RUA GAL GLICERIO S/N Q. 117, L. 46 Jardim Buriti Sereno Aparecida de Goiânia GO 74943080 | G65: ADE-15941-W3D0B3 | H65: 46082 | I65: 202603 | J65: 247.0988 | L65: 247.1 | N65: 90520135 | O65: 46101 | P65: 46111 | R65: 15 | S65: 2 - CPF | T65: Em aberto - Vencido | U65: Em aberto - Vencido | V65: F3JK089 | W65: 6 | X65: false | Y65: 6 | Z65: Em aberto - Vencido | AA65: ASSOCIAÇÃO GO-L1 | AB65: 35.686.965/0001-64 - ALEXANDRIA TECH | AC65: Estimado | AE65: 1 a 30 dias | AF65: 845d21c7-65b4-4c7a-9558-e5d0896e18f3 | AG65: 46120 | AH65: 1 a 30 dias | AI65: =_xlfn.XLOOKUP(Tabela5[[#This Row],[UUID]],Planilha2!$A:$A,Planilha2!B:B,"") -> 1 | AJ65: =_xlfn.XLOOKUP(Tabela5[[#This Row],[UUID]],Planilha2!$A:$A,Planilha2!C:C,"") -> 1 | AK65: =_xlfn.XLOOKUP(Tabela5[[#This Row],[UUID]],Planilha2!$A:$A,Planilha2!D:D,"") -> 1 | AL65: =_xlfn.XLOOKUP(Tabela5[[#This Row],[UUID]],Planilha2!$A:$A,Planilha2!E:E,"") -> 0 | AM65: =_xlfn.XLOOKUP(Tabela5[[#This Row],[UUID]],Planilha2!$A:$A,Planilha2!F:F,"") -> 1 | AN65: =_xlfn.XLOOKUP(Tabela5[[#This Row],[UUID]],Planilha2!$A:$A,Planilha2!G:G,"") -> 0 | AO65: =_xlfn.XLOOKUP(Tabela5[[#This Row],[UUID]],Planilha2!$A:$A,Planilha2!H:H,"") -> 0 | AP65: =_xlfn.XLOOKUP(Tabela5[[#This Row],[UUID]],Planilha2!$A:$A,Planilha2!I:I,"") -> 0 | AQ65: =_xlfn.XLOOKUP(Tabela5[[#This Row],[UUID]],Planilha2!$A:$A,Planilha2!J:J,"") -> 0 | AR65: =_xlfn.XLOOKUP(Tabela5[[#This Row],[UUID]],Planilha2!$A:$A,Planilha2!K:K,"") -> 0 | AS65: =_xlfn.XLOOKUP(Tabela5[[#This Row],[UUID]],Planilha2!$A:$A,Planilha2!L:L,"") -> 0 | AT65: =_xlfn.XLOOKUP(Tabela5[[#This Row],[UUID]],Planilha2!$A:$A,Planilha2!M:M,"") -> 0 | AU65: =_xlfn.XLOOKUP(Tabela5[[#This Row],[UUID]],Planilha2!$A:$A,Planilha2!N:N,"") -> 1 | AV65: =_xlfn.XLOOKUP(Tabela5[[#This Row],[UUID]],Planilha2!$A:$A,Planilha2!O:O,"") -> 1
A66: COB-239356 | B66: Faturado | C66: 10020744828 | D66: 71132155134 | E66: FREDERICK VIEIRA SILVA | F66: RUA RIT-1, Q. AREA, L. AREA, S/N, - COND ALTO DA BOA VISTA, CASA - 90B RESIDENCIAL ITAMARACA CEP: 74580810 GOIANIA GO BRASIL | G66: ADE-15919-Y9C7N9 | H66: 46082 | I66: 202603 | J66: 298.82708 | L66: 298.83 | N66: 90519916 | O66: 46101 | P66: 46111 | R66: 15 | S66: 2 - CPF | T66: Em aberto - Vencido | U66: Em aberto - Vencido | V66: 270YDAM | W66: 6 | X66: false | Y66: 6 | Z66: Em aberto - Vencido | AA66: ASSOCIAÇÃO GO-L1 | AB66: 35.686.965/0001-64 - ALEXANDRIA TECH | AE66: 1 a 30 dias | AF66: 104b1b4e-713d-41f2-90dd-8003e873ffa7 | AG66: 46106 | AH66: 1 a 30 dias | AI66: =_xlfn.XLOOKUP(Tabela5[[#This Row],[UUID]],Planilha2!$A:$A,Planilha2!B:B,"") -> 1 | AJ66: =_xlfn.XLOOKUP(Tabela5[[#This Row],[UUID]],Planilha2!$A:$A,Planilha2!C:C,"") -> 2 | AK66: =_xlfn.XLOOKUP(Tabela5[[#This Row],[UUID]],Planilha2!$A:$A,Planilha2!D:D,"") -> 5 | AL66: =_xlfn.XLOOKUP(Tabela5[[#This Row],[UUID]],Planilha2!$A:$A,Planilha2!E:E,"") -> 0 | AM66: =_xlfn.XLOOKUP(Tabela5[[#This Row],[UUID]],Planilha2!$A:$A,Planilha2!F:F,"") -> 1 | AN66: =_xlfn.XLOOKUP(Tabela5[[#This Row],[UUID]],Planilha2!$A:$A,Planilha2!G:G,"") -> 1 | AO66: =_xlfn.XLOOKUP(Tabela5[[#This Row],[UUID]],Planilha2!$A:$A,Planilha2!H:H,"") -> 1 | AP66: =_xlfn.XLOOKUP(Tabela5[[#This Row],[UUID]],Planilha2!$A:$A,Planilha2!I:I,"") -> 1 | AQ66: =_xlfn.XLOOKUP(Tabela5[[#This Row],[UUID]],Planilha2!$A:$A,Planilha2!J:J,"") -> 1 | AR66: =_xlfn.XLOOKUP(Tabela5[[#This Row],[UUID]],Planilha2!$A:$A,Planilha2!K:K,"") -> 0 | AS66: =_xlfn.XLOOKUP(Tabela5[[#This Row],[UUID]],Planilha2!$A:$A,Planilha2!L:L,"") -> 0 | AT66: =_xlfn.XLOOKUP(Tabela5[[#This Row],[UUID]],Planilha2!$A:$A,Planilha2!M:M,"") -> 0 | AU66: =_xlfn.XLOOKUP(Tabela5[[#This Row],[UUID]],Planilha2!$A:$A,Planilha2!N:N,"") -> 1 | AV66: =_xlfn.XLOOKUP(Tabela5[[#This Row],[UUID]],Planilha2!$A:$A,Planilha2!O:O,"") -> 1
A67: COB-242814 | B67: Faturado | C67: 20581129 | D67: 12362166104 | E67: ILSON MENDES DE MORAIS | F67: Rua Sete de Setembro S/N Q. 16, L. 25, - CASA 103 Alvorada Anápolis GO 75084-620 | G67: ADE-15888-F2C0L3 | H67: 46082 | I67: 202603 | J67: 200.4168 | L67: 200.42 | N67: 90520387 | O67: 46101 | P67: 46111 | R67: 15 | S67: 2 - CPF | T67: Em aberto - Vencido | U67: Em aberto - Vencido | V67: RC7VT0M | W67: 6 | X67: false | Y67: 6 | Z67: Em aberto - Vencido | AA67: ASSOCIAÇÃO GO-L1 | AB67: 35.686.965/0001-64 - ALEXANDRIA TECH | AC67: Estimado | AE67: 1 a 30 dias | AF67: 3898e7b5-f0d7-4362-a160-8d9e3677238c | AG67: 46117 | AH67: 1 a 30 dias | AI67: =_xlfn.XLOOKUP(Tabela5[[#This Row],[UUID]],Planilha2!$A:$A,Planilha2!B:B,"") -> 1 | AJ67: =_xlfn.XLOOKUP(Tabela5[[#This Row],[UUID]],Planilha2!$A:$A,Planilha2!C:C,"") -> 1 | AK67: =_xlfn.XLOOKUP(Tabela5[[#This Row],[UUID]],Planilha2!$A:$A,Planilha2!D:D,"") -> 11 | AL67: =_xlfn.XLOOKUP(Tabela5[[#This Row],[UUID]],Planilha2!$A:$A,Planilha2!E:E,"") -> 0 | AM67: =_xlfn.XLOOKUP(Tabela5[[#This Row],[UUID]],Planilha2!$A:$A,Planilha2!F:F,"") -> 1 | AN67: =_xlfn.XLOOKUP(Tabela5[[#This Row],[UUID]],Planilha2!$A:$A,Planilha2!G:G,"") -> 0 | AO67: =_xlfn.XLOOKUP(Tabela5[[#This Row],[UUID]],Planilha2!$A:$A,Planilha2!H:H,"") -> 0 | AP67: =_xlfn.XLOOKUP(Tabela5[[#This Row],[UUID]],Planilha2!$A:$A,Planilha2!I:I,"") -> 0 | AQ67: =_xlfn.XLOOKUP(Tabela5[[#This Row],[UUID]],Planilha2!$A:$A,Planilha2!J:J,"") -> 0 | AR67: =_xlfn.XLOOKUP(Tabela5[[#This Row],[UUID]],Planilha2!$A:$A,Planilha2!K:K,"") -> 0 | AS67: =_xlfn.XLOOKUP(Tabela5[[#This Row],[UUID]],Planilha2!$A:$A,Planilha2!L:L,"") -> 0 | AT67: =_xlfn.XLOOKUP(Tabela5[[#This Row],[UUID]],Planilha2!$A:$A,Planilha2!M:M,"") -> 1 | AU67: =_xlfn.XLOOKUP(Tabela5[[#This Row],[UUID]],Planilha2!$A:$A,Planilha2!N:N,"") -> 1 | AV67: =_xlfn.XLOOKUP(Tabela5[[#This Row],[UUID]],Planilha2!$A:$A,Planilha2!O:O,"") -> 1
A68: COB-242806 | B68: Faturado | C68: 10015962804 | D68: 2201298190 | E68: SUZANE MENDES DE OLIVEIRA | F68: RUA SEM NOME, RUA 57 S/N Q. 78, L. 07, APART - 102 JARDIM CEU AZUL Valparaíso de Goiás GO 00000-000 | G68: ADE-15866-J0S3Y1 | H68: 46082 | I68: 202603 | J68: 167.17875 | L68: 167.18 | N68: 90520093 | O68: 46101 | P68: 46111 | R68: 15 | S68: 2 - CPF | T68: Em aberto - Vencido | U68: Em aberto - Vencido | V68: DIKLM4R | Y68: 6 | Z68: Em aberto - Vencido | AA68: ASSOCIAÇÃO GO-L1 | AB68: 35.686.965/0001-64 - ALEXANDRIA TECH | AC68: Estimado | AE68: 1 a 30 dias | AF68: 4dd779d7-27fe-41e3-af86-3b5c66534f27 | AG68: 46107 | AH68: 1 a 30 dias | AI68: =_xlfn.XLOOKUP(Tabela5[[#This Row],[UUID]],Planilha2!$A:$A,Planilha2!B:B,"") -> 1 | AJ68: =_xlfn.XLOOKUP(Tabela5[[#This Row],[UUID]],Planilha2!$A:$A,Planilha2!C:C,"") -> 1 | AK68: =_xlfn.XLOOKUP(Tabela5[[#This Row],[UUID]],Planilha2!$A:$A,Planilha2!D:D,"") -> 4 | AL68: =_xlfn.XLOOKUP(Tabela5[[#This Row],[UUID]],Planilha2!$A:$A,Planilha2!E:E,"") -> 0 | AM68: =_xlfn.XLOOKUP(Tabela5[[#This Row],[UUID]],Planilha2!$A:$A,Planilha2!F:F,"") -> 1 | AN68: =_xlfn.XLOOKUP(Tabela5[[#This Row],[UUID]],Planilha2!$A:$A,Planilha2!G:G,"") -> 1 | AO68: =_xlfn.XLOOKUP(Tabela5[[#This Row],[UUID]],Planilha2!$A:$A,Planilha2!H:H,"") -> 1 | AP68: =_xlfn.XLOOKUP(Tabela5[[#This Row],[UUID]],Planilha2!$A:$A,Planilha2!I:I,"") -> 1 | AQ68: =_xlfn.XLOOKUP(Tabela5[[#This Row],[UUID]],Planilha2!$A:$A,Planilha2!J:J,"") -> 0 | AR68: =_xlfn.XLOOKUP(Tabela5[[#This Row],[UUID]],Planilha2!$A:$A,Planilha2!K:K,"") -> 0 | AS68: =_xlfn.XLOOKUP(Tabela5[[#This Row],[UUID]],Planilha2!$A:$A,Planilha2!L:L,"") -> 0 | AT68: =_xlfn.XLOOKUP(Tabela5[[#This Row],[UUID]],Planilha2!$A:$A,Planilha2!M:M,"") -> 0 | AU68: =_xlfn.XLOOKUP(Tabela5[[#This Row],[UUID]],Planilha2!$A:$A,Planilha2!N:N,"") -> 1 | AV68: =_xlfn.XLOOKUP(Tabela5[[#This Row],[UUID]],Planilha2!$A:$A,Planilha2!O:O,"") -> 1
A69: COB-242805 | B69: Faturado | C69: 610139769 | D69: 62294261100 | E69: MARIA ROSA DE OLIVEIRA | F69: RUA CIRCULAR S/N Q. 09, L. 01, LAGOA DOS SANTOS Formosa GO 73800-000 | G69: ADE-15858-Z9M8S7 | H69: 46082 | I69: 202603 | J69: 258.03663 | L69: 258.04 | N69: 90520411 | O69: 46101 | P69: 46111 | R69: 15 | S69: 2 - CPF | T69: Em aberto - Vencido | U69: Em aberto - Vencido | V69: 8VML93Z | W69: 6 | X69: false | Y69: 6 | Z69: Em aberto - Vencido | AA69: ASSOCIAÇÃO GO-L1 | AB69: 35.686.965/0001-64 - ALEXANDRIA TECH | AC69: Estimado | AE69: 1 a 30 dias | AF69: 60841d7e-dd46-42ff-9c35-86fb437366e1 | AG69: 46117 | AH69: 1 a 30 dias | AI69: =_xlfn.XLOOKUP(Tabela5[[#This Row],[UUID]],Planilha2!$A:$A,Planilha2!B:B,"") -> 1 | AJ69: =_xlfn.XLOOKUP(Tabela5[[#This Row],[UUID]],Planilha2!$A:$A,Planilha2!C:C,"") -> 1 | AK69: =_xlfn.XLOOKUP(Tabela5[[#This Row],[UUID]],Planilha2!$A:$A,Planilha2!D:D,"") -> 1 | AL69: =_xlfn.XLOOKUP(Tabela5[[#This Row],[UUID]],Planilha2!$A:$A,Planilha2!E:E,"") -> 0 | AM69: =_xlfn.XLOOKUP(Tabela5[[#This Row],[UUID]],Planilha2!$A:$A,Planilha2!F:F,"") -> 1 | AN69: =_xlfn.XLOOKUP(Tabela5[[#This Row],[UUID]],Planilha2!$A:$A,Planilha2!G:G,"") -> 0 | AO69: =_xlfn.XLOOKUP(Tabela5[[#This Row],[UUID]],Planilha2!$A:$A,Planilha2!H:H,"") -> 0 | AP69: =_xlfn.XLOOKUP(Tabela5[[#This Row],[UUID]],Planilha2!$A:$A,Planilha2!I:I,"") -> 0 | AQ69: =_xlfn.XLOOKUP(Tabela5[[#This Row],[UUID]],Planilha2!$A:$A,Planilha2!J:J,"") -> 0 | AR69: =_xlfn.XLOOKUP(Tabela5[[#This Row],[UUID]],Planilha2!$A:$A,Planilha2!K:K,"") -> 0 | AS69: =_xlfn.XLOOKUP(Tabela5[[#This Row],[UUID]],Planilha2!$A:$A,Planilha2!L:L,"") -> 0 | AT69: =_xlfn.XLOOKUP(Tabela5[[#This Row],[UUID]],Planilha2!$A:$A,Planilha2!M:M,"") -> 1 | AU69: =_xlfn.XLOOKUP(Tabela5[[#This Row],[UUID]],Planilha2!$A:$A,Planilha2!N:N,"") -> 1 | AV69: =_xlfn.XLOOKUP(Tabela5[[#This Row],[UUID]],Planilha2!$A:$A,Planilha2!O:O,"") -> 1
A70: COB-242804 | B70: Faturado | C70: 10028793739 | D70: 92727662149 | E70: ELVIRENE PEREIRA DOS SANTOS | F70: RUA PSR-1, Q. 4, L. 5, S/N GOIANIA S/N Residencial Portal Santa Rita Goiânia GO 74395067 | G70: ADE-15857-P4L3H3 | H70: 46082 | I70: 202603 | J70: 282.06159 | L70: 282.06 | N70: 90520136 | O70: 46101 | P70: 46111 | R70: 15 | S70: 2 - CPF | T70: Em aberto - Vencido | U70: Em aberto - Vencido | V70: VQR6RFJ | W70: 6 | X70: true | Y70: 6 | Z70: Em aberto - Vencido | AA70: ASSOCIAÇÃO GO-L1 | AB70: 35.686.965/0001-64 - ALEXANDRIA TECH | AC70: Estimado | AE70: 1 a 30 dias | AF70: d03c2e5b-3af5-45b2-800f-781e423b6e1a | AG70: 46112 | AH70: 1 a 30 dias | AI70: =_xlfn.XLOOKUP(Tabela5[[#This Row],[UUID]],Planilha2!$A:$A,Planilha2!B:B,"") -> 1 | AJ70: =_xlfn.XLOOKUP(Tabela5[[#This Row],[UUID]],Planilha2!$A:$A,Planilha2!C:C,"") -> 1 | AK70: =_xlfn.XLOOKUP(Tabela5[[#This Row],[UUID]],Planilha2!$A:$A,Planilha2!D:D,"") -> 1 | AL70: =_xlfn.XLOOKUP(Tabela5[[#This Row],[UUID]],Planilha2!$A:$A,Planilha2!E:E,"") -> 0 | AM70: =_xlfn.XLOOKUP(Tabela5[[#This Row],[UUID]],Planilha2!$A:$A,Planilha2!F:F,"") -> 1 | AN70: =_xlfn.XLOOKUP(Tabela5[[#This Row],[UUID]],Planilha2!$A:$A,Planilha2!G:G,"") -> 1 | AO70: =_xlfn.XLOOKUP(Tabela5[[#This Row],[UUID]],Planilha2!$A:$A,Planilha2!H:H,"") -> 1 | AP70: =_xlfn.XLOOKUP(Tabela5[[#This Row],[UUID]],Planilha2!$A:$A,Planilha2!I:I,"") -> 0 | AQ70: =_xlfn.XLOOKUP(Tabela5[[#This Row],[UUID]],Planilha2!$A:$A,Planilha2!J:J,"") -> 0 | AR70: =_xlfn.XLOOKUP(Tabela5[[#This Row],[UUID]],Planilha2!$A:$A,Planilha2!K:K,"") -> 0 | AS70: =_xlfn.XLOOKUP(Tabela5[[#This Row],[UUID]],Planilha2!$A:$A,Planilha2!L:L,"") -> 0 | AT70: =_xlfn.XLOOKUP(Tabela5[[#This Row],[UUID]],Planilha2!$A:$A,Planilha2!M:M,"") -> 1 | AU70: =_xlfn.XLOOKUP(Tabela5[[#This Row],[UUID]],Planilha2!$A:$A,Planilha2!N:N,"") -> 1 | AV70: =_xlfn.XLOOKUP(Tabela5[[#This Row],[UUID]],Planilha2!$A:$A,Planilha2!O:O,"") -> 1
A71: COB-242796 | B71: Faturado | C71: 850009686 | D71: 5089490171 | E71: ANNA CARLA DOS SANTOS LEMOS | F71: RUA FADUA FARA S/N Q. 22, L. 10 Setor Central Professor Jamil GO 75645000 | G71: ADE-15836-C1P2T6 | H71: 46082 | I71: 202603 | J71: 1778.6991 | L71: 1778.7 | N71: 90520499 | O71: 46101 | P71: 46111 | R71: 15 | S71: 2 - CPF | T71: Em aberto - Vencido | U71: Em aberto - Vencido | V71: 3ZA4R8C | W71: 6 | X71: false | Y71: 6 | Z71: Em aberto - Vencido | AA71: ASSOCIAÇÃO GO-L1 | AB71: 35.686.965/0001-64 - ALEXANDRIA TECH | AC71: Estimado | AE71: 1 a 30 dias | AF71: 45910891-790f-43af-8a88-1b04f34be3fa | AG71: 46113 | AH71: 1 a 30 dias | AI71: =_xlfn.XLOOKUP(Tabela5[[#This Row],[UUID]],Planilha2!$A:$A,Planilha2!B:B,"") -> 1 | AJ71: =_xlfn.XLOOKUP(Tabela5[[#This Row],[UUID]],Planilha2!$A:$A,Planilha2!C:C,"") -> 1 | AK71: =_xlfn.XLOOKUP(Tabela5[[#This Row],[UUID]],Planilha2!$A:$A,Planilha2!D:D,"") -> 1 | AL71: =_xlfn.XLOOKUP(Tabela5[[#This Row],[UUID]],Planilha2!$A:$A,Planilha2!E:E,"") -> 0 | AM71: =_xlfn.XLOOKUP(Tabela5[[#This Row],[UUID]],Planilha2!$A:$A,Planilha2!F:F,"") -> 1 | AN71: =_xlfn.XLOOKUP(Tabela5[[#This Row],[UUID]],Planilha2!$A:$A,Planilha2!G:G,"") -> 1 | AO71: =_xlfn.XLOOKUP(Tabela5[[#This Row],[UUID]],Planilha2!$A:$A,Planilha2!H:H,"") -> 1 | AP71: =_xlfn.XLOOKUP(Tabela5[[#This Row],[UUID]],Planilha2!$A:$A,Planilha2!I:I,"") -> 0 | AQ71: =_xlfn.XLOOKUP(Tabela5[[#This Row],[UUID]],Planilha2!$A:$A,Planilha2!J:J,"") -> 0 | AR71: =_xlfn.XLOOKUP(Tabela5[[#This Row],[UUID]],Planilha2!$A:$A,Planilha2!K:K,"") -> 0 | AS71: =_xlfn.XLOOKUP(Tabela5[[#This Row],[UUID]],Planilha2!$A:$A,Planilha2!L:L,"") -> 0 | AT71: =_xlfn.XLOOKUP(Tabela5[[#This Row],[UUID]],Planilha2!$A:$A,Planilha2!M:M,"") -> 0 | AU71: =_xlfn.XLOOKUP(Tabela5[[#This Row],[UUID]],Planilha2!$A:$A,Planilha2!N:N,"") -> 1 | AV71: =_xlfn.XLOOKUP(Tabela5[[#This Row],[UUID]],Planilha2!$A:$A,Planilha2!O:O,"") -> 1
A72: COB-242751 | B72: Faturado | C72: 12299900 | D72: 51807130134 | E72: KESYA MATIAS ALVES PEREIRA | F72: AVENIDA PRES VARGAS S/N Q. 34, L. 5 Goiânia Park Sul Aparecida de Goiânia GO 74945300 | G72: ADE-15633-J5H6X4 | H72: 46082 | I72: 202603 | J72: 344.17845 | L72: 344.18 | N72: 90520453 | O72: 46101 | P72: 46111 | R72: 15 | S72: 2 - CPF | T72: Em aberto - Vencido | U72: Em aberto - Vencido | V72: NZP1EK2 | W72: 6 | X72: false | Y72: 6 | Z72: Em aberto - Vencido | AA72: ASSOCIAÇÃO GO-L1 | AB72: 35.686.965/0001-64 - ALEXANDRIA TECH | AC72: Estimado | AE72: 1 a 30 dias | AF72: 0e39997d-8999-415a-8708-c84174899a47 | AG72: 46115 | AH72: 1 a 30 dias | AI72: =_xlfn.XLOOKUP(Tabela5[[#This Row],[UUID]],Planilha2!$A:$A,Planilha2!B:B,"") -> 1 | AJ72: =_xlfn.XLOOKUP(Tabela5[[#This Row],[UUID]],Planilha2!$A:$A,Planilha2!C:C,"") -> 1 | AK72: =_xlfn.XLOOKUP(Tabela5[[#This Row],[UUID]],Planilha2!$A:$A,Planilha2!D:D,"") -> 1 | AL72: =_xlfn.XLOOKUP(Tabela5[[#This Row],[UUID]],Planilha2!$A:$A,Planilha2!E:E,"") -> 0 | AM72: =_xlfn.XLOOKUP(Tabela5[[#This Row],[UUID]],Planilha2!$A:$A,Planilha2!F:F,"") -> 1 | AN72: =_xlfn.XLOOKUP(Tabela5[[#This Row],[UUID]],Planilha2!$A:$A,Planilha2!G:G,"") -> 1 | AO72: =_xlfn.XLOOKUP(Tabela5[[#This Row],[UUID]],Planilha2!$A:$A,Planilha2!H:H,"") -> 0 | AP72: =_xlfn.XLOOKUP(Tabela5[[#This Row],[UUID]],Planilha2!$A:$A,Planilha2!I:I,"") -> 0 | AQ72: =_xlfn.XLOOKUP(Tabela5[[#This Row],[UUID]],Planilha2!$A:$A,Planilha2!J:J,"") -> 0 | AR72: =_xlfn.XLOOKUP(Tabela5[[#This Row],[UUID]],Planilha2!$A:$A,Planilha2!K:K,"") -> 0 | AS72: =_xlfn.XLOOKUP(Tabela5[[#This Row],[UUID]],Planilha2!$A:$A,Planilha2!L:L,"") -> 0 | AT72: =_xlfn.XLOOKUP(Tabela5[[#This Row],[UUID]],Planilha2!$A:$A,Planilha2!M:M,"") -> 0 | AU72: =_xlfn.XLOOKUP(Tabela5[[#This Row],[UUID]],Planilha2!$A:$A,Planilha2!N:N,"") -> 1 | AV72: =_xlfn.XLOOKUP(Tabela5[[#This Row],[UUID]],Planilha2!$A:$A,Planilha2!O:O,"") -> 1
A73: COB-242750 | B73: Faturado | C73: 21057620 | D73: 75565269172 | E73: DEBORA CRISTINA SILVA MAIA | F73: RUA DEOCLECIANO MOREIRA ALVES S/N Q. 3, L. 19 SETOR RESIDENCIAL PEDRO LUDOVICO Anápolis GO 75000-000 | G73: ADE-15630-R3K1R3 | H73: 46082 | I73: 202603 | J73: 322.33702 | K73: 8.81 | L73: 331.15 | N73: 90520270 | O73: 46101 | P73: 46111 | R73: 15 | S73: 2 - CPF | T73: Em aberto - Vencido | U73: Em aberto - Vencido | V73: T5YQ6FC | W73: 6 | X73: false | Y73: 6 | Z73: Em aberto - Vencido | AA73: ASSOCIAÇÃO GO-L1 | AB73: 35.686.965/0001-64 - ALEXANDRIA TECH | AC73: Estimado | AE73: 1 a 30 dias | AF73: f2169ae3-52f8-45cf-8ff2-b26a09d8a0af | AG73: 46117 | AH73: 1 a 30 dias | AI73: =_xlfn.XLOOKUP(Tabela5[[#This Row],[UUID]],Planilha2!$A:$A,Planilha2!B:B,"") -> 1 | AJ73: =_xlfn.XLOOKUP(Tabela5[[#This Row],[UUID]],Planilha2!$A:$A,Planilha2!C:C,"") -> 1 | AK73: =_xlfn.XLOOKUP(Tabela5[[#This Row],[UUID]],Planilha2!$A:$A,Planilha2!D:D,"") -> 1 | AL73: =_xlfn.XLOOKUP(Tabela5[[#This Row],[UUID]],Planilha2!$A:$A,Planilha2!E:E,"") -> 0 | AM73: =_xlfn.XLOOKUP(Tabela5[[#This Row],[UUID]],Planilha2!$A:$A,Planilha2!F:F,"") -> 1 | AN73: =_xlfn.XLOOKUP(Tabela5[[#This Row],[UUID]],Planilha2!$A:$A,Planilha2!G:G,"") -> 0 | AO73: =_xlfn.XLOOKUP(Tabela5[[#This Row],[UUID]],Planilha2!$A:$A,Planilha2!H:H,"") -> 0 | AP73: =_xlfn.XLOOKUP(Tabela5[[#This Row],[UUID]],Planilha2!$A:$A,Planilha2!I:I,"") -> 0 | AQ73: =_xlfn.XLOOKUP(Tabela5[[#This Row],[UUID]],Planilha2!$A:$A,Planilha2!J:J,"") -> 0 | AR73: =_xlfn.XLOOKUP(Tabela5[[#This Row],[UUID]],Planilha2!$A:$A,Planilha2!K:K,"") -> 0 | AS73: =_xlfn.XLOOKUP(Tabela5[[#This Row],[UUID]],Planilha2!$A:$A,Planilha2!L:L,"") -> 0 | AT73: =_xlfn.XLOOKUP(Tabela5[[#This Row],[UUID]],Planilha2!$A:$A,Planilha2!M:M,"") -> 1 | AU73: =_xlfn.XLOOKUP(Tabela5[[#This Row],[UUID]],Planilha2!$A:$A,Planilha2!N:N,"") -> 1 | AV73: =_xlfn.XLOOKUP(Tabela5[[#This Row],[UUID]],Planilha2!$A:$A,Planilha2!O:O,"") -> 1
A74: COB-242749 | B74: Faturado | C74: 10033194708 | D74: 78820308134 | E74: ELSON GOMES DA FONSECA | F74: RUA OTACILIA DE MORAES NERES, Q. 23, L. 06, S/N S/N Q. 23, L. 06, PARQUE SAO PEDRO Iaciara GO 73920000 | G74: ADE-15625-D3R3G4 | H74: 46082 | I74: 202603 | J74: 151.98274 | L74: 151.98 | N74: 90520496 | O74: 46101 | P74: 46111 | R74: 15 | S74: 2 - CPF | T74: Em aberto - Vencido | U74: Em aberto - Vencido | V74: HCH3PZD | W74: 6 | X74: false | Y74: 6 | Z74: Em aberto - Vencido | AA74: ASSOCIAÇÃO GO-L1 | AB74: 35.686.965/0001-64 - ALEXANDRIA TECH | AC74: Estimado | AE74: 1 a 30 dias | AF74: 3149e720-01b0-43d5-849d-086d6774f7c3 | AG74: 46106 | AH74: 1 a 30 dias | AI74: =_xlfn.XLOOKUP(Tabela5[[#This Row],[UUID]],Planilha2!$A:$A,Planilha2!B:B,"") -> 1 | AJ74: =_xlfn.XLOOKUP(Tabela5[[#This Row],[UUID]],Planilha2!$A:$A,Planilha2!C:C,"") -> 2 | AK74: =_xlfn.XLOOKUP(Tabela5[[#This Row],[UUID]],Planilha2!$A:$A,Planilha2!D:D,"") -> 5 | AL74: =_xlfn.XLOOKUP(Tabela5[[#This Row],[UUID]],Planilha2!$A:$A,Planilha2!E:E,"") -> 0 | AM74: =_xlfn.XLOOKUP(Tabela5[[#This Row],[UUID]],Planilha2!$A:$A,Planilha2!F:F,"") -> 1 | AN74: =_xlfn.XLOOKUP(Tabela5[[#This Row],[UUID]],Planilha2!$A:$A,Planilha2!G:G,"") -> 1 | AO74: =_xlfn.XLOOKUP(Tabela5[[#This Row],[UUID]],Planilha2!$A:$A,Planilha2!H:H,"") -> 1 | AP74: =_xlfn.XLOOKUP(Tabela5[[#This Row],[UUID]],Planilha2!$A:$A,Planilha2!I:I,"") -> 1 | AQ74: =_xlfn.XLOOKUP(Tabela5[[#This Row],[UUID]],Planilha2!$A:$A,Planilha2!J:J,"") -> 1 | AR74: =_xlfn.XLOOKUP(Tabela5[[#This Row],[UUID]],Planilha2!$A:$A,Planilha2!K:K,"") -> 0 | AS74: =_xlfn.XLOOKUP(Tabela5[[#This Row],[UUID]],Planilha2!$A:$A,Planilha2!L:L,"") -> 0 | AT74: =_xlfn.XLOOKUP(Tabela5[[#This Row],[UUID]],Planilha2!$A:$A,Planilha2!M:M,"") -> 0 | AU74: =_xlfn.XLOOKUP(Tabela5[[#This Row],[UUID]],Planilha2!$A:$A,Planilha2!N:N,"") -> 1 | AV74: =_xlfn.XLOOKUP(Tabela5[[#This Row],[UUID]],Planilha2!$A:$A,Planilha2!O:O,"") -> 1
A75: COB-242734 | B75: Faturado | C75: 10033917661 | D75: 907320147 | E75: WANDERSON BRAGA | F75: AVENIDA DA LUZ S/N Q. 5, L. 2, SALA - 1 Jardim Tropical Aparecida de Goiânia GO 74946550 | G75: ADE-15577-L5B6P8 | H75: 46082 | I75: 202603 | J75: 912.14916 | L75: 912.15 | N75: 90520369 | O75: 46101 | P75: 46111 | R75: 15 | S75: 2 - CPF | T75: Em aberto - Vencido | U75: Em aberto - Vencido | V75: WAELT7M | W75: 6 | X75: false | Y75: 6 | Z75: Em aberto - Vencido | AA75: ASSOCIAÇÃO GO-L1 | AB75: 35.686.965/0001-64 - ALEXANDRIA TECH | AC75: Estimado | AE75: 1 a 30 dias | AF75: ee65cc3b-d2e2-4ca5-ae70-2a6ee9341bf3 | AG75: 46111 | AH75: 1 a 30 dias | AI75: =_xlfn.XLOOKUP(Tabela5[[#This Row],[UUID]],Planilha2!$A:$A,Planilha2!B:B,"") -> 1 | AJ75: =_xlfn.XLOOKUP(Tabela5[[#This Row],[UUID]],Planilha2!$A:$A,Planilha2!C:C,"") -> 1 | AK75: =_xlfn.XLOOKUP(Tabela5[[#This Row],[UUID]],Planilha2!$A:$A,Planilha2!D:D,"") -> 1 | AL75: =_xlfn.XLOOKUP(Tabela5[[#This Row],[UUID]],Planilha2!$A:$A,Planilha2!E:E,"") -> 0 | AM75: =_xlfn.XLOOKUP(Tabela5[[#This Row],[UUID]],Planilha2!$A:$A,Planilha2!F:F,"") -> 1 | AN75: =_xlfn.XLOOKUP(Tabela5[[#This Row],[UUID]],Planilha2!$A:$A,Planilha2!G:G,"") -> 1 | AO75: =_xlfn.XLOOKUP(Tabela5[[#This Row],[UUID]],Planilha2!$A:$A,Planilha2!H:H,"") -> 1 | AP75: =_xlfn.XLOOKUP(Tabela5[[#This Row],[UUID]],Planilha2!$A:$A,Planilha2!I:I,"") -> 0 | AQ75: =_xlfn.XLOOKUP(Tabela5[[#This Row],[UUID]],Planilha2!$A:$A,Planilha2!J:J,"") -> 0 | AR75: =_xlfn.XLOOKUP(Tabela5[[#This Row],[UUID]],Planilha2!$A:$A,Planilha2!K:K,"") -> 0 | AS75: =_xlfn.XLOOKUP(Tabela5[[#This Row],[UUID]],Planilha2!$A:$A,Planilha2!L:L,"") -> 0 | AT75: =_xlfn.XLOOKUP(Tabela5[[#This Row],[UUID]],Planilha2!$A:$A,Planilha2!M:M,"") -> 1 | AU75: =_xlfn.XLOOKUP(Tabela5[[#This Row],[UUID]],Planilha2!$A:$A,Planilha2!N:N,"") -> 1 | AV75: =_xlfn.XLOOKUP(Tabela5[[#This Row],[UUID]],Planilha2!$A:$A,Planilha2!O:O,"") -> 1
A76: COB-176523 | B76: Faturado | C76: 160706555 | D76: 3105774700 | E76: LUCIANA GRASSI ALVES | F76: AV CONCEICAO DA BARRA 2266 T.A TREVISO AP 102 SHELL / LINHARES - ES CEP: 29901-592 | G76: ADE-12152-G3S9X1 | H76: 45839 | I76: 202507 | J76: 233.07117 | L76: 233.07 | N76: 90427203 | O76: 45995 | P76: 46006 | R76: 120 | S76: 2 - CPF | T76: Em aberto - Vencido | U76: Em aberto - Vencido | V76: GL9KVNS | W76: 6 | X76: false | Y76: 6 | Z76: Em aberto - Vencido | AA76: ASSOCIAÇÃO ES-L1 | AB76: 35.686.965/0001-64 - ALEXANDRIA TECH | AE76: 61 a 120 dias | AF76: e35a9f13-ff65-4098-bad7-e0afdcb3dfe8 | AG76: 45917 | AH76: Maior que 90 | AI76: =_xlfn.XLOOKUP(Tabela5[[#This Row],[UUID]],Planilha2!$A:$A,Planilha2!B:B,"") -> 0 | AJ76: =_xlfn.XLOOKUP(Tabela5[[#This Row],[UUID]],Planilha2!$A:$A,Planilha2!C:C,"") -> 0 | AK76: =_xlfn.XLOOKUP(Tabela5[[#This Row],[UUID]],Planilha2!$A:$A,Planilha2!D:D,"") -> 0 | AL76: =_xlfn.XLOOKUP(Tabela5[[#This Row],[UUID]],Planilha2!$A:$A,Planilha2!E:E,"") -> 13 | AM76: =_xlfn.XLOOKUP(Tabela5[[#This Row],[UUID]],Planilha2!$A:$A,Planilha2!F:F,"") -> 0 | AN76: =_xlfn.XLOOKUP(Tabela5[[#This Row],[UUID]],Planilha2!$A:$A,Planilha2!G:G,"") -> 0 | AO76: =_xlfn.XLOOKUP(Tabela5[[#This Row],[UUID]],Planilha2!$A:$A,Planilha2!H:H,"") -> 0 | AP76: =_xlfn.XLOOKUP(Tabela5[[#This Row],[UUID]],Planilha2!$A:$A,Planilha2!I:I,"") -> 0 | AQ76: =_xlfn.XLOOKUP(Tabela5[[#This Row],[UUID]],Planilha2!$A:$A,Planilha2!J:J,"") -> 0 | AR76: =_xlfn.XLOOKUP(Tabela5[[#This Row],[UUID]],Planilha2!$A:$A,Planilha2!K:K,"") -> 0 | AS76: =_xlfn.XLOOKUP(Tabela5[[#This Row],[UUID]],Planilha2!$A:$A,Planilha2!L:L,"") -> 0 | AT76: =_xlfn.XLOOKUP(Tabela5[[#This Row],[UUID]],Planilha2!$A:$A,Planilha2!M:M,"") -> 0 | AU76: =_xlfn.XLOOKUP(Tabela5[[#This Row],[UUID]],Planilha2!$A:$A,Planilha2!N:N,"") -> 0 | AV76: =_xlfn.XLOOKUP(Tabela5[[#This Row],[UUID]],Planilha2!$A:$A,Planilha2!O:O,"") -> 0
A77: COB-242733 | B77: Faturado | C77: 10018971499 | D77: 93021240100 | E77: GISLENE MARIA DE OLIVEIRA DOS SANTOS LIMA | F77: Avenida Pedro Paulo de Souza S/N Q. 0, L. 0, S/N, APART - 3, BLOCO - 6, RES. CLUB CHEVERNY TOWER F3 Goiânia GO 74663-520 | G77: ADE-15576-B6C7P2 | H77: 46082 | I77: 202603 | J77: 165.34386 | L77: 165.34 | N77: 90519909 | O77: 46101 | P77: 46111 | R77: 15 | S77: 2 - CPF | T77: Em aberto - Vencido | U77: Em aberto - Vencido | V77: W32Q9FW | W77: 6 | X77: false | Y77: 6 | Z77: Em aberto - Vencido | AA77: ASSOCIAÇÃO GO-L1 | AB77: 35.686.965/0001-64 - ALEXANDRIA TECH | AC77: Estimado | AE77: 1 a 30 dias | AF77: 75d158fc-0cca-4b15-bbf7-4d53947b7d71 | AG77: 46111 | AH77: 1 a 30 dias | AI77: =_xlfn.XLOOKUP(Tabela5[[#This Row],[UUID]],Planilha2!$A:$A,Planilha2!B:B,"") -> 1 | AJ77: =_xlfn.XLOOKUP(Tabela5[[#This Row],[UUID]],Planilha2!$A:$A,Planilha2!C:C,"") -> 1 | AK77: =_xlfn.XLOOKUP(Tabela5[[#This Row],[UUID]],Planilha2!$A:$A,Planilha2!D:D,"") -> 1 | AL77: =_xlfn.XLOOKUP(Tabela5[[#This Row],[UUID]],Planilha2!$A:$A,Planilha2!E:E,"") -> 0 | AM77: =_xlfn.XLOOKUP(Tabela5[[#This Row],[UUID]],Planilha2!$A:$A,Planilha2!F:F,"") -> 1 | AN77: =_xlfn.XLOOKUP(Tabela5[[#This Row],[UUID]],Planilha2!$A:$A,Planilha2!G:G,"") -> 1 | AO77: =_xlfn.XLOOKUP(Tabela5[[#This Row],[UUID]],Planilha2!$A:$A,Planilha2!H:H,"") -> 1 | AP77: =_xlfn.XLOOKUP(Tabela5[[#This Row],[UUID]],Planilha2!$A:$A,Planilha2!I:I,"") -> 0 | AQ77: =_xlfn.XLOOKUP(Tabela5[[#This Row],[UUID]],Planilha2!$A:$A,Planilha2!J:J,"") -> 0 | AR77: =_xlfn.XLOOKUP(Tabela5[[#This Row],[UUID]],Planilha2!$A:$A,Planilha2!K:K,"") -> 0 | AS77: =_xlfn.XLOOKUP(Tabela5[[#This Row],[UUID]],Planilha2!$A:$A,Planilha2!L:L,"") -> 0 | AT77: =_xlfn.XLOOKUP(Tabela5[[#This Row],[UUID]],Planilha2!$A:$A,Planilha2!M:M,"") -> 1 | AU77: =_xlfn.XLOOKUP(Tabela5[[#This Row],[UUID]],Planilha2!$A:$A,Planilha2!N:N,"") -> 1 | AV77: =_xlfn.XLOOKUP(Tabela5[[#This Row],[UUID]],Planilha2!$A:$A,Planilha2!O:O,"") -> 1
A78: COB-242730 | B78: Faturado | C78: 13558092 | D78: 5496076170 | E78: ABRAIM COSTA LINS DE SOUZA | F78: RUA X-25 S/N Q. 12, L. 25 - CASA 1 Jardim Olímpico Aparecida de Goiânia GO 74922330 | G78: ADE-15571-V2Q0L0 | H78: 46082 | I78: 202603 | J78: 364.92559 | L78: 364.93 | N78: 90520245 | O78: 46101 | P78: 46111 | R78: 15 | S78: 2 - CPF | T78: Em aberto - Vencido | U78: Em aberto - Vencido | V78: D3SCIWK | W78: 6 | X78: false | Y78: 6 | Z78: Em aberto - Vencido | AA78: ASSOCIAÇÃO GO-L1 | AB78: 35.686.965/0001-64 - ALEXANDRIA TECH | AC78: Estimado | AE78: 1 a 30 dias | AF78: fcbbdf56-ee5e-4f20-9102-081d764c48a3 | AG78: 46117 | AH78: 1 a 30 dias | AI78: =_xlfn.XLOOKUP(Tabela5[[#This Row],[UUID]],Planilha2!$A:$A,Planilha2!B:B,"") -> 1 | AJ78: =_xlfn.XLOOKUP(Tabela5[[#This Row],[UUID]],Planilha2!$A:$A,Planilha2!C:C,"") -> 1 | AK78: =_xlfn.XLOOKUP(Tabela5[[#This Row],[UUID]],Planilha2!$A:$A,Planilha2!D:D,"") -> 1 | AL78: =_xlfn.XLOOKUP(Tabela5[[#This Row],[UUID]],Planilha2!$A:$A,Planilha2!E:E,"") -> 0 | AM78: =_xlfn.XLOOKUP(Tabela5[[#This Row],[UUID]],Planilha2!$A:$A,Planilha2!F:F,"") -> 1 | AN78: =_xlfn.XLOOKUP(Tabela5[[#This Row],[UUID]],Planilha2!$A:$A,Planilha2!G:G,"") -> 0 | AO78: =_xlfn.XLOOKUP(Tabela5[[#This Row],[UUID]],Planilha2!$A:$A,Planilha2!H:H,"") -> 0 | AP78: =_xlfn.XLOOKUP(Tabela5[[#This Row],[UUID]],Planilha2!$A:$A,Planilha2!I:I,"") -> 0 | AQ78: =_xlfn.XLOOKUP(Tabela5[[#This Row],[UUID]],Planilha2!$A:$A,Planilha2!J:J,"") -> 0 | AR78: =_xlfn.XLOOKUP(Tabela5[[#This Row],[UUID]],Planilha2!$A:$A,Planilha2!K:K,"") -> 0 | AS78: =_xlfn.XLOOKUP(Tabela5[[#This Row],[UUID]],Planilha2!$A:$A,Planilha2!L:L,"") -> 0 | AT78: =_xlfn.XLOOKUP(Tabela5[[#This Row],[UUID]],Planilha2!$A:$A,Planilha2!M:M,"") -> 1 | AU78: =_xlfn.XLOOKUP(Tabela5[[#This Row],[UUID]],Planilha2!$A:$A,Planilha2!N:N,"") -> 1 | AV78: =_xlfn.XLOOKUP(Tabela5[[#This Row],[UUID]],Planilha2!$A:$A,Planilha2!O:O,"") -> 1
A79: COB-242729 | B79: Faturado | C79: 10031142816 | D79: 92074588100 | E79: ROSINEIDE NUNES DA COSTA | F79: AVENIDA BRASIL CENTRAL, Q. 50, L. 16, S/N, CASA - 2 S/N Q. 50, L. 16 CENTRO Mambaí GO 73970000 | G79: ADE-15570-G7K8M9 | H79: 46082 | I79: 202603 | J79: 159.49837 | K79: 4.36 | L79: 163.86 | N79: 90520052 | O79: 46101 | P79: 46111 | R79: 15 | S79: 2 - CPF | T79: Em aberto - Vencido | U79: Em aberto - Vencido | V79: AEIPQQH | W79: 6 | X79: false | Y79: 6 | Z79: Em aberto - Vencido | AA79: ASSOCIAÇÃO GO-L1 | AB79: 35.686.965/0001-64 - ALEXANDRIA TECH | AC79: Estimado | AE79: 1 a 30 dias | AF79: 022ba0c0-0e94-4111-ab5e-fcd2160f62f2 | AG79: 46111 | AH79: 1 a 30 dias | AI79: =_xlfn.XLOOKUP(Tabela5[[#This Row],[UUID]],Planilha2!$A:$A,Planilha2!B:B,"") -> 1 | AJ79: =_xlfn.XLOOKUP(Tabela5[[#This Row],[UUID]],Planilha2!$A:$A,Planilha2!C:C,"") -> 1 | AK79: =_xlfn.XLOOKUP(Tabela5[[#This Row],[UUID]],Planilha2!$A:$A,Planilha2!D:D,"") -> 1 | AL79: =_xlfn.XLOOKUP(Tabela5[[#This Row],[UUID]],Planilha2!$A:$A,Planilha2!E:E,"") -> 0 | AM79: =_xlfn.XLOOKUP(Tabela5[[#This Row],[UUID]],Planilha2!$A:$A,Planilha2!F:F,"") -> 1 | AN79: =_xlfn.XLOOKUP(Tabela5[[#This Row],[UUID]],Planilha2!$A:$A,Planilha2!G:G,"") -> 1 | AO79: =_xlfn.XLOOKUP(Tabela5[[#This Row],[UUID]],Planilha2!$A:$A,Planilha2!H:H,"") -> 1 | AP79: =_xlfn.XLOOKUP(Tabela5[[#This Row],[UUID]],Planilha2!$A:$A,Planilha2!I:I,"") -> 0 | AQ79: =_xlfn.XLOOKUP(Tabela5[[#This Row],[UUID]],Planilha2!$A:$A,Planilha2!J:J,"") -> 0 | AR79: =_xlfn.XLOOKUP(Tabela5[[#This Row],[UUID]],Planilha2!$A:$A,Planilha2!K:K,"") -> 0 | AS79: =_xlfn.XLOOKUP(Tabela5[[#This Row],[UUID]],Planilha2!$A:$A,Planilha2!L:L,"") -> 0 | AT79: =_xlfn.XLOOKUP(Tabela5[[#This Row],[UUID]],Planilha2!$A:$A,Planilha2!M:M,"") -> 1 | AU79: =_xlfn.XLOOKUP(Tabela5[[#This Row],[UUID]],Planilha2!$A:$A,Planilha2!N:N,"") -> 1 | AV79: =_xlfn.XLOOKUP(Tabela5[[#This Row],[UUID]],Planilha2!$A:$A,Planilha2!O:O,"") -> 1
A80: COB-242728 | B80: Faturado | C80: 10031557994 | D80: 5654374370 | E80: RAFAEL DOS SANTOS SOUZA | F80: Avenida Moinho dos Ventos S/N Q 00 L 00, APART - 103, BLOCO - 10, - RUA MDV 1 MOINHO DOS VENTOS Goiânia GO 74391-395 | G80: ADE-15569-C1B0S3 | H80: 46082 | I80: 202603 | J80: 343.21377 | L80: 343.21 | N80: 90520185 | O80: 46101 | P80: 46111 | R80: 15 | S80: 2 - CPF | T80: Em aberto - Vencido | U80: Em aberto - Vencido | V80: 1FYZZC1 | W80: 6 | X80: false | Y80: 6 | Z80: Em aberto - Vencido | AA80: ASSOCIAÇÃO GO-L1 | AB80: 35.686.965/0001-64 - ALEXANDRIA TECH | AC80: Estimado | AE80: 1 a 30 dias | AF80: 330a11f9-5d53-4e4a-b9dc-38581ae1e7f7 | AG80: 46117 | AH80: 1 a 30 dias | AI80: =_xlfn.XLOOKUP(Tabela5[[#This Row],[UUID]],Planilha2!$A:$A,Planilha2!B:B,"") -> 1 | AJ80: =_xlfn.XLOOKUP(Tabela5[[#This Row],[UUID]],Planilha2!$A:$A,Planilha2!C:C,"") -> 1 | AK80: =_xlfn.XLOOKUP(Tabela5[[#This Row],[UUID]],Planilha2!$A:$A,Planilha2!D:D,"") -> 11 | AL80: =_xlfn.XLOOKUP(Tabela5[[#This Row],[UUID]],Planilha2!$A:$A,Planilha2!E:E,"") -> 0 | AM80: =_xlfn.XLOOKUP(Tabela5[[#This Row],[UUID]],Planilha2!$A:$A,Planilha2!F:F,"") -> 1 | AN80: =_xlfn.XLOOKUP(Tabela5[[#This Row],[UUID]],Planilha2!$A:$A,Planilha2!G:G,"") -> 0 | AO80: =_xlfn.XLOOKUP(Tabela5[[#This Row],[UUID]],Planilha2!$A:$A,Planilha2!H:H,"") -> 0 | AP80: =_xlfn.XLOOKUP(Tabela5[[#This Row],[UUID]],Planilha2!$A:$A,Planilha2!I:I,"") -> 0 | AQ80: =_xlfn.XLOOKUP(Tabela5[[#This Row],[UUID]],Planilha2!$A:$A,Planilha2!J:J,"") -> 0 | AR80: =_xlfn.XLOOKUP(Tabela5[[#This Row],[UUID]],Planilha2!$A:$A,Planilha2!K:K,"") -> 0 | AS80: =_xlfn.XLOOKUP(Tabela5[[#This Row],[UUID]],Planilha2!$A:$A,Planilha2!L:L,"") -> 0 | AT80: =_xlfn.XLOOKUP(Tabela5[[#This Row],[UUID]],Planilha2!$A:$A,Planilha2!M:M,"") -> 1 | AU80: =_xlfn.XLOOKUP(Tabela5[[#This Row],[UUID]],Planilha2!$A:$A,Planilha2!N:N,"") -> 1 | AV80: =_xlfn.XLOOKUP(Tabela5[[#This Row],[UUID]],Planilha2!$A:$A,Planilha2!O:O,"") -> 1
A81: COB-242727 | B81: Faturado | C81: 20876579 | D81: 91105846172 | E81: PATRICIA GONCALVES MENDONCA | F81: RUA LUCIANA, Q. 53, L. 22, S/N, - CASA 1 ANAPOLIS S/N Q. 53, L. 22, CASA 01 JK Nova Capital Anápolis GO 75114725 | G81: ADE-15566-P9N7Q3 | H81: 46082 | I81: 202603 | J81: 164.02476 | L81: 164.02 | N81: 90520297 | O81: 46101 | P81: 46111 | R81: 15 | S81: 2 - CPF | T81: Em aberto - Vencido | U81: Em aberto - Vencido | V81: B0TSE37 | W81: 6 | X81: false | Y81: 6 | Z81: Em aberto - Vencido | AA81: ASSOCIAÇÃO GO-L1 | AB81: 35.686.965/0001-64 - ALEXANDRIA TECH | AC81: Estimado | AE81: 1 a 30 dias | AF81: 59efc0ef-0718-4094-8f3c-878e3e539eaf | AG81: 46115 | AH81: 1 a 30 dias | AI81: =_xlfn.XLOOKUP(Tabela5[[#This Row],[UUID]],Planilha2!$A:$A,Planilha2!B:B,"") -> 1 | AJ81: =_xlfn.XLOOKUP(Tabela5[[#This Row],[UUID]],Planilha2!$A:$A,Planilha2!C:C,"") -> 1 | AK81: =_xlfn.XLOOKUP(Tabela5[[#This Row],[UUID]],Planilha2!$A:$A,Planilha2!D:D,"") -> 1 | AL81: =_xlfn.XLOOKUP(Tabela5[[#This Row],[UUID]],Planilha2!$A:$A,Planilha2!E:E,"") -> 0 | AM81: =_xlfn.XLOOKUP(Tabela5[[#This Row],[UUID]],Planilha2!$A:$A,Planilha2!F:F,"") -> 1 | AN81: =_xlfn.XLOOKUP(Tabela5[[#This Row],[UUID]],Planilha2!$A:$A,Planilha2!G:G,"") -> 1 | AO81: =_xlfn.XLOOKUP(Tabela5[[#This Row],[UUID]],Planilha2!$A:$A,Planilha2!H:H,"") -> 0 | AP81: =_xlfn.XLOOKUP(Tabela5[[#This Row],[UUID]],Planilha2!$A:$A,Planilha2!I:I,"") -> 0 | AQ81: =_xlfn.XLOOKUP(Tabela5[[#This Row],[UUID]],Planilha2!$A:$A,Planilha2!J:J,"") -> 0 | AR81: =_xlfn.XLOOKUP(Tabela5[[#This Row],[UUID]],Planilha2!$A:$A,Planilha2!K:K,"") -> 0 | AS81: =_xlfn.XLOOKUP(Tabela5[[#This Row],[UUID]],Planilha2!$A:$A,Planilha2!L:L,"") -> 0 | AT81: =_xlfn.XLOOKUP(Tabela5[[#This Row],[UUID]],Planilha2!$A:$A,Planilha2!M:M,"") -> 0 | AU81: =_xlfn.XLOOKUP(Tabela5[[#This Row],[UUID]],Planilha2!$A:$A,Planilha2!N:N,"") -> 1 | AV81: =_xlfn.XLOOKUP(Tabela5[[#This Row],[UUID]],Planilha2!$A:$A,Planilha2!O:O,"") -> 1
A82: COB-242706 | B82: Faturado | C82: 4830120618 | D82: 4561969195 | E82: ALAN DAVID DE OLIVEIRA SILVA | F82: RUA 19 s/n Q. 67, L. 19 Setor 08 Águas Lindas de Goiás GO 72910001 | G82: ADE-15369-L6Z4R5 | H82: 46082 | I82: 202603 | J82: 146.97232 | L82: 146.97 | N82: 90520422 | O82: 46101 | P82: 46111 | R82: 15 | S82: 2 - CPF | T82: Em aberto - Vencido | U82: Em aberto - Vencido | V82: E5RMAF8 | W82: 6 | X82: false | Y82: 6 | Z82: Em aberto - Vencido | AA82: ASSOCIAÇÃO GO-L1 | AB82: 35.686.965/0001-64 - ALEXANDRIA TECH | AC82: Estimado | AE82: 1 a 30 dias | AF82: c35072fc-af9a-49ef-b08f-86befac11179 | AG82: 46111 | AH82: 1 a 30 dias | AI82: =_xlfn.XLOOKUP(Tabela5[[#This Row],[UUID]],Planilha2!$A:$A,Planilha2!B:B,"") -> 1 | AJ82: =_xlfn.XLOOKUP(Tabela5[[#This Row],[UUID]],Planilha2!$A:$A,Planilha2!C:C,"") -> 1 | AK82: =_xlfn.XLOOKUP(Tabela5[[#This Row],[UUID]],Planilha2!$A:$A,Planilha2!D:D,"") -> 1 | AL82: =_xlfn.XLOOKUP(Tabela5[[#This Row],[UUID]],Planilha2!$A:$A,Planilha2!E:E,"") -> 0 | AM82: =_xlfn.XLOOKUP(Tabela5[[#This Row],[UUID]],Planilha2!$A:$A,Planilha2!F:F,"") -> 1 | AN82: =_xlfn.XLOOKUP(Tabela5[[#This Row],[UUID]],Planilha2!$A:$A,Planilha2!G:G,"") -> 1 | AO82: =_xlfn.XLOOKUP(Tabela5[[#This Row],[UUID]],Planilha2!$A:$A,Planilha2!H:H,"") -> 1 | AP82: =_xlfn.XLOOKUP(Tabela5[[#This Row],[UUID]],Planilha2!$A:$A,Planilha2!I:I,"") -> 0 | AQ82: =_xlfn.XLOOKUP(Tabela5[[#This Row],[UUID]],Planilha2!$A:$A,Planilha2!J:J,"") -> 0 | AR82: =_xlfn.XLOOKUP(Tabela5[[#This Row],[UUID]],Planilha2!$A:$A,Planilha2!K:K,"") -> 0 | AS82: =_xlfn.XLOOKUP(Tabela5[[#This Row],[UUID]],Planilha2!$A:$A,Planilha2!L:L,"") -> 0 | AT82: =_xlfn.XLOOKUP(Tabela5[[#This Row],[UUID]],Planilha2!$A:$A,Planilha2!M:M,"") -> 1 | AU82: =_xlfn.XLOOKUP(Tabela5[[#This Row],[UUID]],Planilha2!$A:$A,Planilha2!N:N,"") -> 1 | AV82: =_xlfn.XLOOKUP(Tabela5[[#This Row],[UUID]],Planilha2!$A:$A,Planilha2!O:O,"") -> 1
A83: COB-242700 | B83: Faturado | C83: 2860309026 | D83: 6154792190 | E83: ROMARIO SOUZA DOS REIS | F83: RUA 14 SN Q. 23, L. 12, S/N, - RUA 13/14, - LOJA 01 JARDIM ORIENTE Valparaíso de Goiás GO 72870-000 | G83: ADE-15345-G8G5B1 | H83: 46082 | I83: 202603 | J83: 379.12178 | L83: 379.12 | N83: 90520229 | O83: 46101 | P83: 46111 | R83: 15 | S83: 2 - CPF | T83: Em aberto - Vencido | U83: Em aberto - Vencido | V83: J8LJ8GS | W83: 6 | X83: false | Y83: 6 | Z83: Em aberto - Vencido | AA83: ASSOCIAÇÃO GO-L1 | AB83: 35.686.965/0001-64 - ALEXANDRIA TECH | AC83: Estimado | AE83: 1 a 30 dias | AF83: a2df9785-5872-4bd3-bd3e-327f65ee6ff8 | AG83: 46111 | AH83: 1 a 30 dias | AI83: =_xlfn.XLOOKUP(Tabela5[[#This Row],[UUID]],Planilha2!$A:$A,Planilha2!B:B,"") -> 1 | AJ83: =_xlfn.XLOOKUP(Tabela5[[#This Row],[UUID]],Planilha2!$A:$A,Planilha2!C:C,"") -> 1 | AK83: =_xlfn.XLOOKUP(Tabela5[[#This Row],[UUID]],Planilha2!$A:$A,Planilha2!D:D,"") -> 8 | AL83: =_xlfn.XLOOKUP(Tabela5[[#This Row],[UUID]],Planilha2!$A:$A,Planilha2!E:E,"") -> 0 | AM83: =_xlfn.XLOOKUP(Tabela5[[#This Row],[UUID]],Planilha2!$A:$A,Planilha2!F:F,"") -> 1 | AN83: =_xlfn.XLOOKUP(Tabela5[[#This Row],[UUID]],Planilha2!$A:$A,Planilha2!G:G,"") -> 1 | AO83: =_xlfn.XLOOKUP(Tabela5[[#This Row],[UUID]],Planilha2!$A:$A,Planilha2!H:H,"") -> 1 | AP83: =_xlfn.XLOOKUP(Tabela5[[#This Row],[UUID]],Planilha2!$A:$A,Planilha2!I:I,"") -> 0 | AQ83: =_xlfn.XLOOKUP(Tabela5[[#This Row],[UUID]],Planilha2!$A:$A,Planilha2!J:J,"") -> 0 | AR83: =_xlfn.XLOOKUP(Tabela5[[#This Row],[UUID]],Planilha2!$A:$A,Planilha2!K:K,"") -> 0 | AS83: =_xlfn.XLOOKUP(Tabela5[[#This Row],[UUID]],Planilha2!$A:$A,Planilha2!L:L,"") -> 0 | AT83: =_xlfn.XLOOKUP(Tabela5[[#This Row],[UUID]],Planilha2!$A:$A,Planilha2!M:M,"") -> 1 | AU83: =_xlfn.XLOOKUP(Tabela5[[#This Row],[UUID]],Planilha2!$A:$A,Planilha2!N:N,"") -> 1 | AV83: =_xlfn.XLOOKUP(Tabela5[[#This Row],[UUID]],Planilha2!$A:$A,Planilha2!O:O,"") -> 1
A84: COB-242694 | B84: Faturado | C84: 10843735 | D84: 889977151 | E84: FERNANDO KRISTIAN FERREIRA BARBOSA | F84: RUA BLUMENAU S/N Q. 55, L. 7, | CASA 1 Jardim Novo Mundo Goiânia GO 74715080 | G84: ADE-15102-D5Z8P7 | H84: 46082 | I84: 202603 | J84: 286.42901 | L84: 286.43 | N84: 90520345 | O84: 46101 | P84: 46111 | R84: 15 | S84: 2 - CPF | T84: Em aberto - Vencido | U84: Em aberto - Vencido | V84: PVZ0JNS | W84: 6 | X84: false | Y84: 6 | Z84: Em aberto - Vencido | AA84: ASSOCIAÇÃO GO-L1 | AB84: 35.686.965/0001-64 - ALEXANDRIA TECH | AC84: Estimado | AE84: 1 a 30 dias | AF84: 425588d5-dbd1-47bd-8ab4-c0a813372cfb | AG84: 46111 | AH84: 1 a 30 dias | AI84: =_xlfn.XLOOKUP(Tabela5[[#This Row],[UUID]],Planilha2!$A:$A,Planilha2!B:B,"") -> 1 | AJ84: =_xlfn.XLOOKUP(Tabela5[[#This Row],[UUID]],Planilha2!$A:$A,Planilha2!C:C,"") -> 1 | AK84: =_xlfn.XLOOKUP(Tabela5[[#This Row],[UUID]],Planilha2!$A:$A,Planilha2!D:D,"") -> 8 | AL84: =_xlfn.XLOOKUP(Tabela5[[#This Row],[UUID]],Planilha2!$A:$A,Planilha2!E:E,"") -> 0 | AM84: =_xlfn.XLOOKUP(Tabela5[[#This Row],[UUID]],Planilha2!$A:$A,Planilha2!F:F,"") -> 1 | AN84: =_xlfn.XLOOKUP(Tabela5[[#This Row],[UUID]],Planilha2!$A:$A,Planilha2!G:G,"") -> 1 | AO84: =_xlfn.XLOOKUP(Tabela5[[#This Row],[UUID]],Planilha2!$A:$A,Planilha2!H:H,"") -> 1 | AP84: =_xlfn.XLOOKUP(Tabela5[[#This Row],[UUID]],Planilha2!$A:$A,Planilha2!I:I,"") -> 0 | AQ84: =_xlfn.XLOOKUP(Tabela5[[#This Row],[UUID]],Planilha2!$A:$A,Planilha2!J:J,"") -> 0 | AR84: =_xlfn.XLOOKUP(Tabela5[[#This Row],[UUID]],Planilha2!$A:$A,Planilha2!K:K,"") -> 0 | AS84: =_xlfn.XLOOKUP(Tabela5[[#This Row],[UUID]],Planilha2!$A:$A,Planilha2!L:L,"") -> 0 | AT84: =_xlfn.XLOOKUP(Tabela5[[#This Row],[UUID]],Planilha2!$A:$A,Planilha2!M:M,"") -> 1 | AU84: =_xlfn.XLOOKUP(Tabela5[[#This Row],[UUID]],Planilha2!$A:$A,Planilha2!N:N,"") -> 1 | AV84: =_xlfn.XLOOKUP(Tabela5[[#This Row],[UUID]],Planilha2!$A:$A,Planilha2!O:O,"") -> 1
A85: COB-176561 | B85: Faturado | C85: 764335 | D85: 42110629720 | E85: PAULO ROBERTO DOS SANTOS | F85: RUA ADELAIDE CINELLI 15 ULISSES GUIMARAES / VILA VELHA - ES CEP: 29131-105 | G85: ADE-12215-H8P7M8 | H85: 45839 | I85: 202507 | J85: 106.56095 | L85: 106.56 | N85: 90427208 | O85: 45995 | P85: 46006 | R85: 120 | S85: 2 - CPF | T85: Em aberto - Vencido | U85: Em aberto - Vencido | V85: UBLI1FM | W85: 6 | X85: false | Y85: 6 | Z85: Em aberto - Vencido | AA85: ASSOCIAÇÃO ES-L1 | AB85: 35.686.965/0001-64 - ALEXANDRIA TECH | AE85: 61 a 120 dias | AF85: a1ef1d08-eb6c-4325-bf59-5965358cfa8f | AG85: 45917 | AH85: Maior que 90 | AI85: =_xlfn.XLOOKUP(Tabela5[[#This Row],[UUID]],Planilha2!$A:$A,Planilha2!B:B,"") -> 0 | AJ85: =_xlfn.XLOOKUP(Tabela5[[#This Row],[UUID]],Planilha2!$A:$A,Planilha2!C:C,"") -> 0 | AK85: =_xlfn.XLOOKUP(Tabela5[[#This Row],[UUID]],Planilha2!$A:$A,Planilha2!D:D,"") -> 0 | AL85: =_xlfn.XLOOKUP(Tabela5[[#This Row],[UUID]],Planilha2!$A:$A,Planilha2!E:E,"") -> 5 | AM85: =_xlfn.XLOOKUP(Tabela5[[#This Row],[UUID]],Planilha2!$A:$A,Planilha2!F:F,"") -> 0 | AN85: =_xlfn.XLOOKUP(Tabela5[[#This Row],[UUID]],Planilha2!$A:$A,Planilha2!G:G,"") -> 0 | AO85: =_xlfn.XLOOKUP(Tabela5[[#This Row],[UUID]],Planilha2!$A:$A,Planilha2!H:H,"") -> 0 | AP85: =_xlfn.XLOOKUP(Tabela5[[#This Row],[UUID]],Planilha2!$A:$A,Planilha2!I:I,"") -> 0 | AQ85: =_xlfn.XLOOKUP(Tabela5[[#This Row],[UUID]],Planilha2!$A:$A,Planilha2!J:J,"") -> 0 | AR85: =_xlfn.XLOOKUP(Tabela5[[#This Row],[UUID]],Planilha2!$A:$A,Planilha2!K:K,"") -> 0 | AS85: =_xlfn.XLOOKUP(Tabela5[[#This Row],[UUID]],Planilha2!$A:$A,Planilha2!L:L,"") -> 0 | AT85: =_xlfn.XLOOKUP(Tabela5[[#This Row],[UUID]],Planilha2!$A:$A,Planilha2!M:M,"") -> 0 | AU85: =_xlfn.XLOOKUP(Tabela5[[#This Row],[UUID]],Planilha2!$A:$A,Planilha2!N:N,"") -> 0 | AV85: =_xlfn.XLOOKUP(Tabela5[[#This Row],[UUID]],Planilha2!$A:$A,Planilha2!O:O,"") -> 0
A86: COB-242688 | B86: Faturado | C86: 10017912359 | D86: 48314676187 | E86: NELMA DOS SANTOS | F86: RUA SEM NOME, Q. 26, L. 14, S/N, APT 103 AGUAS LINDAS DE GOIAS S/N Parque da Barragem Setor 08 Águas Lindas de Goiás GO 72910001 | G86: ADE-15088-R1S1T1 | H86: 46082 | I86: 202603 | J86: 70.17864 | K86: 18.15 | L86: 88.33 | N86: 90519973 | O86: 46101 | P86: 46111 | R86: 15 | S86: 2 - CPF | T86: Em aberto - Vencido | U86: Em aberto - Vencido | V86: NGMOESY | W86: 6 | X86: false | Y86: 6 | Z86: Em aberto - Vencido | AA86: ASSOCIAÇÃO GO-L1 | AB86: 35.686.965/0001-64 - ALEXANDRIA TECH | AC86: Estimado | AE86: 1 a 30 dias | AF86: 3304b013-e8f3-4959-a8af-ad86d2aeba03 | AG86: 46104 | AH86: 1 a 30 dias | AI86: =_xlfn.XLOOKUP(Tabela5[[#This Row],[UUID]],Planilha2!$A:$A,Planilha2!B:B,"") -> 1 | AJ86: =_xlfn.XLOOKUP(Tabela5[[#This Row],[UUID]],Planilha2!$A:$A,Planilha2!C:C,"") -> 1 | AK86: =_xlfn.XLOOKUP(Tabela5[[#This Row],[UUID]],Planilha2!$A:$A,Planilha2!D:D,"") -> 1 | AL86: =_xlfn.XLOOKUP(Tabela5[[#This Row],[UUID]],Planilha2!$A:$A,Planilha2!E:E,"") -> 0 | AM86: =_xlfn.XLOOKUP(Tabela5[[#This Row],[UUID]],Planilha2!$A:$A,Planilha2!F:F,"") -> 1 | AN86: =_xlfn.XLOOKUP(Tabela5[[#This Row],[UUID]],Planilha2!$A:$A,Planilha2!G:G,"") -> 1 | AO86: =_xlfn.XLOOKUP(Tabela5[[#This Row],[UUID]],Planilha2!$A:$A,Planilha2!H:H,"") -> 1 | AP86: =_xlfn.XLOOKUP(Tabela5[[#This Row],[UUID]],Planilha2!$A:$A,Planilha2!I:I,"") -> 1 | AQ86: =_xlfn.XLOOKUP(Tabela5[[#This Row],[UUID]],Planilha2!$A:$A,Planilha2!J:J,"") -> 1 | AR86: =_xlfn.XLOOKUP(Tabela5[[#This Row],[UUID]],Planilha2!$A:$A,Planilha2!K:K,"") -> 0 | AS86: =_xlfn.XLOOKUP(Tabela5[[#This Row],[UUID]],Planilha2!$A:$A,Planilha2!L:L,"") -> 0 | AT86: =_xlfn.XLOOKUP(Tabela5[[#This Row],[UUID]],Planilha2!$A:$A,Planilha2!M:M,"") -> 1 | AU86: =_xlfn.XLOOKUP(Tabela5[[#This Row],[UUID]],Planilha2!$A:$A,Planilha2!N:N,"") -> 1 | AV86: =_xlfn.XLOOKUP(Tabela5[[#This Row],[UUID]],Planilha2!$A:$A,Planilha2!O:O,"") -> 1
A87: COB-242687 | B87: Faturado | C87: 9880005046 | D87: 60030143187 | E87: PAULO SERGIO JOSE DE OLIVEIRA | F87: AVENIDA INDAIA OESTE, Q. 27, L. 0, N. 59 CHAPADAO DO CEU 59 CENTRO Chapadão do Céu GO 75828000 | G87: ADE-15087-F5P5C4 | H87: 46082 | I87: 202603 | J87: 640.49869 | K87: 17.51 | L87: 658.01 | N87: 90520396 | O87: 46101 | P87: 46111 | R87: 15 | S87: 2 - CPF | T87: Em aberto - Vencido | U87: Em aberto - Vencido | V87: V9Z3XK7 | W87: 6 | X87: false | Y87: 6 | Z87: Em aberto - Vencido | AA87: ASSOCIAÇÃO GO-L1 | AB87: 35.686.965/0001-64 - ALEXANDRIA TECH | AC87: Estimado | AE87: 1 a 30 dias | AF87: 73219331-0372-4b43-befa-60b3a756de50 | AG87: 46111 | AH87: 1 a 30 dias | AI87: =_xlfn.XLOOKUP(Tabela5[[#This Row],[UUID]],Planilha2!$A:$A,Planilha2!B:B,"") -> 1 | AJ87: =_xlfn.XLOOKUP(Tabela5[[#This Row],[UUID]],Planilha2!$A:$A,Planilha2!C:C,"") -> 1 | AK87: =_xlfn.XLOOKUP(Tabela5[[#This Row],[UUID]],Planilha2!$A:$A,Planilha2!D:D,"") -> 8 | AL87: =_xlfn.XLOOKUP(Tabela5[[#This Row],[UUID]],Planilha2!$A:$A,Planilha2!E:E,"") -> 0 | AM87: =_xlfn.XLOOKUP(Tabela5[[#This Row],[UUID]],Planilha2!$A:$A,Planilha2!F:F,"") -> 1 | AN87: =_xlfn.XLOOKUP(Tabela5[[#This Row],[UUID]],Planilha2!$A:$A,Planilha2!G:G,"") -> 1 | AO87: =_xlfn.XLOOKUP(Tabela5[[#This Row],[UUID]],Planilha2!$A:$A,Planilha2!H:H,"") -> 1 | AP87: =_xlfn.XLOOKUP(Tabela5[[#This Row],[UUID]],Planilha2!$A:$A,Planilha2!I:I,"") -> 0 | AQ87: =_xlfn.XLOOKUP(Tabela5[[#This Row],[UUID]],Planilha2!$A:$A,Planilha2!J:J,"") -> 0 | AR87: =_xlfn.XLOOKUP(Tabela5[[#This Row],[UUID]],Planilha2!$A:$A,Planilha2!K:K,"") -> 0 | AS87: =_xlfn.XLOOKUP(Tabela5[[#This Row],[UUID]],Planilha2!$A:$A,Planilha2!L:L,"") -> 0 | AT87: =_xlfn.XLOOKUP(Tabela5[[#This Row],[UUID]],Planilha2!$A:$A,Planilha2!M:M,"") -> 1 | AU87: =_xlfn.XLOOKUP(Tabela5[[#This Row],[UUID]],Planilha2!$A:$A,Planilha2!N:N,"") -> 1 | AV87: =_xlfn.XLOOKUP(Tabela5[[#This Row],[UUID]],Planilha2!$A:$A,Planilha2!O:O,"") -> 1
A88: COB-242656 | B88: Faturado | C88: 20373480 | D88: 99009811115 | E88: GRACE KELLY FERREIRA MAIA SOUTO | F88: RUA C 118 VILA INDUSTRIAL JUNDIAI Anápolis GO 75115205 | G88: ADE-14883-M5T1H4 | H88: 46082 | I88: 202603 | J88: 149.81244 | L88: 149.81 | N88: 90520315 | O88: 46101 | P88: 46111 | R88: 15 | S88: 2 - CPF | T88: Em aberto - Vencido | U88: Em aberto - Vencido | V88: RKYKZZ9 | W88: 6 | X88: false | Y88: 6 | Z88: Em aberto - Vencido | AA88: ASSOCIAÇÃO GO-L1 | AB88: 35.686.965/0001-64 - ALEXANDRIA TECH | AC88: Estimado | AE88: 1 a 30 dias | AF88: 70337b5c-3108-478b-8e1a-0d6e1010ca47 | AG88: 46117 | AH88: 1 a 30 dias | AI88: =_xlfn.XLOOKUP(Tabela5[[#This Row],[UUID]],Planilha2!$A:$A,Planilha2!B:B,"") -> 1 | AJ88: =_xlfn.XLOOKUP(Tabela5[[#This Row],[UUID]],Planilha2!$A:$A,Planilha2!C:C,"") -> 1 | AK88: =_xlfn.XLOOKUP(Tabela5[[#This Row],[UUID]],Planilha2!$A:$A,Planilha2!D:D,"") -> 1 | AL88: =_xlfn.XLOOKUP(Tabela5[[#This Row],[UUID]],Planilha2!$A:$A,Planilha2!E:E,"") -> 0 | AM88: =_xlfn.XLOOKUP(Tabela5[[#This Row],[UUID]],Planilha2!$A:$A,Planilha2!F:F,"") -> 1 | AN88: =_xlfn.XLOOKUP(Tabela5[[#This Row],[UUID]],Planilha2!$A:$A,Planilha2!G:G,"") -> 0 | AO88: =_xlfn.XLOOKUP(Tabela5[[#This Row],[UUID]],Planilha2!$A:$A,Planilha2!H:H,"") -> 0 | AP88: =_xlfn.XLOOKUP(Tabela5[[#This Row],[UUID]],Planilha2!$A:$A,Planilha2!I:I,"") -> 0 | AQ88: =_xlfn.XLOOKUP(Tabela5[[#This Row],[UUID]],Planilha2!$A:$A,Planilha2!J:J,"") -> 0 | AR88: =_xlfn.XLOOKUP(Tabela5[[#This Row],[UUID]],Planilha2!$A:$A,Planilha2!K:K,"") -> 0 | AS88: =_xlfn.XLOOKUP(Tabela5[[#This Row],[UUID]],Planilha2!$A:$A,Planilha2!L:L,"") -> 0 | AT88: =_xlfn.XLOOKUP(Tabela5[[#This Row],[UUID]],Planilha2!$A:$A,Planilha2!M:M,"") -> 1 | AU88: =_xlfn.XLOOKUP(Tabela5[[#This Row],[UUID]],Planilha2!$A:$A,Planilha2!N:N,"") -> 1 | AV88: =_xlfn.XLOOKUP(Tabela5[[#This Row],[UUID]],Planilha2!$A:$A,Planilha2!O:O,"") -> 1
A89: COB-242655 | B89: Faturado | C89: 2570003639 | D89: 2283331137 | E89: LEIDILENE SOARES CASTRO | F89: RUA MARQ MACIEL EVANGELIS S/N Q. 00, L. | N. 0S/N, - - 1 Vila canaa Divinópolis de Goiás GO 73865000 | G89: ADE-14880-J2P2W1 | H89: 46082 | I89: 202603 | J89: 159.49837 | L89: 159.5 | N89: 90520310 | O89: 46101 | P89: 46111 | R89: 15 | S89: 2 - CPF | T89: Em aberto - Vencido | U89: Em aberto - Vencido | V89: QWMCQY7 | W89: 6 | X89: true | Y89: 6 | Z89: Em aberto - Vencido | AA89: ASSOCIAÇÃO GO-L1 | AB89: 35.686.965/0001-64 - ALEXANDRIA TECH | AC89: Estimado | AE89: 1 a 30 dias | AF89: 90367fb0-4fb5-4fbb-81c5-717f2e47fa1a | AG89: 46111 | AH89: 1 a 30 dias | AI89: =_xlfn.XLOOKUP(Tabela5[[#This Row],[UUID]],Planilha2!$A:$A,Planilha2!B:B,"") -> 1 | AJ89: =_xlfn.XLOOKUP(Tabela5[[#This Row],[UUID]],Planilha2!$A:$A,Planilha2!C:C,"") -> 1 | AK89: =_xlfn.XLOOKUP(Tabela5[[#This Row],[UUID]],Planilha2!$A:$A,Planilha2!D:D,"") -> 8 | AL89: =_xlfn.XLOOKUP(Tabela5[[#This Row],[UUID]],Planilha2!$A:$A,Planilha2!E:E,"") -> 0 | AM89: =_xlfn.XLOOKUP(Tabela5[[#This Row],[UUID]],Planilha2!$A:$A,Planilha2!F:F,"") -> 1 | AN89: =_xlfn.XLOOKUP(Tabela5[[#This Row],[UUID]],Planilha2!$A:$A,Planilha2!G:G,"") -> 1 | AO89: =_xlfn.XLOOKUP(Tabela5[[#This Row],[UUID]],Planilha2!$A:$A,Planilha2!H:H,"") -> 1 | AP89: =_xlfn.XLOOKUP(Tabela5[[#This Row],[UUID]],Planilha2!$A:$A,Planilha2!I:I,"") -> 0 | AQ89: =_xlfn.XLOOKUP(Tabela5[[#This Row],[UUID]],Planilha2!$A:$A,Planilha2!J:J,"") -> 0 | AR89: =_xlfn.XLOOKUP(Tabela5[[#This Row],[UUID]],Planilha2!$A:$A,Planilha2!K:K,"") -> 0 | AS89: =_xlfn.XLOOKUP(Tabela5[[#This Row],[UUID]],Planilha2!$A:$A,Planilha2!L:L,"") -> 0 | AT89: =_xlfn.XLOOKUP(Tabela5[[#This Row],[UUID]],Planilha2!$A:$A,Planilha2!M:M,"") -> 1 | AU89: =_xlfn.XLOOKUP(Tabela5[[#This Row],[UUID]],Planilha2!$A:$A,Planilha2!N:N,"") -> 1 | AV89: =_xlfn.XLOOKUP(Tabela5[[#This Row],[UUID]],Planilha2!$A:$A,Planilha2!O:O,"") -> 1
A90: COB-242650 | B90: Faturado | C90: 760267388 | D90: 2847585150 | E90: GILCIMAR WATHERSON GUERRA TOME | F90: RUA 29 S/N Q. 16, L. 12 ESTANCIA ITAGUAI Caldas Novas GO 75690-000 | G90: ADE-14870-P4Y5T9 | H90: 46082 | I90: 202603 | J90: 686.42754 | K90: 18.76 | L90: 705.19 | N90: 90520354 | O90: 46101 | P90: 46111 | R90: 15 | S90: 2 - CPF | T90: Em aberto - Vencido | U90: Em aberto - Vencido | V90: UGQKL4F | W90: 6 | X90: false | Y90: 6 | Z90: Em aberto - Vencido | AA90: ASSOCIAÇÃO GO-L1 | AB90: 35.686.965/0001-64 - ALEXANDRIA TECH | AC90: Estimado | AE90: 1 a 30 dias | AF90: d47110c4-892b-4b1b-b6bd-a31abc3abc8a | AG90: 46117 | AH90: 1 a 30 dias | AI90: =_xlfn.XLOOKUP(Tabela5[[#This Row],[UUID]],Planilha2!$A:$A,Planilha2!B:B,"") -> 1 | AJ90: =_xlfn.XLOOKUP(Tabela5[[#This Row],[UUID]],Planilha2!$A:$A,Planilha2!C:C,"") -> 1 | AK90: =_xlfn.XLOOKUP(Tabela5[[#This Row],[UUID]],Planilha2!$A:$A,Planilha2!D:D,"") -> 1 | AL90: =_xlfn.XLOOKUP(Tabela5[[#This Row],[UUID]],Planilha2!$A:$A,Planilha2!E:E,"") -> 0 | AM90: =_xlfn.XLOOKUP(Tabela5[[#This Row],[UUID]],Planilha2!$A:$A,Planilha2!F:F,"") -> 1 | AN90: =_xlfn.XLOOKUP(Tabela5[[#This Row],[UUID]],Planilha2!$A:$A,Planilha2!G:G,"") -> 0 | AO90: =_xlfn.XLOOKUP(Tabela5[[#This Row],[UUID]],Planilha2!$A:$A,Planilha2!H:H,"") -> 0 | AP90: =_xlfn.XLOOKUP(Tabela5[[#This Row],[UUID]],Planilha2!$A:$A,Planilha2!I:I,"") -> 0 | AQ90: =_xlfn.XLOOKUP(Tabela5[[#This Row],[UUID]],Planilha2!$A:$A,Planilha2!J:J,"") -> 0 | AR90: =_xlfn.XLOOKUP(Tabela5[[#This Row],[UUID]],Planilha2!$A:$A,Planilha2!K:K,"") -> 0 | AS90: =_xlfn.XLOOKUP(Tabela5[[#This Row],[UUID]],Planilha2!$A:$A,Planilha2!L:L,"") -> 0 | AT90: =_xlfn.XLOOKUP(Tabela5[[#This Row],[UUID]],Planilha2!$A:$A,Planilha2!M:M,"") -> 1 | AU90: =_xlfn.XLOOKUP(Tabela5[[#This Row],[UUID]],Planilha2!$A:$A,Planilha2!N:N,"") -> 1 | AV90: =_xlfn.XLOOKUP(Tabela5[[#This Row],[UUID]],Planilha2!$A:$A,Planilha2!O:O,"") -> 1
A91: COB-242646 | B91: Faturado | C91: 21108808 | D91: 95127313120 | E91: ELAINE RIBEIRO BARROS | F91: RUA TOCANTINS S/N Q. 12, L. 58 JARDIM ESPERANÇA Tatuí SP 18270-840 | G91: ADE-14822-Y4M8M2 | H91: 46082 | I91: 202603 | J91: 226.61741 | L91: 226.62 | N91: 90520258 | O91: 46101 | P91: 46111 | R91: 15 | S91: 2 - CPF | T91: Em aberto - Vencido | U91: Em aberto - Vencido | V91: UGNV92A | Y91: 6 | Z91: Em aberto - Vencido | AA91: ASSOCIAÇÃO GO-L1 | AB91: 35.686.965/0001-64 - ALEXANDRIA TECH | AC91: Estimado | AE91: 1 a 30 dias | AF91: 49e792bc-26e3-4f70-8b52-0979d91149f9 | AG91: 46111 | AH91: 1 a 30 dias | AI91: =_xlfn.XLOOKUP(Tabela5[[#This Row],[UUID]],Planilha2!$A:$A,Planilha2!B:B,"") -> 1 | AJ91: =_xlfn.XLOOKUP(Tabela5[[#This Row],[UUID]],Planilha2!$A:$A,Planilha2!C:C,"") -> 1 | AK91: =_xlfn.XLOOKUP(Tabela5[[#This Row],[UUID]],Planilha2!$A:$A,Planilha2!D:D,"") -> 8 | AL91: =_xlfn.XLOOKUP(Tabela5[[#This Row],[UUID]],Planilha2!$A:$A,Planilha2!E:E,"") -> 0 | AM91: =_xlfn.XLOOKUP(Tabela5[[#This Row],[UUID]],Planilha2!$A:$A,Planilha2!F:F,"") -> 1 | AN91: =_xlfn.XLOOKUP(Tabela5[[#This Row],[UUID]],Planilha2!$A:$A,Planilha2!G:G,"") -> 1 | AO91: =_xlfn.XLOOKUP(Tabela5[[#This Row],[UUID]],Planilha2!$A:$A,Planilha2!H:H,"") -> 1 | AP91: =_xlfn.XLOOKUP(Tabela5[[#This Row],[UUID]],Planilha2!$A:$A,Planilha2!I:I,"") -> 0 | AQ91: =_xlfn.XLOOKUP(Tabela5[[#This Row],[UUID]],Planilha2!$A:$A,Planilha2!J:J,"") -> 0 | AR91: =_xlfn.XLOOKUP(Tabela5[[#This Row],[UUID]],Planilha2!$A:$A,Planilha2!K:K,"") -> 0 | AS91: =_xlfn.XLOOKUP(Tabela5[[#This Row],[UUID]],Planilha2!$A:$A,Planilha2!L:L,"") -> 0 | AT91: =_xlfn.XLOOKUP(Tabela5[[#This Row],[UUID]],Planilha2!$A:$A,Planilha2!M:M,"") -> 1 | AU91: =_xlfn.XLOOKUP(Tabela5[[#This Row],[UUID]],Planilha2!$A:$A,Planilha2!N:N,"") -> 1 | AV91: =_xlfn.XLOOKUP(Tabela5[[#This Row],[UUID]],Planilha2!$A:$A,Planilha2!O:O,"") -> 1
A92: COB-242624 | B92: Faturado | C92: 10007630253 | D92: 19128975120 | E92: RONILDO JALES DE SOUZA | F92: RUA JONAS DUARTE, Q. 28, L. 3, S/N ANAPOLIS S/N Q. 28, L. 3 Calixtolândia Anápolis GO 75130530 | G92: ADE-14699-Y0G8C5 | H92: 46082 | I92: 202603 | J92: 1163.1285 | L92: 1163.13 | N92: 90519558 | O92: 46101 | P92: 46111 | R92: 15 | S92: 2 - CPF | T92: Em aberto - Vencido | U92: Em aberto - Vencido | V92: RDRK600 | W92: 6 | X92: false | Y92: 6 | Z92: Em aberto - Vencido | AA92: ASSOCIAÇÃO GO-L1 | AB92: 35.686.965/0001-64 - ALEXANDRIA TECH | AC92: Estimado | AE92: 1 a 30 dias | AF92: 61f3ca56-ab5c-4d75-980e-cb12f6ac8ced | AG92: 46111 | AH92: 1 a 30 dias | AI92: =_xlfn.XLOOKUP(Tabela5[[#This Row],[UUID]],Planilha2!$A:$A,Planilha2!B:B,"") -> 1 | AJ92: =_xlfn.XLOOKUP(Tabela5[[#This Row],[UUID]],Planilha2!$A:$A,Planilha2!C:C,"") -> 1 | AK92: =_xlfn.XLOOKUP(Tabela5[[#This Row],[UUID]],Planilha2!$A:$A,Planilha2!D:D,"") -> 1 | AL92: =_xlfn.XLOOKUP(Tabela5[[#This Row],[UUID]],Planilha2!$A:$A,Planilha2!E:E,"") -> 0 | AM92: =_xlfn.XLOOKUP(Tabela5[[#This Row],[UUID]],Planilha2!$A:$A,Planilha2!F:F,"") -> 1 | AN92: =_xlfn.XLOOKUP(Tabela5[[#This Row],[UUID]],Planilha2!$A:$A,Planilha2!G:G,"") -> 1 | AO92: =_xlfn.XLOOKUP(Tabela5[[#This Row],[UUID]],Planilha2!$A:$A,Planilha2!H:H,"") -> 1 | AP92: =_xlfn.XLOOKUP(Tabela5[[#This Row],[UUID]],Planilha2!$A:$A,Planilha2!I:I,"") -> 0 | AQ92: =_xlfn.XLOOKUP(Tabela5[[#This Row],[UUID]],Planilha2!$A:$A,Planilha2!J:J,"") -> 0 | AR92: =_xlfn.XLOOKUP(Tabela5[[#This Row],[UUID]],Planilha2!$A:$A,Planilha2!K:K,"") -> 0 | AS92: =_xlfn.XLOOKUP(Tabela5[[#This Row],[UUID]],Planilha2!$A:$A,Planilha2!L:L,"") -> 0 | AT92: =_xlfn.XLOOKUP(Tabela5[[#This Row],[UUID]],Planilha2!$A:$A,Planilha2!M:M,"") -> 1 | AU92: =_xlfn.XLOOKUP(Tabela5[[#This Row],[UUID]],Planilha2!$A:$A,Planilha2!N:N,"") -> 1 | AV92: =_xlfn.XLOOKUP(Tabela5[[#This Row],[UUID]],Planilha2!$A:$A,Planilha2!O:O,"") -> 1
A93: COB-242621 | B93: Faturado | C93: 9700000326 | D93: 8401025184 | E93: GLORIA LORENA BATISTA VIEIRA | F93: RUA ARAGUAIA S/N Q. 22, L. 02 Setor Central Colinas do Sul GO 73740000 | G93: ADE-14689-G7T1X0 | H93: 46082 | I93: 202603 | J93: 470.59774 | K93: 17.49 | L93: 488.09 | N93: 90519833 | O93: 46101 | P93: 46111 | R93: 15 | S93: 2 - CPF | T93: Em aberto - Vencido | U93: Em aberto - Vencido | V93: GI6IW1H | W93: 6 | X93: false | Y93: 6 | Z93: Em aberto - Vencido | AA93: ASSOCIAÇÃO GO-L1 | AB93: 35.686.965/0001-64 - ALEXANDRIA TECH | AC93: Estimado | AE93: 1 a 30 dias | AF93: a8944f63-cb3d-4458-895d-ba4c21a4680b | AG93: 46111 | AH93: 1 a 30 dias | AI93: =_xlfn.XLOOKUP(Tabela5[[#This Row],[UUID]],Planilha2!$A:$A,Planilha2!B:B,"") -> 1 | AJ93: =_xlfn.XLOOKUP(Tabela5[[#This Row],[UUID]],Planilha2!$A:$A,Planilha2!C:C,"") -> 1 | AK93: =_xlfn.XLOOKUP(Tabela5[[#This Row],[UUID]],Planilha2!$A:$A,Planilha2!D:D,"") -> 1 | AL93: =_xlfn.XLOOKUP(Tabela5[[#This Row],[UUID]],Planilha2!$A:$A,Planilha2!E:E,"") -> 0 | AM93: =_xlfn.XLOOKUP(Tabela5[[#This Row],[UUID]],Planilha2!$A:$A,Planilha2!F:F,"") -> 1 | AN93: =_xlfn.XLOOKUP(Tabela5[[#This Row],[UUID]],Planilha2!$A:$A,Planilha2!G:G,"") -> 1 | AO93: =_xlfn.XLOOKUP(Tabela5[[#This Row],[UUID]],Planilha2!$A:$A,Planilha2!H:H,"") -> 1 | AP93: =_xlfn.XLOOKUP(Tabela5[[#This Row],[UUID]],Planilha2!$A:$A,Planilha2!I:I,"") -> 0 | AQ93: =_xlfn.XLOOKUP(Tabela5[[#This Row],[UUID]],Planilha2!$A:$A,Planilha2!J:J,"") -> 0 | AR93: =_xlfn.XLOOKUP(Tabela5[[#This Row],[UUID]],Planilha2!$A:$A,Planilha2!K:K,"") -> 0 | AS93: =_xlfn.XLOOKUP(Tabela5[[#This Row],[UUID]],Planilha2!$A:$A,Planilha2!L:L,"") -> 0 | AT93: =_xlfn.XLOOKUP(Tabela5[[#This Row],[UUID]],Planilha2!$A:$A,Planilha2!M:M,"") -> 1 | AU93: =_xlfn.XLOOKUP(Tabela5[[#This Row],[UUID]],Planilha2!$A:$A,Planilha2!N:N,"") -> 1 | AV93: =_xlfn.XLOOKUP(Tabela5[[#This Row],[UUID]],Planilha2!$A:$A,Planilha2!O:O,"") -> 1
A94: COB-242620 | B94: Faturado | C94: 10028367683 | D94: 94843775134 | E94: SANDRA REGINA EUGENIA PACHECO | F94: RUA DOS MAGISTRADOS, S/N Q. 355, L. 1, APART - 304, BLOCO - 8 Jardim Buriti Sereno Aparecida de Goiânia GO 74942504 | G94: ADE-14688-C5S2N1 | H94: 46082 | I94: 202603 | J94: 228.40347 | L94: 228.4 | N94: 90519731 | O94: 46101 | P94: 46111 | R94: 15 | S94: 2 - CPF | T94: Em aberto - Vencido | U94: Em aberto - Vencido | V94: JTPPW4K | W94: 6 | X94: false | Y94: 6 | Z94: Em aberto - Vencido | AA94: ASSOCIAÇÃO GO-L1 | AB94: 35.686.965/0001-64 - ALEXANDRIA TECH | AC94: Estimado | AE94: 1 a 30 dias | AF94: 574620ef-5bc3-46db-a797-774998f63d2f | AG94: 46111 | AH94: 1 a 30 dias | AI94: =_xlfn.XLOOKUP(Tabela5[[#This Row],[UUID]],Planilha2!$A:$A,Planilha2!B:B,"") -> 1 | AJ94: =_xlfn.XLOOKUP(Tabela5[[#This Row],[UUID]],Planilha2!$A:$A,Planilha2!C:C,"") -> 1 | AK94: =_xlfn.XLOOKUP(Tabela5[[#This Row],[UUID]],Planilha2!$A:$A,Planilha2!D:D,"") -> 2 | AL94: =_xlfn.XLOOKUP(Tabela5[[#This Row],[UUID]],Planilha2!$A:$A,Planilha2!E:E,"") -> 0 | AM94: =_xlfn.XLOOKUP(Tabela5[[#This Row],[UUID]],Planilha2!$A:$A,Planilha2!F:F,"") -> 1 | AN94: =_xlfn.XLOOKUP(Tabela5[[#This Row],[UUID]],Planilha2!$A:$A,Planilha2!G:G,"") -> 1 | AO94: =_xlfn.XLOOKUP(Tabela5[[#This Row],[UUID]],Planilha2!$A:$A,Planilha2!H:H,"") -> 1 | AP94: =_xlfn.XLOOKUP(Tabela5[[#This Row],[UUID]],Planilha2!$A:$A,Planilha2!I:I,"") -> 0 | AQ94: =_xlfn.XLOOKUP(Tabela5[[#This Row],[UUID]],Planilha2!$A:$A,Planilha2!J:J,"") -> 0 | AR94: =_xlfn.XLOOKUP(Tabela5[[#This Row],[UUID]],Planilha2!$A:$A,Planilha2!K:K,"") -> 0 | AS94: =_xlfn.XLOOKUP(Tabela5[[#This Row],[UUID]],Planilha2!$A:$A,Planilha2!L:L,"") -> 0 | AT94: =_xlfn.XLOOKUP(Tabela5[[#This Row],[UUID]],Planilha2!$A:$A,Planilha2!M:M,"") -> 1 | AU94: =_xlfn.XLOOKUP(Tabela5[[#This Row],[UUID]],Planilha2!$A:$A,Planilha2!N:N,"") -> 1 | AV94: =_xlfn.XLOOKUP(Tabela5[[#This Row],[UUID]],Planilha2!$A:$A,Planilha2!O:O,"") -> 1
A95: COB-242618 | B95: Faturado | C95: 8680005905 | D95: 76167070172 | E95: GENESIO JOSE ROSA | F95: RUA JOAO PAULO I S/N Q. 45, L. 11 SETOR LESTE São Domingos GO 73860-000 | G95: ADE-14683-W3D2W8 | H95: 46082 | I95: 202603 | J95: 134.62067 | L95: 134.62 | N95: 90519593 | O95: 46101 | P95: 46111 | R95: 15 | S95: 2 - CPF | T95: Em aberto - Vencido | U95: Em aberto - Vencido | V95: SEPHORO | W95: 6 | X95: false | Y95: 6 | Z95: Em aberto - Vencido | AA95: ASSOCIAÇÃO GO-L1 | AB95: 35.686.965/0001-64 - ALEXANDRIA TECH | AC95: Estimado | AE95: 1 a 30 dias | AF95: 1a1a42c3-36ae-40af-8f82-814ab4461b86 | AG95: 46113 | AH95: 1 a 30 dias | AI95: =_xlfn.XLOOKUP(Tabela5[[#This Row],[UUID]],Planilha2!$A:$A,Planilha2!B:B,"") -> 1 | AJ95: =_xlfn.XLOOKUP(Tabela5[[#This Row],[UUID]],Planilha2!$A:$A,Planilha2!C:C,"") -> 1 | AK95: =_xlfn.XLOOKUP(Tabela5[[#This Row],[UUID]],Planilha2!$A:$A,Planilha2!D:D,"") -> 2 | AL95: =_xlfn.XLOOKUP(Tabela5[[#This Row],[UUID]],Planilha2!$A:$A,Planilha2!E:E,"") -> 0 | AM95: =_xlfn.XLOOKUP(Tabela5[[#This Row],[UUID]],Planilha2!$A:$A,Planilha2!F:F,"") -> 1 | AN95: =_xlfn.XLOOKUP(Tabela5[[#This Row],[UUID]],Planilha2!$A:$A,Planilha2!G:G,"") -> 1 | AO95: =_xlfn.XLOOKUP(Tabela5[[#This Row],[UUID]],Planilha2!$A:$A,Planilha2!H:H,"") -> 1 | AP95: =_xlfn.XLOOKUP(Tabela5[[#This Row],[UUID]],Planilha2!$A:$A,Planilha2!I:I,"") -> 0 | AQ95: =_xlfn.XLOOKUP(Tabela5[[#This Row],[UUID]],Planilha2!$A:$A,Planilha2!J:J,"") -> 0 | AR95: =_xlfn.XLOOKUP(Tabela5[[#This Row],[UUID]],Planilha2!$A:$A,Planilha2!K:K,"") -> 0 | AS95: =_xlfn.XLOOKUP(Tabela5[[#This Row],[UUID]],Planilha2!$A:$A,Planilha2!L:L,"") -> 0 | AT95: =_xlfn.XLOOKUP(Tabela5[[#This Row],[UUID]],Planilha2!$A:$A,Planilha2!M:M,"") -> 0 | AU95: =_xlfn.XLOOKUP(Tabela5[[#This Row],[UUID]],Planilha2!$A:$A,Planilha2!N:N,"") -> 1 | AV95: =_xlfn.XLOOKUP(Tabela5[[#This Row],[UUID]],Planilha2!$A:$A,Planilha2!O:O,"") -> 1
A96: COB-242614 | B96: Faturado | C96: 200461266 | D96: 94991600197 | E96: JOYCE DE OLIVEIRA MOURA MARQUES | F96: Rua Gaviões SN 18, L. 8 Jardim das Acácias A Aparecida de Goiânia GO 74987-210 | G96: ADE-14668-D4B7X4 | H96: 46082 | I96: 202603 | J96: 214.8065 | L96: 214.81 | N96: 90519971 | O96: 46101 | P96: 46111 | R96: 15 | S96: 2 - CPF | T96: Em aberto - Vencido | U96: Em aberto - Vencido | V96: M6LKM39 | W96: 6 | X96: false | Y96: 6 | Z96: Em aberto - Vencido | AA96: ASSOCIAÇÃO GO-L1 | AB96: 35.686.965/0001-64 - ALEXANDRIA TECH | AC96: Estimado | AE96: 1 a 30 dias | AF96: e02bb8d3-52a5-41bf-8d47-86742c84dc98 | AG96: 46113 | AH96: 1 a 30 dias | AI96: =_xlfn.XLOOKUP(Tabela5[[#This Row],[UUID]],Planilha2!$A:$A,Planilha2!B:B,"") -> 1 | AJ96: =_xlfn.XLOOKUP(Tabela5[[#This Row],[UUID]],Planilha2!$A:$A,Planilha2!C:C,"") -> 1 | AK96: =_xlfn.XLOOKUP(Tabela5[[#This Row],[UUID]],Planilha2!$A:$A,Planilha2!D:D,"") -> 2 | AL96: =_xlfn.XLOOKUP(Tabela5[[#This Row],[UUID]],Planilha2!$A:$A,Planilha2!E:E,"") -> 0 | AM96: =_xlfn.XLOOKUP(Tabela5[[#This Row],[UUID]],Planilha2!$A:$A,Planilha2!F:F,"") -> 1 | AN96: =_xlfn.XLOOKUP(Tabela5[[#This Row],[UUID]],Planilha2!$A:$A,Planilha2!G:G,"") -> 1 | AO96: =_xlfn.XLOOKUP(Tabela5[[#This Row],[UUID]],Planilha2!$A:$A,Planilha2!H:H,"") -> 1 | AP96: =_xlfn.XLOOKUP(Tabela5[[#This Row],[UUID]],Planilha2!$A:$A,Planilha2!I:I,"") -> 0 | AQ96: =_xlfn.XLOOKUP(Tabela5[[#This Row],[UUID]],Planilha2!$A:$A,Planilha2!J:J,"") -> 0 | AR96: =_xlfn.XLOOKUP(Tabela5[[#This Row],[UUID]],Planilha2!$A:$A,Planilha2!K:K,"") -> 0 | AS96: =_xlfn.XLOOKUP(Tabela5[[#This Row],[UUID]],Planilha2!$A:$A,Planilha2!L:L,"") -> 0 | AT96: =_xlfn.XLOOKUP(Tabela5[[#This Row],[UUID]],Planilha2!$A:$A,Planilha2!M:M,"") -> 0 | AU96: =_xlfn.XLOOKUP(Tabela5[[#This Row],[UUID]],Planilha2!$A:$A,Planilha2!N:N,"") -> 1 | AV96: =_xlfn.XLOOKUP(Tabela5[[#This Row],[UUID]],Planilha2!$A:$A,Planilha2!O:O,"") -> 1
A97: COB-130813 | B97: Faturado | C97: 10004439510 | D97: 95294643120 | E97: ROSEVANIA CONCEICAO DE SOUZA | F97: AVENIDA FERROVIARIA E, N. 1361 SETOR NORDESTE CEP: 73807330 FORMOSA GO BRASIL | G97: ADE-11730-Q6H2K4 | H97: 45839 | I97: 202507 | J97: 185.26333 | L97: 185.26 | N97: 90364286 | O97: 45916 | P97: 45926 | R97: 200 | S97: 2 - CPF | T97: Em aberto - Vencido | U97: Em aberto - Vencido | V97: NZKLMFL | W97: 6 | X97: false | Y97: 6 | Z97: Em aberto - Vencido | AA97: ASSOCIAÇÃO GO-L1 | AB97: 35.686.965/0001-64 - ALEXANDRIA TECH | AE97: 171 a 450 dias | AF97: f721e58e-0d87-4f50-8ae5-f906e8dbce05 | AG97: 45954 | AH97: Maior que 90 | AI97: =_xlfn.XLOOKUP(Tabela5[[#This Row],[UUID]],Planilha2!$A:$A,Planilha2!B:B,"") -> 0 | AJ97: =_xlfn.XLOOKUP(Tabela5[[#This Row],[UUID]],Planilha2!$A:$A,Planilha2!C:C,"") -> 0 | AK97: =_xlfn.XLOOKUP(Tabela5[[#This Row],[UUID]],Planilha2!$A:$A,Planilha2!D:D,"") -> 0 | AL97: =_xlfn.XLOOKUP(Tabela5[[#This Row],[UUID]],Planilha2!$A:$A,Planilha2!E:E,"") -> 5 | AM97: =_xlfn.XLOOKUP(Tabela5[[#This Row],[UUID]],Planilha2!$A:$A,Planilha2!F:F,"") -> 0 | AN97: =_xlfn.XLOOKUP(Tabela5[[#This Row],[UUID]],Planilha2!$A:$A,Planilha2!G:G,"") -> 0 | AO97: =_xlfn.XLOOKUP(Tabela5[[#This Row],[UUID]],Planilha2!$A:$A,Planilha2!H:H,"") -> 0 | AP97: =_xlfn.XLOOKUP(Tabela5[[#This Row],[UUID]],Planilha2!$A:$A,Planilha2!I:I,"") -> 0 | AQ97: =_xlfn.XLOOKUP(Tabela5[[#This Row],[UUID]],Planilha2!$A:$A,Planilha2!J:J,"") -> 0 | AR97: =_xlfn.XLOOKUP(Tabela5[[#This Row],[UUID]],Planilha2!$A:$A,Planilha2!K:K,"") -> 0 | AS97: =_xlfn.XLOOKUP(Tabela5[[#This Row],[UUID]],Planilha2!$A:$A,Planilha2!L:L,"") -> 0 | AT97: =_xlfn.XLOOKUP(Tabela5[[#This Row],[UUID]],Planilha2!$A:$A,Planilha2!M:M,"") -> 0 | AU97: =_xlfn.XLOOKUP(Tabela5[[#This Row],[UUID]],Planilha2!$A:$A,Planilha2!N:N,"") -> 0 | AV97: =_xlfn.XLOOKUP(Tabela5[[#This Row],[UUID]],Planilha2!$A:$A,Planilha2!O:O,"") -> 0
A98: COB-242613 | B98: Faturado | C98: 690293112 | D98: 16840305104 | E98: ILDO ALVES BORGES | F98: RUA DO BRAZ, Q. 963 Q. 9, L. 20 Dom Bosco Itumbiara GO 75533780 | G98: ADE-14667-P5R1W8 | H98: 46082 | I98: 202603 | J98: 248.82289 | L98: 248.82 | N98: 90519636 | O98: 46101 | P98: 46111 | R98: 15 | S98: 2 - CPF | T98: Em aberto - Vencido | U98: Em aberto - Vencido | V98: 3WA2IYY | W98: 6 | X98: false | Y98: 6 | Z98: Em aberto - Vencido | AA98: ASSOCIAÇÃO GO-L1 | AB98: 35.686.965/0001-64 - ALEXANDRIA TECH | AC98: Estimado | AE98: 1 a 30 dias | AF98: f9587467-e482-4bf1-a28c-c2efe1c33dfe | AG98: 46121 | AH98: 1 a 30 dias | AI98: =_xlfn.XLOOKUP(Tabela5[[#This Row],[UUID]],Planilha2!$A:$A,Planilha2!B:B,"") -> 1 | AJ98: =_xlfn.XLOOKUP(Tabela5[[#This Row],[UUID]],Planilha2!$A:$A,Planilha2!C:C,"") -> 1 | AK98: =_xlfn.XLOOKUP(Tabela5[[#This Row],[UUID]],Planilha2!$A:$A,Planilha2!D:D,"") -> 11 | AL98: =_xlfn.XLOOKUP(Tabela5[[#This Row],[UUID]],Planilha2!$A:$A,Planilha2!E:E,"") -> 0 | AM98: =_xlfn.XLOOKUP(Tabela5[[#This Row],[UUID]],Planilha2!$A:$A,Planilha2!F:F,"") -> 1 | AN98: =_xlfn.XLOOKUP(Tabela5[[#This Row],[UUID]],Planilha2!$A:$A,Planilha2!G:G,"") -> 0 | AO98: =_xlfn.XLOOKUP(Tabela5[[#This Row],[UUID]],Planilha2!$A:$A,Planilha2!H:H,"") -> 0 | AP98: =_xlfn.XLOOKUP(Tabela5[[#This Row],[UUID]],Planilha2!$A:$A,Planilha2!I:I,"") -> 0 | AQ98: =_xlfn.XLOOKUP(Tabela5[[#This Row],[UUID]],Planilha2!$A:$A,Planilha2!J:J,"") -> 0 | AR98: =_xlfn.XLOOKUP(Tabela5[[#This Row],[UUID]],Planilha2!$A:$A,Planilha2!K:K,"") -> 0 | AS98: =_xlfn.XLOOKUP(Tabela5[[#This Row],[UUID]],Planilha2!$A:$A,Planilha2!L:L,"") -> 0 | AT98: =_xlfn.XLOOKUP(Tabela5[[#This Row],[UUID]],Planilha2!$A:$A,Planilha2!M:M,"") -> 0 | AU98: =_xlfn.XLOOKUP(Tabela5[[#This Row],[UUID]],Planilha2!$A:$A,Planilha2!N:N,"") -> 1 | AV98: =_xlfn.XLOOKUP(Tabela5[[#This Row],[UUID]],Planilha2!$A:$A,Planilha2!O:O,"") -> 0
A99: COB-242612 | B99: Faturado | C99: 10036795660 | D99: 6345828360 | E99: ANTONIA LIDINARIA LAGO BARBOSA | F99: AVENIDA DR EPITACIO S DA CRUZ, S/N , Q. 61, L. 9 JARDIM DOM BOSCO II Aparecida de Goiânia GO 74963645 | G99: ADE-14663-C6G3L4 | H99: 46082 | I99: 202603 | J99: 205.42722 | K99: 0 | L99: 205.43 | N99: 90520038 | O99: 46101 | P99: 46111 | R99: 15 | S99: 2 - CPF | T99: Em aberto - Vencido | U99: Em aberto - Vencido | V99: 5H1NVIS | W99: 6 | X99: false | Y99: 6 | Z99: Em aberto - Vencido | AA99: ASSOCIAÇÃO GO-L1 | AB99: 35.686.965/0001-64 - ALEXANDRIA TECH | AC99: Estimado | AE99: 1 a 30 dias | AF99: 5134880b-8de8-44ff-adec-81a5034f262a | AG99: 46122 | AH99: 1 a 30 dias | AI99: =_xlfn.XLOOKUP(Tabela5[[#This Row],[UUID]],Planilha2!$A:$A,Planilha2!B:B,"") -> 1 | AJ99: =_xlfn.XLOOKUP(Tabela5[[#This Row],[UUID]],Planilha2!$A:$A,Planilha2!C:C,"") -> 1 | AK99: =_xlfn.XLOOKUP(Tabela5[[#This Row],[UUID]],Planilha2!$A:$A,Planilha2!D:D,"") -> 1 | AL99: =_xlfn.XLOOKUP(Tabela5[[#This Row],[UUID]],Planilha2!$A:$A,Planilha2!E:E,"") -> 0 | AM99: =_xlfn.XLOOKUP(Tabela5[[#This Row],[UUID]],Planilha2!$A:$A,Planilha2!F:F,"") -> 1 | AN99: =_xlfn.XLOOKUP(Tabela5[[#This Row],[UUID]],Planilha2!$A:$A,Planilha2!G:G,"") -> 0 | AO99: =_xlfn.XLOOKUP(Tabela5[[#This Row],[UUID]],Planilha2!$A:$A,Planilha2!H:H,"") -> 0 | AP99: =_xlfn.XLOOKUP(Tabela5[[#This Row],[UUID]],Planilha2!$A:$A,Planilha2!I:I,"") -> 0 | AQ99: =_xlfn.XLOOKUP(Tabela5[[#This Row],[UUID]],Planilha2!$A:$A,Planilha2!J:J,"") -> 0 | AR99: =_xlfn.XLOOKUP(Tabela5[[#This Row],[UUID]],Planilha2!$A:$A,Planilha2!K:K,"") -> 0 | AS99: =_xlfn.XLOOKUP(Tabela5[[#This Row],[UUID]],Planilha2!$A:$A,Planilha2!L:L,"") -> 0 | AT99: =_xlfn.XLOOKUP(Tabela5[[#This Row],[UUID]],Planilha2!$A:$A,Planilha2!M:M,"") -> 0 | AU99: =_xlfn.XLOOKUP(Tabela5[[#This Row],[UUID]],Planilha2!$A:$A,Planilha2!N:N,"") -> 1 | AV99: =_xlfn.XLOOKUP(Tabela5[[#This Row],[UUID]],Planilha2!$A:$A,Planilha2!O:O,"") -> 0
A100: COB-242610 | B100: Faturado | C100: 200011390 | D100: 461939100 | E100: ALEX DIAS MUNIZ | F100: RUA 1 DE MAIO, S/N Q. 48, L. 1 Cidade Livre Aparecida de Goiânia GO 74970280 | G100: ADE-14658-T8C9H4 | H100: 46082 | I100: 202603 | J100: 231.98463 | L100: 231.98 | N100: 90519572 | O100: 46101 | P100: 46111 | R100: 15 | S100: 2 - CPF | T100: Em aberto - Vencido | U100: Em aberto - Vencido | V100: FJQXI96 | W100: 6 | X100: false | Y100: 6 | Z100: Em aberto - Vencido | AA100: ASSOCIAÇÃO GO-L1 | AB100: 35.686.965/0001-64 - ALEXANDRIA TECH | AC100: Estimado | AE100: 1 a 30 dias | AF100: 0ac42009-cddb-40ae-8980-8d725dd5fa3a | AG100: 46106 | AH100: 1 a 30 dias | AI100: =_xlfn.XLOOKUP(Tabela5[[#This Row],[UUID]],Planilha2!$A:$A,Planilha2!B:B,"") -> 1 | AJ100: =_xlfn.XLOOKUP(Tabela5[[#This Row],[UUID]],Planilha2!$A:$A,Planilha2!C:C,"") -> 2 | AK100: =_xlfn.XLOOKUP(Tabela5[[#This Row],[UUID]],Planilha2!$A:$A,Planilha2!D:D,"") -> 5 | AL100: =_xlfn.XLOOKUP(Tabela5[[#This Row],[UUID]],Planilha2!$A:$A,Planilha2!E:E,"") -> 0 | AM100: =_xlfn.XLOOKUP(Tabela5[[#This Row],[UUID]],Planilha2!$A:$A,Planilha2!F:F,"") -> 1 | AN100: =_xlfn.XLOOKUP(Tabela5[[#This Row],[UUID]],Planilha2!$A:$A,Planilha2!G:G,"") -> 1 | AO100: =_xlfn.XLOOKUP(Tabela5[[#This Row],[UUID]],Planilha2!$A:$A,Planilha2!H:H,"") -> 1 | AP100: =_xlfn.XLOOKUP(Tabela5[[#This Row],[UUID]],Planilha2!$A:$A,Planilha2!I:I,"") -> 1 | AQ100: =_xlfn.XLOOKUP(Tabela5[[#This Row],[UUID]],Planilha2!$A:$A,Planilha2!J:J,"") -> 1 | AR100: =_xlfn.XLOOKUP(Tabela5[[#This Row],[UUID]],Planilha2!$A:$A,Planilha2!K:K,"") -> 0 | AS100: =_xlfn.XLOOKUP(Tabela5[[#This Row],[UUID]],Planilha2!$A:$A,Planilha2!L:L,"") -> 0 | AT100: =_xlfn.XLOOKUP(Tabela5[[#This Row],[UUID]],Planilha2!$A:$A,Planilha2!M:M,"") -> 0 | AU100: =_xlfn.XLOOKUP(Tabela5[[#This Row],[UUID]],Planilha2!$A:$A,Planilha2!N:N,"") -> 1 | AV100: =_xlfn.XLOOKUP(Tabela5[[#This Row],[UUID]],Planilha2!$A:$A,Planilha2!O:O,"") -> 1
A101: COB-242608 | B101: Faturado | C101: 20337887 | D101: 39422208734 | E101: ALDEMIRO ALVES DUARTE | F101: RUA 07 S/N Q. 11, L. 15 Frei Eustáquio Anápolis GO 75044110 | G101: ADE-14655-G8W0Y8 | H101: 46082 | I101: 202603 | J101: 210.67962 | L101: 210.68 | N101: 90519544 | O101: 46101 | P101: 46111 | R101: 15 | S101: 2 - CPF | T101: Em aberto - Vencido | U101: Em aberto - Vencido | V101: UIOCGPT | W101: 6 | X101: false | Y101: 6 | Z101: Em aberto - Vencido | AA101: ASSOCIAÇÃO GO-L1 | AB101: 35.686.965/0001-64 - ALEXANDRIA TECH | AC101: Estimado | AE101: 1 a 30 dias | AF101: 0da3fdd9-fe33-406a-861e-c19b0e7435db | AG101: 46117 | AH101: 1 a 30 dias | AI101: =_xlfn.XLOOKUP(Tabela5[[#This Row],[UUID]],Planilha2!$A:$A,Planilha2!B:B,"") -> 1 | AJ101: =_xlfn.XLOOKUP(Tabela5[[#This Row],[UUID]],Planilha2!$A:$A,Planilha2!C:C,"") -> 1 | AK101: =_xlfn.XLOOKUP(Tabela5[[#This Row],[UUID]],Planilha2!$A:$A,Planilha2!D:D,"") -> 1 | AL101: =_xlfn.XLOOKUP(Tabela5[[#This Row],[UUID]],Planilha2!$A:$A,Planilha2!E:E,"") -> 0 | AM101: =_xlfn.XLOOKUP(Tabela5[[#This Row],[UUID]],Planilha2!$A:$A,Planilha2!F:F,"") -> 1 | AN101: =_xlfn.XLOOKUP(Tabela5[[#This Row],[UUID]],Planilha2!$A:$A,Planilha2!G:G,"") -> 0 | AO101: =_xlfn.XLOOKUP(Tabela5[[#This Row],[UUID]],Planilha2!$A:$A,Planilha2!H:H,"") -> 0 | AP101: =_xlfn.XLOOKUP(Tabela5[[#This Row],[UUID]],Planilha2!$A:$A,Planilha2!I:I,"") -> 0 | AQ101: =_xlfn.XLOOKUP(Tabela5[[#This Row],[UUID]],Planilha2!$A:$A,Planilha2!J:J,"") -> 0 | AR101: =_xlfn.XLOOKUP(Tabela5[[#This Row],[UUID]],Planilha2!$A:$A,Planilha2!K:K,"") -> 0 | AS101: =_xlfn.XLOOKUP(Tabela5[[#This Row],[UUID]],Planilha2!$A:$A,Planilha2!L:L,"") -> 0 | AT101: =_xlfn.XLOOKUP(Tabela5[[#This Row],[UUID]],Planilha2!$A:$A,Planilha2!M:M,"") -> 1 | AU101: =_xlfn.XLOOKUP(Tabela5[[#This Row],[UUID]],Planilha2!$A:$A,Planilha2!N:N,"") -> 1 | AV101: =_xlfn.XLOOKUP(Tabela5[[#This Row],[UUID]],Planilha2!$A:$A,Planilha2!O:O,"") -> 1
...

Sheet Acordos
A1: Acordo Alexandria - EDP
C3: 215989.54 | H3: 43197.91 | I3: 43197.91 | J3: 43197.91 | K3: 43197.91 | L3: 43197.91
A4: mes_referencia | B4: status | C4: valor_total | D4: UC_Numero | E4: Cliente_Nome | F4: numero_parcela | G4: Data de Adesão | H4: Entrada | I4: Parcela 1 - Abril | J4: Parcela 2 - Maio | K4: Parcela 3 - Junho | L4: Parcela 4 - Julho
A5: 46023 | B5: Em Acordo_Campanha Consumidor | C5: 197.98 | D5: 97711357 | E5: ADRIANA VALERIA CORDEIRO PINTO | F5: Entrada 20% + 4 parcelas | G5: 46093 | H5: 39.6 | I5: 39.6 | J5: 39.6 | K5: 39.6 | L5: 39.6
A6: 46023 | B6: Em Acordo_Campanha Consumidor | C6: 143.36 | D6: 35405821 | E6: ALBERT LOIS FERNANDEZ GIMON | F6: Entrada 20% + 4 parcelas | G6: 46093 | H6: 28.67 | I6: 28.67 | J6: 28.67 | K6: 28.67 | L6: 28.67
A7: 46023 | B7: Em Acordo_Campanha Consumidor | C7: 230.82 | D7: 782708 | E7: Alenir Souza | F7: Entrada 20% + 4 parcelas | G7: 46093 | H7: 46.16 | I7: 46.16 | J7: 46.16 | K7: 46.16 | L7: 46.16
A8: 46023 | B8: Em Acordo_Campanha Consumidor | C8: 237.06 | D8: 5300800 | E8: ALEXANDRE DE SOUZA | F8: Entrada 20% + 4 parcelas | G8: 46093 | H8: 47.41 | I8: 47.41 | J8: 47.41 | K8: 47.41 | L8: 47.41
A9: 46023 | B9: Em Acordo_Campanha Consumidor | C9: 830.01 | D9: 76629040 | E9: ALVORADA SHOW COMERCIO DE DOCES LTDA | F9: Entrada 20% + 4 parcelas | G9: 46093 | H9: 166 | I9: 166 | J9: 166 | K9: 166 | L9: 166
A10: 46023 | B10: Em Acordo_Campanha Consumidor | C10: 498.53 | D10: 150976475 | E10: AMERICAN COLORS DO BRASIL INDUSTRIA DE TINTAS LTDA | F10: Entrada 20% + 4 parcelas | G10: 46093 | H10: 99.71 | I10: 99.71 | J10: 99.71 | K10: 99.71 | L10: 99.71
A11: 46023 | B11: Em Acordo_Campanha Consumidor | C11: 11367.2 | D11: 414361319 | E11: AMERICAS CENTRO DE BELEZA LTDA | F11: Entrada 20% + 4 parcelas | G11: 46093 | H11: 2273.44 | I11: 2273.44 | J11: 2273.44 | K11: 2273.44 | L11: 2273.44
A12: 46023 | B12: Em Acordo_Campanha Consumidor | C12: 242.42 | D12: 10031440914 | E12: ANA CAROLINA VIEIRA DOS SANTOS | F12: Entrada 20% + 4 parcelas | G12: 46093 | H12: 48.48 | I12: 48.48 | J12: 48.48 | K12: 48.48 | L12: 48.48
A13: 46023 | B13: Em Acordo_Campanha Consumidor | C13: 685.92 | D13: 40395618 | E13: ANA CLAUDIA MENDONCA RODRIGUES GUAZZELLI | F13: Entrada 20% + 4 parcelas | G13: 46093 | H13: 137.18 | I13: 137.18 | J13: 137.18 | K13: 137.18 | L13: 137.18
A14: 46023 | B14: Em Acordo_Campanha Consumidor | C14: 200.14 | D14: 59679271 | E14: ANANDA PEREIRA COELHO | F14: Entrada 20% + 4 parcelas | G14: 46093 | H14: 40.03 | I14: 40.03 | J14: 40.03 | K14: 40.03 | L14: 40.03
A15: 46023 | B15: Em Acordo_Campanha Consumidor | C15: 210.3 | D15: 70908401 | E15: ANDRE PAULO DE OLIVEIRA ROCHA | F15: Entrada 20% + 4 parcelas | G15: 46093 | H15: 42.06 | I15: 42.06 | J15: 42.06 | K15: 42.06 | L15: 42.06
A16: 45901 | B16: Em Acordo_Campanha Consumidor | C16: 181.91 | D16: 10037258760 | E16: ANNA BEATRIZ DIAS DE OLIVEIRA SILVA | F16: Entrada 20% + 4 parcelas | G16: 46093 | H16: 36.38 | I16: 36.38 | J16: 36.38 | K16: 36.38 | L16: 36.38
... A273: 46023 | B273: Em Acordo_Campanha Consumidor | C273: 127.23 | D273: 85389439 | E273: WILLIAM GOMES TEIXEIRA | F273: Entrada 20% + 4 parcelas | G273: 46102 | H273: 25.45 | I273: 25.45 | J273: 25.45 | K273: 25.45 | L273: 25.45

Sheet Planilha2
A1: identificador | B1: AVISO_VENCIMENTO_2DIAS | C1: AVISO_VENCIMENTO_5DIAS | D1: FATURA_ENVIO | E1: FATURA_INADIMPLENCIA | F1: FATURA_VENCE_HOJE | G1: FATURA_VENCIDA_10_DIAS | H1: FATURA_VENCIDA_14_DIAS | I1: FATURA_VENCIDA_17_DIAS | J1: FATURA_VENCIDA_21_DIAS | K1: FATURA_VENCIDA_25_DIAS | L1: FATURA_VENCIDA_30_DIAS | M1: FATURA_VENCIDA_3_DIAS | N1: FATURA_VENCIDA_5_DIAS | O1: FATURA_VENCIDA_7_DIAS
A2: 000b7de5-68e0-465c-9af7-670b4a2a9d79 | B2: 1 | C2: 1 | D2: 1 | F2: 1 | G2: 1 | H2: 1 | I2: 1 | J2: 1 | K2: 1 | L2: 1 | N2: 1 | O2: 1
A3: 001d9e77-43c5-43f3-bafd-466608d37c2f | B3: 1 | C3: 1 | D3: 1 | F3: 1 | G3: 1 | N3: 1 | O3: 1
A4: 004c9136-a745-42f4-a630-08e36ec22e04 | B4: 1 | D4: 1 | F4: 1 | G4: 1 | H4: 1 | I4: 1 | J4: 1 | K4: 1 | L4: 1 | N4: 1 | O4: 1
A5: 00651071-57f6-459e-bb1e-fe8f8acc56f2 | B5: 1 | D5: 5 | E5: 1 | F5: 1 | G5: 1 | H5: 1 | I5: 1 | J5: 1 | K5: 1 | N5: 1 | O5: 1
A6: 006c8c5f-fdf4-46fb-b2be-cca6701750a3 | B6: 1 | D6: 44 | F6: 1 | G6: 1 | H6: 1 | I6: 1 | J6: 1 | K6: 1 | L6: 1 | N6: 1 | O6: 1
A7: 0082e2f5-42d0-4c91-9b77-63332d8f2c5e | B7: 1 | C7: 2 | D7: 22 | F7: 1 | G7: 1 | H7: 1 | I7: 1 | J7: 1 | N7: 1 | O7: 1
A8: 00c541af-609c-46cd-8e0e-90d014aec71d | B8: 1 | D8: 6 | F8: 1 | G8: 1 | H8: 1 | I8: 1 | J8: 1 | K8: 1 | L8: 1 | N8: 1 | O8: 1
A9: 00de30a6-52ee-4aa8-8d87-c8e376b4c457 | B9: 1 | D9: 1 | F9: 1 | G9: 1 | H9: 1 | I9: 1 | J9: 1 | K9: 1 | L9: 1 | N9: 1 | O9: 1
A10: 011469cd-e097-4af4-b547-8eda06d49b8e | B10: 1 | C10: 1 | D10: 5 | F10: 1 | G10: 1 | H10: 1 | I10: 1 | J10: 1 | K10: 1 | L10: 1 | N10: 1 | O10: 1
A11: 014adca5-99b9-4372-99c8-382e28603956 | B11: 1 | C11: 1 | D11: 1 | F11: 1 | G11: 1 | H11: 1 | M11: 1 | N11: 1 | O11: 1
A12: 017c0d10-2314-4dd7-941c-621a02291862 | B12: 1 | D12: 1 | E12: 4 | F12: 1 | G12: 1 | H12: 1 | I12: 1 | J12: 1 | K12: 1 | L12: 1 | N12: 1 | O12: 1
A13: 0182d9d5-feed-4a24-923f-61dc8d9c3415 | B13: 1 | D13: 182 | F13: 1 | G13: 1 | H13: 1 | I13: 1 | J13: 1 | K13: 1 | L13: 1 | N13: 1 | O13: 1
A14: 0184f91a-5333-474a-9e0b-0e56b2e8ebfb | B14: 1 | D14: 6 | E14: 1 | F14: 1 | G14: 1 | H14: 1 | I14: 1 | J14: 1 | K14: 1 | L14: 1 | N14: 1 | O14: 1
A15: 019358c2-cb87-4d2a-bf89-5993e6417355 | B15: 1 | D15: 5 | F15: 1 | G15: 1 | H15: 1 | I15: 1 | J15: 1 | K15: 1 | L15: 1 | N15: 1 | O15: 1
A16: 019a09f2-5aad-4f3b-a766-ee4243311f62 | B16: 1 | D16: 6 | F16: 1 | G16: 1 | H16: 1 | I16: 1 | J16: 1 | K16: 1 | L16: 1 | N16: 1 | O16: 1
A17: 01a1cea8-20ea-49e5-83ae-6ea012713dae | C17: 1 | D17: 1 | F17: 1 | G17: 1 | H17: 1 | I17: 1 | J17: 1 | K17: 1 | L17: 1 | M17: 1 | N17: 1 | O17: 1
A18: 01a83a6c-2a26-45a0-a6ab-55d69fcfc7fb | B18: 1 | C18: 1 | D18: 1 | F18: 1 | G18: 1 | N18: 1 | O18: 1
A19: 01b9ca64-24e6-422b-9bf0-7c7a2a031ac4 | B19: 1 | D19: 1 | F19: 1 | G19: 1 | H19: 1 | I19: 1 | J19: 1 | K19: 1 | L19: 1 | N19: 1 | O19: 1
A20: 01d071c7-3289-453c-af1c-e229dcf0a96e | E20: 5
A21: 01eb9fe3-45cc-4820-89f3-f77aafe0d70d | C21: 1 | D21: 1 | E21: 1 | F21: 1 | G21: 1 | H21: 1 | I21: 1 | J21: 1 | K21: 1 | L21: 1 | M21: 1 | N21: 1 | O21: 1
A22: 01f6fe59-7dfc-4b1e-9cd4-89f189746294 | B22: 1 | D22: 1 | F22: 1 | G22: 1 | H22: 1 | I22: 1 | J22: 1 | K22: 1 | N22: 1 | O22: 1
A23: 02001255-77c6-4d7c-9323-7c2dd9ec3ee7 | B23: 1 | D23: 2 | F23: 1 | G23: 1 | H23: 1 | I23: 1 | J23: 1 | K23: 1 | L23: 1 | N23: 1 | O23: 1
A24: 0208b75c-2ac4-4b88-b826-0ddf797996a0 | B24: 1 | C24: 1 | D24: 5 | F24: 1 | G24: 1 | H24: 1 | I24: 1 | J24: 1 | K24: 1 | L24: 1 | N24: 1 | O24: 1
A25: 0212c815-4185-42f3-84af-ba12ad9cfbce | C25: 1 | D25: 1 | F25: 1 | G25: 1 | H25: 1 | I25: 1 | J25: 1 | K25: 1 | L25: 1 | M25: 1 | N25: 1 | O25: 1
A26: 022458f1-3d5f-42c1-acf8-ace24f5b35d3 | B26: 1 | C26: 1 | D26: 1 | G26: 1 | H26: 1 | I26: 1 | J26: 1 | K26: 1 | L26: 1 | M26: 1 | N26: 1 | O26: 1
A27: 022ba0c0-0e94-4111-ab5e-fcd2160f62f2 | B27: 1 | C27: 1 | D27: 1 | F27: 1 | G27: 1 | H27: 1 | M27: 1 | N27: 1 | O27: 1
A28: 023b5cb3-7489-40c7-b802-125dbc91ab2f | B28: 1 | C28: 1 | D28: 6 | F28: 1
A29: 023ba7b1-a1fd-4b15-b854-469741d8281a | B29: 1 | C29: 1 | D29: 1 | F29: 1 | G29: 1 | H29: 1 | I29: 1 | J29: 1 | K29: 1 | L29: 1 | N29: 1 | O29: 1
A30: 0246de9f-5e96-46db-aca5-5e23c1cfa765 | B30: 1 | D30: 1 | F30: 1 | G30: 1 | H30: 1 | I30: 1 | J30: 1 | K30: 1 | L30: 1 | N30: 1 | O30: 1
A31: 0248a31c-a176-4243-be88-974b9f5e9571 | B31: 1 | C31: 2 | D31: 1 | F31: 1 | G31: 1 | H31: 1 | I31: 1 | N31: 1 | O31: 1
A32: 0280fa18-04ed-49e2-8c3a-246d30af6261 | E32: 5
A33: 0293ad30-78fe-4d59-bc40-89ed8ffd6013 | B33: 1 | C33: 1 | D33: 1 | F33: 1 | G33: 1 | H33: 1 | I33: 1 | J33: 1 | K33: 1 | N33: 1 | O33: 1
A34: 029eab72-ef30-4342-be7e-a3750f06ba8e | B34: 1 | D34: 1 | F34: 1 | G34: 1 | H34: 1 | I34: 1 | J34: 1 | K34: 1 | L34: 1 | N34: 1 | O34: 1
A35: 02c20063-ecb8-4d8a-a548-d0171e4cb426 | B35: 1 | C35: 1 | D35: 1 | F35: 1 | N35: 1
A36: 02d56640-005c-4a85-a049-122c29e7b0a7 | B36: 1 | C36: 1 | D36: 5 | F36: 1 | G36: 1 | H36: 1 | N36: 1 | O36: 1
A37: 02d7fdc2-eec0-4514-b0cf-b0b9d06c08b7 | B37: 1 | D37: 5 | E37: 1 | F37: 1 | G37: 1 | H37: 1 | I37: 1 | J37: 1 | K37: 1 | N37: 1 | O37: 1
A38: 02f72647-7594-4e6a-8bf0-47c05dc0998d | C38: 1 | D38: 1 | F38: 1 | G38: 1 | H38: 1 | I38: 1 | J38: 1 | K38: 1 | L38: 1 | M38: 1 | N38: 1 | O38: 1
A39: 02f7c14c-d5ab-4f6a-9607-7025d83d4e21 | E39: 4 | L39: 1
A40: 030e6d82-9a8a-4548-b31e-33ce98769a9f | B40: 1 | C40: 1 | D40: 1 | F40: 1 | G40: 1 | H40: 1 | M40: 1 | N40: 1 | O40: 1
A41: 03471aa3-242a-43ed-ae7f-f6ee631121b7 | B41: 1 | C41: 1 | D41: 1 | F41: 1 | M41: 1
A42: 034cb11e-0029-4162-98b4-011d00cd8439 | B42: 1 | C42: 1 | D42: 1 | G42: 1 | H42: 1 | I42: 1 | J42: 1 | K42: 1 | L42: 1 | M42: 1 | N42: 1 | O42: 1
A43: 03671c74-7082-43c0-bcf7-fefdb227eaac | B43: 1 | C43: 1 | D43: 9 | G43: 1 | H43: 1 | I43: 1 | J43: 1 | K43: 1 | L43: 1 | M43: 1 | N43: 1 | O43: 1
A44: 036c9136-e356-46ec-93cf-cbe40258ebfd | B44: 1 | C44: 1 | D44: 1 | G44: 1 | H44: 1 | I44: 1 | J44: 1 | K44: 1 | L44: 1 | M44: 1 | N44: 1 | O44: 1
A45: 0387da3b-a92a-4a1a-92f5-4776f47ac436 | B45: 1 | D45: 1 | F45: 1 | G45: 1 | H45: 1 | I45: 1 | J45: 1 | K45: 1 | L45: 1 | N45: 1 | O45: 1
A46: 03af49fe-da09-450c-a169-7e7d425a49d3 | D46: 1 | E46: 2 | J46: 1 | K46: 1 | L46: 1
A47: 03d8ec4c-5614-4c4c-a3dd-6086ff680fc7 | B47: 1 | C47: 1 | D47: 1 | F47: 1 | G47: 1 | H47: 1 | I47: 1 | J47: 1 | K47: 1 | L47: 1 | N47: 1 | O47: 1
